Workbook

Sheet Responsables empresas
A1: PÁGINA PARA DEFINIR QUE PERSONAS AGREGAN Y EDITAN LOS DATOS POR EMPRESA Y QUE PERSONAS REVISAN ESTOS DATOS
A2: *POR FAVOR SOLO LAS PERSONAS CON BUEN DOMINIO DE EXCEL TOMEN EL ROL DE EDITORES (ASI EVITAREMOS MUCHOS ERRORES)
B5: EMPRESA | C5: Empresa | D5: ¿Quién EDITA LOS DATOS DE LA EMPRESA? | E5: ESTADO DE LLENADO? Indicar Trimetre y Año de datos (ejemplo: Q4-2025) | F5: Contacto EDITOR | G5: Comentario EDITOR | H5: ¿Quién REVISA LOS DATOS DE LA EMPRESA? | I5: Contacto EDITOR | J5: Comentario Revisor
A6: TOMAR ESTA HOJA COMO REFERENCIA PARA LLENAR DATOS | B6: EMBOTELLADORA | C6: ANDINA A | D6: Victor Araya | E6: Q4-2025 | F6: 952254143
B7: EMBOTELLADORA | C7: ANDINA B | D7: Victor Araya | E7: Q4-2025
B8: ELÉCTRICAS | C8: COLBUN | D8: Victor Araya | E8: Q4-2025
B9: BANCO | C9: BANCO CHILE | D9: Van Olivares | E9: Q4-2025 | F9: volivaresh@outlook.com | G9: Listo
B10: ELÉCTRICAS | C10: PEHUENCHE | D10: Victor Jofré | E10: NO COMPLETADO
B11: EMBOTELLADORA | C11: EMBONOR B | D11: Victor Jofré | E11: Q4-2025
B12: EMBOTELLADORA | C12: EMBONOR A | D12: Victor Jofré | E12: NO COMPLETADO
B13: AFP | C13: HABITAT | E13: NO COMPLETADO
B14: GAS | C14: LIPIGAS | E14: NO COMPLETADO
B15: AFP | C15: AAISA | E15: NO COMPLETADO
B16: CONCESIÓN | C16: ZOFRI | E16: NO COMPLETADO
B17: HOLDING | C17: QUIÑENCO | D17: Manuel González | E17: Q4-2025 | F17: (+56)941389809
B18: INMOBILIARIO | C18: CENCOMALLS | D18: Manuel González | E18: Q4-2025
B19: ELÉCTRICAS | C19: ENELGXCH | E19: NO COMPLETADO
B20: AFP | C20: PROVIDA | D20: Alvaro De la Quintana | E20: Q4-2025
B21: AFP | C21: PLANVITAL | D21: Alvaro De la Quintana | E21: Q4-2024
B22: AFP | C22: CUPRUM | D22: Alvaro De la Quintana | E22: Q4-2025
B23: AFP | C23: AFPCAPITAL | D23: Alvaro De la Quintana | E23: Q4-2024
B24: ELÉCTRICAS | C24: CGE | D24: Manuel González | E24: Q4-2025
B25: ELÉCTRICAS | C25: EDELMAG | E25: NO COMPLETADO
B26: GAS | C26: NTGCLGAS | E26: NO COMPLETADO
B27: GAS | C27: GASCO | D27: Alvaro De la Quintana | E27: Q4-2025
B28: EMBOTELLADORA | C28: CCU | D28: Jean Herrera | E28: Q4-2025
B29: ELÉCTRICAS | C29: ENELCHILE | D29: Jean Herrera | E29: Q4-2024
B30: BANCO | C30: SANTANDER | D30: Manuel González | E30: Q4-2025 | F30: (+56)941389809
B31: SUPERMERCADOS | C31: SMU | D31: Manuel González | E31: Q4-2025 | F31: (+56)941389809
B32: INMOBILIARIO | C32: PARAUCO | D32: Alvaro De la Quintana | E32: Q4-2025
B33: INMOBILIARIO | C33: MALLPLAZA | D33: Alvaro De la Quintana | E33: Q4-2025
B34: FERTILIZANTES | C34: SOQUICOM | D34: Gian Carlo Giuliano | E34: Q1-2025 | F34: (+56)998724806
B35: ELÉCTRICAS | C35: TRICAHUE | E35: NO COMPLETADO | F35: jpg139@gmail.com
B36: FINANCIERA | C36: NUAM | D36: Edo Otero | E36: Q4-2025 | F36: eoterovtmt@gmail.com
B37: HOLDING | C37: ILC | E37: NO COMPLETADO
C38: CFINRENTAS | D38: Diego Muñoz C | E38: Por crear
D46: {=_xlfn.UNIQUE(D7:D38)} -> Victor Araya
D47: Van Olivares
D48: Victor Jofré
D49: 0
D50: Manuel González
D51: Alvaro De la Quintana
D52: Jean Herrera
D53: Gian Carlo Giuliano
D54: Edo Otero
D55: Diego Muñoz C

Sheet Cuidados a tener en la planilla
B2: POR FAVOR TOMAR EN CUENTA ESTAS INDICACIONES ANTES DE EDITAR LAS EMPRESAS
B4: Por favor solo las personas que se sientan bien capacitadas en Excel tomen el rol de "editores" de las hojas. Las demás solo contribuyan revisando, pero no editando. En conjunto haremos que esto funcione.
B5: Se deben llenar los dividendos "año calendario" y los dividendos "año utilidad" según se indica en hoja "Como llenar dividendos". Esto es LA PARTE PRINCIPAL Y MÁS DIFÍCIL.
B6: En toda empresa se debe agregar el concepto "PRECIO" en alguna fila de la columna B asociada al año 2017 (y no en otro año). Este precio debe apuntar al precio al cual cotiza la empresa. CLAVE QUE FUNCIONE
B7: No cambiar el nombre de las hojas a las empresas que ya están listas en Power BI. Si la hoja se llama Andina A, dejar tal como está.
B8: La columna A de todas las empresas debe estar vacía (debe existir, pero en blanco sin datos)
B9: Cuando agregues datos de una nueva empresa que no esté en Power BI, debes ir a hoja "Empresas Power BI" y llenar sus datos (usa el mismo nombre de hoja de empresa). LUEGO AVÍSAME PARA INCLUIRLA
B10: La columna B (únicamente) debe tener los conceptos a usar (activos corrientes, Cuentas por cobrar, etc). Deben tener exactamente los mismos nombres en todas las empresas.
B11: Tomar ANDINA-A como referencia de los conceptos. Es decir, estos son los nombres que se usarán en Power BI y que deben ser iguales en todas las empresas donde aplique.
B12: No importa si un mismo concepto en una empresa se encuentra fila 5 y en otra se encuentra en fila 20 (solo importa que estén en columna B y que tengan EXACTAMENTE el mismo nombre)
B13: Power BI solo está usando los conceptos que ven en ese reporte. Más adelante podremos incluir más cosas que crean relevantes.
B14: Power BI distingue entre mayúsculas, minúsculas, espacios, saltos de líneas, etc. Los nombres a usar en todas las empresas deben ser EXACTAMENTE iguales y UBICADOS EN LA MISMA COLUMNA B.
... B23: Cualquier duda la pueden escribir aquí mismo.

Sheet Actualización de POWER BI
B1: Actualización Power BI
B3: Enlace a reporte (público): | C3: https://app.powerbi.com/view?r=eyJrIjoiZDNmYTQ1YjYtZGJmOS00MWUwLTg1Y2QtNGMyNTZkMjEyNTkxIiwidCI6IjYxZWJjMzI1LWFlNTAtNDhmZC1iOTdmLTk5ZDI3N2RmMjg3NCIsImMiOjR9
B5: Frecuencia de actualización (AM):
B6: 8:30, 9, 9:30, 10, 10:30, 11, 11:30 y 12 hrs todos los días (consideren un delay de 30 minutos, aunque en general es menos)
B7: El reporte se actualizará solo en estos horarios y tomará lo que vea en este Excel en ese momento.
B9: Abrir Excel 1 vez por día al menos para reflejar cambio de precios (solo basta 1 vez, ejecutado por cualquier persona).
B10: Dado que los precios de las acciones solo cambian cuando se abre el Excel, es necesario por ahora que cualquier persona abra el Excel en la mañana.
B11: Cuando tenga tiempo pienso mejorar esto, de forma que el archivo se abra y se cierre solo.
B12: Debe haber algo mejor, así que por favor cualquier idea de mejora vamos compartiendo!

Sheet Como llenar dividendos
B2: En todas las hojas debemos llenar 2 tipos de dividendos, GRUPO 1 y GRUPO 2 (ver ANDINA-A como referencia) | D2: EJEMPLO ANDINA-A CON DATOS EN FOTO (MISMOS DIVIDENDOS, PERO ASOCIADOS A AÑOS DISTINTOS). SE LLENAN AMBOS TIPOS.
B3: GRUPO 1: Los dividendos se deben dejar en la columna del año en el cual se reparten (año calendario). Es el más simple de llenar.
B4: GRUPO 2: Los dividendos se deben dejar en la columna del año al cual corresponde realmente la utilidad (año fiscal). Es el más difícil de llenar.
O6: Año 2025
B7: LOS NOMBRES QUE SE DEBEN USAR EN CADA HOJA DE EMPRESA SON: | F7: Utilidad 2024
O8: Año 2024
B9: Dividendos calendario
B10: Dividendos sin eventual Calendario | F10: Utilidad 2023
B11: Definitivo año calendario
B12: Provisorio calendario
B13: Adicional calendario
B14: Eventual calendario | D14: Pueden revisar los fórmulas para que vean como se van asociando los dividendos al año correcto, según año calendario o según año de utilidad (fiscal)
B15: Dividendos | E15: 2023 | F15: 2024 | G15: 2025
B16: Dividendos sin eventual | D16: Dividendos calendario | E16: =SUM(E18:E21) -> 0 | F16: =SUM(F18:F21) -> 158 | G16: =SUM(G18:G21) -> 141
B17: Definitivo | D17: Dividendos sin eventual Calendario | E17: =SUM(E18:E20) -> 0 | F17: =SUM(F18:F20) -> 158 | G17: =SUM(G18:G20) -> 141
B18: Provisorio | D18: Definitivo año calendario | F18: =30+32+32 -> 94
B19: Adicional | D19: Provisorio calendario | F19: =32+32 -> 64 | G19: 141
B20: Eventual | D20: Adicional calendario
D21: Eventual calendario
B22: SE DEBEN USAR EXACTAMENTE ESTOS NOMBRES | D22: Dividendos | E22: =SUM(E24:E27) -> 94 | F22: =SUM(F24:F27) -> 205 | G22: =SUM(G24:G27) -> 0
B23: SI EN ALGUNA HOJA NO VEN ESTOS NOMBRES, SE DEBEN CREAR INSERTANDO FILAS | D23: Dividendos sin eventual | E23: =SUM(E24:E26) -> 94 | F23: =SUM(F24:F26) -> 205 | G23: =SUM(G24:G26) -> 0
B24: NO IMPORTA LA POSICIÓN DE LA FILA (PUEDEN ESTAR EN LAS ÚLTIMAS FILAS O ANTES, DA IGUAL) | D24: Definitivo | E24: =30+32+32 -> 94
B25: SI IMPORTA LA POSICIÓN DE LA COLUMNA (TODOS LOS CONCEPTOS VAN EN LA COLUMNA B) | D25: Provisorio | F25: =141+32+32 -> 205
B26: LOS COLORES NO IMPORTAN, SON SOLO PARA RESALTAR LA DIFERENCIA DE DIVIDENDO EN ESTA PÁGINA | D26: Adicional
D27: Eventual

Sheet Empresas Power BI
B1: NO MODIFICAR NOMBRE DE TABLA NI NOMBRE DE COLUMNAS
B2: AGREGAR FILAS CUANDO EXISTA UNA EMPRESA NUEVA QUE NO ESTÉ EN EL POWER BI
B4: Empresas | C4: Industria | D4: TIPO EMPPRESA
B5: CHILE | C5: BANCOS | D5: DGI
B6: COLBÚN | C6: ELÉCTRICAS | D6: DGI
B7: LIPIGAS | C7: GAS | D7: DGI
B8: CENCOMALLS | C8: INMOBILIARIO | D8: DGI
B9: ANDINA A | C9: EMBOTELLADORA | D9: DGI
B10: ANDINA B | C10: EMBOTELLADORA | D10: DGI
B11: EMBONOR A | C11: EMBOTELLADORA | D11: DGI
B12: EMBONOR B | C12: EMBOTELLADORA | D12: DGI
B13: QUINENCO | C13: HOLDING | D13: DGI
B14: ENELGXCH | C14: ELÉCTRICAS | D14: DGI
B15: CGE | C15: ELÉCTRICAS | D15: DGI
... B28: ZOFRI | C28: CONCESIÓN | D28: VACA LECHERA
B29: PROVIDA | C29: AFP | D29: VACA LECHERA | F29: No están completos estos datos TRICAHUE. Faltan dividendos "Utilidad" y no está en hoja Responsables
B30: PLANVITAL | C30: AFP | D30: VACA LECHERA
B31: CUPRUM | C31: AFP | D31: VACA LECHERA
B32: AFPCAPITAL | C32: AFP | D32: VACA LECHERA
B33: GASCO | C33: GAS | D33: VACA LECHERA
B34: TRICAHUE | C34: ELÉCTRICAS | D34: VACA LECHERA
B35: SOQUICOM | C35: FERTILIZANTES | D35: VACA LECHERA

Sheet EMPRESAS SELECCIONADAS (2)
B1: EMPRESA | C1: PEHUENCHE
B3: ¿BUENA EMPRESA?
B5: BALANCE
B6: KPI | C6: Criterio | D6: 2022 | E6: 2023 | F6: 2024 | G6: SEMAFORO
A7: =AVERAGE(D7:F7) -> 46092274000 | B7: Capital de Trabajo | C7: Positivo | D7: =IFERROR(PEHUENCHE!H29,"") -> 56284731000 | E7: =IFERROR(PEHUENCHE!I29,"") -> 40793989000 | F7: =IFERROR(PEHUENCHE!J29,"") -> 41198102000 | G7: =IF(SLOPE(D7:F7, $D$6:$F$6)>0, "Creciente", "Decreciente") -> Decreciente
A8: =AVERAGE(D8:F8) -> 1.7291904 | B8: Razón corriente | C8: Bueno: 1,5-2 | D8: =IFERROR(PEHUENCHE!H30,"") -> 1.5780628 | E8: =IFERROR(PEHUENCHE!I30,"") -> 1.809672 | F8: =IFERROR(PEHUENCHE!J30,"") -> 1.7998364 | G8: =IF(A8<1,"🔴",IF(AND(A8>=1.5,A8<=2), "🟢","🟡")) -> 🟢
A9: =AVERAGE(D9:F9) -> 1.7237744 | B9: Razón acida | C9: Bueno: 1-1,5 | D9: =IFERROR(PEHUENCHE!H31,"") -> 1.5754473 | E9: =IFERROR(PEHUENCHE!I31,"") -> 1.8015064 | F9: =IFERROR(PEHUENCHE!J31,"") -> 1.7943694 | G9: =IF(A9<1,"🔴",IF(AND(A9>=1,A9<=1.5), "🟢","🟡")) -> 🟡
A10: =AVERAGE(D10:F10) -> 0.37667865 | B10: Razón de endeudamiento | C10: Max 50% | D10: =IFERROR(PEHUENCHE!H32,"") -> 0.43705173 | E10: =IFERROR(PEHUENCHE!I32,"") -> 0.3515346 | F10: =IFERROR(PEHUENCHE!J32,"") -> 0.34144963 | G10: =IF(A10<40%,"🔴",IF(AND(A10>=40%,A10<=50%), "🟢","🟡")) -> 🔴
B12: EERR
B13: KPI | C13: Criterio | D13: 2022 | E13: 2023 | F13: 2024 | G13: SEMAFORO
B14: EBIT | C14: Creciente | D14: =IFERROR(PEHUENCHE!H35,"") -> 248835472000 | E14: =IFERROR(PEHUENCHE!I35,"") -> 194705044000 | F14: =IFERROR(PEHUENCHE!J35,"") -> 217595776000 | G14: =IF(SLOPE(D14:F14, $D$13:$F$13)>0, "Creciente", "Decreciente") -> Decreciente
B15: %MARGEN EBITDA | C15: Creciente | D15: =IFERROR(PEHUENCHE!H36,"") -> 0.91335228 | E15: =IFERROR(PEHUENCHE!I36,"") -> 0.89430275 | F15: =IFERROR(PEHUENCHE!J36,"") -> 0.87355741 | G15: =IF(SLOPE(D15:F15, $D$13:$F$13)>0, "Creciente", "Decreciente") -> Decreciente
B16: EPS | C16: Creciente | D16: =IFERROR(PEHUENCHE!H39,"") -> 305.1 | E16: =IFERROR(PEHUENCHE!I39,"") -> 241.02 | F16: =IFERROR(PEHUENCHE!J39,"") -> 264.12 | G16: =IF(SLOPE(D16:F16, $D$13:$F$13)>0, "Creciente", "Decreciente") -> Decreciente
B17: ROE | C17: Constante o > 15% | D17: =IFERROR(PEHUENCHE!H40,"") -> 1.0702614 | E17: =IFERROR(PEHUENCHE!I40,"") -> 0.92362252 | F17: =IFERROR(PEHUENCHE!J40,"") -> 0.97760982 | G17: =IF(AVERAGE(D17:F17)<15%,"🔴",IF(AND(AVERAGE(D17:F17)>=15%,AVERAGE(D17:F17)<=100%), "🟢","🟡")) -> 🟢
B19: FCF
B20: KPI | C20: Criterio | D20: 2022 | E20: 2023 | F20: 2024 | G20: SEMAFORO
B21: FCF Simplificado | C21: Creciente | D21: ='ANDINA A'!H43 -> 210750245000 | E21: ='ANDINA A'!I43 -> 174122738000 | F21: ='ANDINA A'!J43 -> 65700300000 | G21: =IF(SLOPE(D21:F21, $D$20:$F$20)>0, "Creciente", "Decreciente") -> Decreciente
B24: ¿BUEN PRECIO?
B26: TIPO EMPRESA | C26: DGI
B28: KPI | C28: 2022 | D28: 2023 | E28: 2024 | F28: PROMEDIO
B29: Dividendos | C29: =IFERROR(PEHUENCHE!H44,"") -> 203.678 | D29: =IFERROR(PEHUENCHE!I44,"") -> 311.995 | E29: =IFERROR(PEHUENCHE!J44,"") -> 251.33 | F29: =AVERAGE(C29:E29) -> 255.66767
B30: PAY OUT | C30: =IFERROR(PEHUENCHE!H55,"") -> 0.99998361 | D30: =IFERROR(PEHUENCHE!I55,"") -> 1.0000041 | E30: =IFERROR(PEHUENCHE!J55,"") -> 1.0000151 | F30: =AVERAGE(C30:E30) -> 1.000001
B31: ROE | C31: =IFERROR(PEHUENCHE!H40,"") -> 1.0702614 | D31: =IFERROR(PEHUENCHE!I40,"") -> 0.92362252 | E31: =IFERROR(PEHUENCHE!J40,"") -> 0.97760982 | F31: =AVERAGE(C31:E31) -> 0.99049791
B33: VALORIZACION POR DIVIDENDOS | E33: VALORIZACION "ME SIRVE"
B35: Dividendos Promedio 3 Ultimado años | C35: =+F29 -> 255.66767 | E35: Dividendos Promedio 3 Ultimado años | F35: =+F29 -> 255.66767
B36: PAY OUT Promedio 3 Ultimado años | C36: =+F30 -> 1.000001 | E36: PRECIO ACTUAL ACCION AL 22/FEB | F36: =C44 -> 2800
B37: % RETENCION | C37: =100%-C36 -> -9.6853167e-07 | E37: Rentabilidad por Dividendo | F37: =F35/F36 -> 0.091309881
B38: ROE Promedio 3 Ultimado años | C38: =+F31 -> 0.99049791
B39: G | C39: =IF((C38*C37)<0,0,(C38*C37)) -> 0
B40: TASA EXIGIDA % | C40: 0.1
B42: PRECIO MAXIMO | C42: =(C35*(1+C39)) /C40 -> 2556.6767
B44: PRECIO ACTUAL ACCION AL 22/FEB | C44: 2800 | D44: =IF(C44>C42,"Precio muy Alto","Compra Ahora") -> Precio muy Alto

Sheet EMPRESAS SELECCIONADAS
B1: EMPRESA | C1: ANDINA - A
B3: ¿BUENA EMPRESA?
B5: BALANCE
B6: KPI | C6: Criterio | D6: 2022 | E6: 2023 | F6: 2024 | G6: SEMAFORO
B7: Capital de Trabajo | C7: Positivo | D7: =+'ANDINA A'!H29 -> 212484258000 | E7: =+'ANDINA A'!I29 -> 288899731000 | F7: =+'ANDINA A'!J29 -> 107051746000
B8: Razón corriente | C8: Bueno: 1,5-2 | D8: =+'ANDINA A'!H30 -> 1.2238455 | E8: =+'ANDINA A'!I30 -> 1.4169602 | F8: =+'ANDINA A'!J30 -> 1.1181399
B9: Razón acida | C9: Bueno: 1-1,5 | D9: ='ANDINA A'!H31 -> 0.96481162 | E9: ='ANDINA A'!I31 -> 1.0806017 | F9: ='ANDINA A'!J31 -> 0.78709878
B10: Razón de endeudamiento | C10: Max 50% | D10: ='ANDINA A'!H32 -> 0.70657904 | E10: ='ANDINA A'!I32 -> 0.68475823 | F10: ='ANDINA A'!J32 -> 0.69177609
B12: EERR
B13: KPI | C13: Criterio | D13: 2022 | E13: 2023 | F13: 2024 | G13: SEMAFORO
B14: EBITDA | C14: Creciente | D14: ='ANDINA A'!H36 -> 321771470000 | E14: ='ANDINA A'!I36 -> 316296892000 | F14: ='ANDINA A'!J36 -> 411911208000
B15: %MARGEN EBITDA | C15: Creciente | D15: =+'ANDINA A'!H37 -> 0.12110884 | E15: =+'ANDINA A'!I37 -> 0.12079606 | F15: =+'ANDINA A'!J37 -> 0.12775479
B16: EPS | C16: Creciente | D16: ='ANDINA A'!H40 -> 126.27 | E16: ='ANDINA A'!I40 -> 172.49 | F16: ='ANDINA A'!J40 -> 234.09
B17: ROE | C17: Constante o > 15% | D17: ='ANDINA A'!H41 -> 0.15019873 | E17: ='ANDINA A'!I41 -> 0.196901 | F17: ='ANDINA A'!J41 -> 0.24031331
B19: FCF
B20: KPI | C20: Criterio | D20: 2022 | E20: 2023 | F20: 2024 | G20: SEMAFORO
B21: FCF Simplificado | C21: Creciente | D21: ='ANDINA A'!H43 -> 210750245000 | E21: ='ANDINA A'!I43 -> 174122738000 | F21: ='ANDINA A'!J43 -> 65700300000
B24: ¿BUEN PRECIO?
B26: TIPO EMPRESA | C26: DGI
B28: KPI | C28: 2022 | D28: 2023 | E28: 2024 | F28: PROMEDIO
B29: Dividendos | C29: ='ANDINA A'!H44 -> 276 | D29: ='ANDINA A'!I44 -> 166 | E29: ='ANDINA A'!J44 -> 158 | F29: =AVERAGE(C29:E29) -> 200 | G29: ? incluye eventuales??
B30: PAY OUT | C30: ='ANDINA A'!H56 -> 0.91866635 | D30: ='ANDINA A'!I56 -> 0.8812105 | E30: ='ANDINA A'!J56 -> 0.87573156 | F30: =AVERAGE(C30:E30) -> 0.89186947
B31: ROE | C31: ='ANDINA A'!H41 -> 0.15019873 | D31: ='ANDINA A'!I41 -> 0.196901 | E31: ='ANDINA A'!J41 -> 0.24031331 | F31: =AVERAGE(C31:E31) -> 0.19580435
B33: VALORIZACION POR DIVIDENDOS | E33: VALORIZACION "ME SIRVE"
B35: Dividendos Promedio 3 Ultimado años | C35: =+F29 -> 200 | E35: Dividendos Promedio 3 Ultimado años | F35: =+F29 -> 200
B36: PAY OUT Promedio 3 Ultimado años | C36: =+F30 -> 0.89186947 | E36: PRECIO ACTUAL ACCION AL 22/FEB | F36: 2406.8
B37: % RETENCION | C37: =100%-C36 -> 0.10813053 | E37: Rentabilidad por Dividendo | F37: =F35/F36 -> 0.083097889
B38: ROE Promedio 3 Ultimado años | C38: =+F31 -> 0.19580435
B39: G | C39: =IF((C38*C37)<0,0,(C38*C37)) -> 0.021172428
B40: TASA EXIGIDA % | C40: 0.07
B42: PRECIO MAXIMO | C42: =(C35*(1+C39)) /C40 -> 2917.6355
B44: PRECIO ACTUAL ACCION AL 22/FEB | C44: 2406.8

Sheet INDICE
H1: =+CGE!C42 -> 0.013524965
F2: MANUAL | H2: =+FOSFOROS!C42 -> 0.02082139 | Q2: DIVIDENDOS SIN ADIC/EVENTUALES | V2: DIVIDENDOS TOTALES
B3: LISTADO EMPRESAS DIVIDENDERAS | H3: =+ENELAM!C45 -> 0.037970316 | Q3: RENT ESPERADA | R3: 0.07 | V3: RENT ESPERADA | W3: 0.08
B4: CANTIDAD | C4: EMPRESA | D4: INDUSTRIA | F4: PRECIO DE CIERRE | H4: =+GASCO!C42 -> 0.042946098 | K4: G | M4: PAYOUT | O4: DY | Q4: PRECIO MAX A CONSIDERAR | T4: Ret Est Precio Cierre | V4: PRECIO MAX A CONSIDERAR | Y4: Ret Est Precio Cierre
B5: 22 | C5: ANDINA-A | D5: EMBOTELLADORA | F5: =+'ANDINA A'!B3 -> 3475 | H5: =+MANQUEHUE!C42 -> 0.052257279 | K5: =+'ANDINA A'!C61 -> 0.02519583 | M5: =+'ANDINA A'!C57 -> 0.89186947 | O5: =+'ANDINA A'!C57 -> 0.89186947 | Q5: =+'ANDINA A'!D3/INDICE!$R$3 -> 2238.0952 | S5: =IF(F5<Q5,"considerar","esperar") -> esperar | T5: =+'ANDINA A'!D3/INDICE!F5 -> 0.045083933 | V5: =+'ANDINA A'!E3/INDICE!$W$3 -> 2500 | X5: =IF(F5<V5,"considerar","esperar") -> esperar | Y5: =+'ANDINA A'!E3/INDICE!F5 -> 0.057553957 | AA5: =F9/R3 -> 179500
B6: 2 | C6: PROVIDA | D6: AFP | F6: =+PROVIDA!B3 -> 5000 | H6: =+NTGCLGAS!C44 -> 0.065494433 | K6: =+PROVIDA!C64 -> 0.0078442042 | M6: =+PROVIDA!C60 -> 0.93285353 | O6: =+PROVIDA!C62 -> 0.13339977 | Q6: =+PROVIDA!D3/INDICE!$R$3 -> 4916.6667 | S6: =IF(F6<Q6,"considerar","esperar") -> esperar | T6: =+PROVIDA!D3/INDICE!F6 -> 0.068833333 | V6: =+PROVIDA!E3/INDICE!$W$3 -> 4927.0833 | X6: =IF(F6<V6,"considerar","esperar") -> esperar | Y6: =+PROVIDA!E3/INDICE!F6 -> 0.078833333
B7: 15 | C7: COLBUN | D7: ELÉCTRICAS | F7: =+COLBÚN!B3 -> 127.23 | H7: =+SONDA!C42 -> 0.068190047 | K7: =+COLBÚN!C63 -> 0.060522633 | M7: =+COLBÚN!C59 -> 0.59920595 | O7: =+COLBÚN!C61 -> 0.33310742 | Q7: =+COLBÚN!D3/INDICE!$R$3 -> 139.88571 | S7: =IF(F7<Q7,"considerar","esperar") -> considerar | T7: =+COLBÚN!D3/INDICE!F7 -> 0.07696298 | V7: =+COLBÚN!E3/INDICE!$W$3 -> 122.4 | X7: =IF(F7<V7,"considerar","esperar") -> esperar | Y7: =+COLBÚN!E3/INDICE!F7 -> 0.07696298
B8: 3 | C8: PLANVITAL | D8: AFP | F8: =+PLANVITAL!B3 -> 282 | H8: =+'SALFACORP (TIKR)'!C42 -> 0.068789745 | K8: =PLANVITAL!C65 -> 0.2448118 | M8: =+PLANVITAL!C61 -> 0.47082548 | O8: =+PLANVITAL!C63 -> 0.25899326 | Q8: =+PLANVITAL!D3/INDICE!$R$3 -> 137.08095 | S8: =IF(F8<Q8,"considerar","esperar") -> esperar | T8: =+PLANVITAL!D3/INDICE!F7 -> 0.075419843 | V8: =+PLANVITAL!E3/INDICE!$W$3 -> 163.19583 | X8: =IF(F8<V8,"considerar","esperar") -> esperar | Y8: =+PLANVITAL!E3/INDICE!F8 -> 0.04629669
B9: 41 | C9: MINERA VALPARAISO | D9: HOLDING | F9: =+MINERA!B3 -> 12565 | H9: =+IAM!C42 -> 0.073837133 | K9: =+MINERA!C59 -> 0.038926328 | M9: =+MINERA!C55 -> 0.64848843 | O9: =+MINERA!C57 -> 0.24299225 | Q9: =MINERA!D3/INDICE!$R$3 -> 22152.081 | S9: =IF(F9<Q9,"considerar","esperar") -> considerar | T9: =MINERA!D3/INDICE!F9 -> 0.12340992 | V9: =MINERA!E3/INDICE!$W$3 -> 37987.238 | X9: =IF(F9<V9,"considerar","esperar") -> considerar | Y9: =MINERA!E3/INDICE!F9 -> 0.24186064
B10: 4 | C10: CUPRUM | D10: AFP | F10: =+CUPRUM!B3 -> 136.87 | H10: =+'EISA (TIKR)'!C42 -> 0.077143735 | K10: =+CUPRUM!C64 -> 0.029484641 | M10: =+CUPRUM!C60 -> 0.81353543 | O10: =+CUPRUM!C62 -> 0.18028205 | Q10: =+CUPRUM!D3/INDICE!$R$3 -> 72.642857 | S10: =IF(F10<Q10,"considerar","esperar") -> esperar | T10: =+CUPRUM!D3/INDICE!F10 -> 0.037152042 | V10: =+CUPRUM!E3/INDICE!$W$3 -> 63.5625 | X10: =IF(F10<V10,"considerar","esperar") -> esperar | Y10: =+CUPRUM!E3/INDICE!F10 -> 0.037152042
B11: 1 | C11: HABITAT | D11: AFP | F11: =+HABITAT!B3 -> 1412 | H11: =+ELECMETAL!C42 -> 0.082637849 | K11: =+HABITAT!C65 -> 0.11925541 | M11: =+HABITAT!C61 -> 0.87767228 | O11: =+HABITAT!C63 -> 0.17112404 | Q11: =+HABITAT!D3/INDICE!$R$3 -> 1657.1429 | S11: =IF(F11<Q11,"considerar","esperar") -> considerar | T11: =+HABITAT!D3/INDICE!F11 -> 0.082152975 | V11: =+HABITAT!E3/INDICE!$W$3 -> 1450 | X11: =IF(F11<V11,"considerar","esperar") -> considerar | Y11: =+HABITAT!E3/INDICE!F11 -> 0.082152975
B12: 34 | C12: ENTEL | D12: TELECOMUNICACIONES | F12: =+ENTEL!B3 -> 3756 | H12: =+MOLYMET!C46 -> 0.085536314 | K12: =+ENTEL!C55 -> 0.065281794 | M12: =+ENTEL!C51 -> 0.61392432 | O12: =+ENTEL!C53 -> 0.24783216 | Q12: f | S12: =IF(F12<Q12,"considerar","esperar") -> considerar | T12: =+ENTEL!D3/INDICE!F12 -> 0.089013135 | V12: =+ENTEL!E3/INDICE!$W$3 -> 9054.1667 | X12: =IF(F12<V12,"considerar","esperar") -> considerar | Y12: =+ENTEL!E3/INDICE!F12 -> 0.192847
B13: 13 | C13: PEHUENCHE | D13: ELÉCTRICAS | F13: =+PEHUENCHE!B3 -> 2719.9 | H13: =+CMPC!C46 -> 0.086055536 | K13: =+PEHUENCHE!C60 -> 7.3766171e-06 | M13: =+PEHUENCHE!C56 -> 0.99999203 | O13: =+PEHUENCHE!C58 -> 0.16072435 | Q13: =+PEHUENCHE!D3/INDICE!$R$3 -> 3652.3952 | S13: =IF(F13<Q13,"considerar","esperar") -> considerar | T13: =+PEHUENCHE!D3/INDICE!F13 -> 0.093998922 | V13: =+PEHUENCHE!E3/INDICE!$W$3 -> 2796.0458 | X13: =IF(F13<V13,"considerar","esperar") -> considerar | Y13: =+PEHUENCHE!E3/INDICE!F13 -> 0.082239666
B14: 31 | C14: QUINENCO | D14: HOLDING | F14: =+QUINENCO!B3 -> 4290 | H14: =+'CAP (TIKR)'!C45 -> 0.092288715 | K14: =+QUINENCO!C63 -> 0.11670464 | M14: =+QUINENCO!C59 -> 0.54782351 | O14: =+QUINENCO!C61 -> 0.14017128 | Q14: =+QUINENCO!D3/INDICE!$R$3 -> 4876.3286 | S14: =IF(F14<Q14,"considerar","esperar") -> considerar | T14: =+QUINENCO!D3/INDICE!F14 -> 0.079567133 | V14: =+QUINENCO!E3/INDICE!$W$3 -> 5632.4833 | X14: =IF(F14<V14,"considerar","esperar") -> considerar | Y14: =+QUINENCO!E3/INDICE!F14 -> 0.10503465
B15: 28 | C15: SOQUICOM | D15: FERTILIZANTES | F15: =+SOQUICOM!B3 -> 379 | H15: =+'BESALCO (TIKR)'!C42 -> 0.096985097 | K15: =+SOQUICOM!C79 -> -5.4531897e-06 | M15: =+SOQUICOM!C75 -> 1.0000339 | O15: =+SOQUICOM!C77 -> 0.12801361 | Q15: =+SOQUICOM!D3/INDICE!$R$3 -> 539.89482 | S15: =IF(F15<Q15,"considerar","esperar") -> considerar | T15: =+SOQUICOM!D3/INDICE!F15 -> 0.099716721 | V15: =+SOQUICOM!E3/INDICE!$W$3 -> 472.40796 | X15: =IF(F15<V15,"considerar","esperar") -> considerar | Y15: =+SOQUICOM!E3/INDICE!F15 -> 0.099716721
B16: 14 | C16: TRICAHUE | D16: ELÉCTRICAS | F16: =+TRICAHUE!B3 -> 1480 | H16: =+ANASAC!C41 -> 0.099081064 | K16: =+TRICAHUE!C61 -> 0.13353851 | M16: =+TRICAHUE!C57 -> 0.98374796 | O16: =+TRICAHUE!C59 -> 0.13568046 | Q16: =+TRICAHUE!D3/INDICE!$R$3 -> 1263.2667 | S16: =IF(F16<Q16,"considerar","esperar") -> esperar | T16: =+TRICAHUE!D3/INDICE!F16 -> 0.059749099 | V16: =+TRICAHUE!E3/INDICE!$W$3 -> 1201.6821 | X16: =IF(F16<V16,"considerar","esperar") -> esperar | Y16: =+TRICAHUE!E3/INDICE!F16 -> 0.064955788
B17: 24 | C17: EMBONOR-A | D17: EMBOTELLADORA | F17: ='EMBONOR A'!B3 -> 1401 | H17: =+PROVIDA!C45 -> 0.1113963 | K17: =+'EMBONOR A'!C61 -> 0.090134722 | M17: =+'EMBONOR A'!C57 -> 0.49741452 | O17: =+'EMBONOR A'!C59 -> 0.1203331 | Q17: =+'EMBONOR A'!D3/INDICE!$R$3 -> 717.69771 | S17: =IF(F17<Q17,"considerar","esperar") -> esperar | T17: =+'EMBONOR A'!D3/INDICE!F17 -> 0.035859272 | V17: =+'EMBONOR A'!E3/INDICE!$W$3 -> 1281.7437 | X17: =IF(F17<V17,"considerar","esperar") -> esperar | Y17: =+'EMBONOR A'!E3/INDICE!F17 -> 0.073190217
B18: 36 | C18: SMU | D18: SUPERMERCADOS | F18: =+SMU!B3 -> 130.83 | H18: =+ITAU!C24 -> 0.102933 | K18: =+SMU!C61 -> 0.023285568 | M18: =+SMU!C57 -> 0.70945222 | O18: =+SMU!C59 -> 0.060254467 | Q18: =+SMU!D3/INDICE!$R$3 -> 136.67943 | S18: =IF(F18<Q18,"considerar","esperar") -> considerar | T18: =+SMU!D3/INDICE!F18 -> 0.07312971 | V18: =+SMU!E3/INDICE!$W$3 -> 119.5945 | X18: =IF(F18<V18,"considerar","esperar") -> esperar | Y18: =+SMU!E3/INDICE!F18 -> 0.07312971
B19: 32 | C19: ILC | D19: HOLDING | F19: =+ILC!B3 -> 19999 | H19: =+ENLASA!C46 -> 0.1079164 | K19: =+ILC!C63 -> 0.099300819 | M19: =+ILC!C59 -> 0.35524406 | O19: =+ILC!C61 -> 0.10637525 | Q19: =+ILC!D3/INDICE!$R$3 -> 6333.2033 | S19: =IF(F19<Q19,"considerar","esperar") -> esperar | T19: =+ILC!D3/INDICE!F19 -> 0.02216732 | V19: =+ILC!E3/INDICE!$W$3 -> 5541.5529 | X19: =IF(F19<V19,"considerar","esperar") -> esperar | Y19: =+ILC!E3/INDICE!F19 -> 0.02216732
B20: 35 | C20: OXIQUIM | D20: INDUSTRIAL | F20: 12000 | H20: =+CCU!C42 -> 0.10962882 | K20: =+OXIQUIM!C57 -> 0.11351219 | M20: =+OXIQUIM!C53 -> 0.55696026 | O20: =+OXIQUIM!C55 -> 0.10158454 | Q20: =+OXIQUIM!D3/INDICE!$R$3 -> 8414.2857 | S20: =IF(F20<Q20,"considerar","esperar") -> esperar | T20: =+OXIQUIM!D3/INDICE!F20 -> 0.049083333 | V20: =+OXIQUIM!E3/INDICE!$W$3 -> 8200 | X20: =IF(F20<V20,"considerar","esperar") -> esperar | Y20: =+OXIQUIM!E3/INDICE!F20 -> 0.054666667
B21: 12 | C21: ZOFRI | D21: CONCESIÓN | F21: =+ZOFRI!B3 -> 1004.3 | H21: =+CONCHATORO!C42 -> 0.11030719 | K21: =+ZOFRI!C61 -> 0.040930351 | M21: =+ZOFRI!C57 -> 0.86664405 | O21: =+ZOFRI!C59 -> 0.097503903 | Q21: =+ZOFRI!D3/INDICE!$R$3 -> 946.3 | S21: =IF(F21<Q21,"considerar","esperar") -> esperar | T21: =+ZOFRI!D3/INDICE!F21 -> 0.065957383 | V21: =+ZOFRI!E3/INDICE!$W$3 -> 828.0125 | X21: =IF(F21<V21,"considerar","esperar") -> esperar | Y21: =+ZOFRI!E3/INDICE!F21 -> 0.065957383
B22: 5 | C22: AFPCAPITAL | D22: AFP | F22: =+AFPCAPITAL!B3 -> 272.25 | H22: =+CUPRUM!C45 -> 0.13499339 | K22: =+AFPCAPITAL!C64 -> 0.11298945 | M22: =+AFPCAPITAL!C60 -> 0.80625394 | O22: =+AFPCAPITAL!C62 -> 0.097456151 | Q22: =+CUPRUM!D3/INDICE!$R$3 -> 72.642857 | S22: =IF(F22<Q22,"considerar","esperar") -> esperar | T22: =AFPCAPITAL!D3/INDICE!F22 -> 0.066010407 | V22: =AFPCAPITAL!E3/INDICE!$W$3 -> 291.33333 | X22: =IF(F22<V22,"considerar","esperar") -> considerar | Y22: =AFPCAPITAL!E3/INDICE!F22 -> 0.085607591
B23: 20 | C23: LIPIGAS | D23: GAS | F23: =+LIPIGAS!B3 -> 8145.9 | H23: =+MINERA!C46 -> 0.11849851 | K23: =+LIPIGAS!C61 -> 0.054783521 | M23: =+LIPIGAS!C57 -> 0.77392457 | O23: =+LIPIGAS!C59 -> 0.095437374 | Q23: =+LIPIGAS!D3/INDICE!R3 -> 4357.1429 | S23: =IF(F23<Q23,"considerar","esperar") -> esperar | T23: =+LIPIGAS!D3/INDICE!F24 -> 0.48958233 | V23: =+LIPIGAS!E3/INDICE!W3 -> 3883.3333 | X23: =IF(F23<V23,"considerar","esperar") -> esperar | Y23: =+LIPIGAS!E3/INDICE!F24 -> 0.4986784
B24: 21 | C24: NTGCLGAS | D24: GAS | F24: =+NTGCLGAS!B3 -> 622.98 | H24: =+'AGUAS-A'!C42 -> 0.12387201 | K24: =+NTGCLGAS!C63 -> 0.03147504 | M24: =+NTGCLGAS!C59 -> 0.21375374 | O24: =+NTGCLGAS!C61 -> 0.092860137 | Q24: =+NTGCLGAS!D3/INDICE!$R$3 -> 166.66667 | S24: =IF(F24<Q24,"considerar","esperar") -> esperar | T24: =+NTGCLGAS!D3/INDICE!F25 -> 0.0037921881 | V24: =+NTGCLGAS!E3/INDICE!$W$3 -> 270.83333 | X24: =IF(F24<V24,"considerar","esperar") -> esperar | Y24: =+NTGCLGAS!E3/INDICE!F25 -> 0.007042635
B25: 39 | C25: VOLCAN | D25: INDUSTRIAL | F25: =+VOLCAN!B3 -> 3076.5 | H25: =+'AGUAS-B'!C42 -> 0.12387201 | K25: =+VOLCAN!C55 -> 0.10319443 | M25: =+VOLCAN!C51 -> 0.31356836 | O25: =+VOLCAN!C53 -> 0.085020849 | Q25: =VOLCAN!D3/INDICE!$R$3 -> 2460.9952 | S25: =IF(F25<Q25,"considerar","esperar") -> esperar | T25: =VOLCAN!D3/INDICE!F26 -> 0.51577745 | V25: =VOLCAN!E3/INDICE!$W$3 -> 2157.125 | X25: =IF(F25<V25,"considerar","esperar") -> esperar | Y25: =VOLCAN!E3/INDICE!F26 -> 0.51667665
B26: 11 | C26: SECURITY | D26: BANCO | F26: =+SECURITY!B3 -> 334 | H26: =+SMU!C42 -> 0.12554186 | K26: =+SECURITY!C26 -> 0.058561578 | M26: =+SECURITY!C19 -> 0.614617 | O26: =+SECURITY!C28 -> 0.083499539 | Q26: =SECURITY!D3/INDICE!$R$3 -> 213.09524 | S26: =IF(F26<Q26,"considerar","esperar") -> esperar | T26: =SECURITY!D3/INDICE!F27 -> 0.0097494553 | V26: =SECURITY!D3/INDICE!$W$3 -> 186.45833 | X26: =IF(F26<V26,"considerar","esperar") -> esperar | Y26: =SECURITY!E3/INDICE!F27 -> 0.0097494553
B27: 25 | C27: EMBONOR-B | D27: EMBOTELLADORA | F27: =+'EMBONOR B'!B3 -> 1530 | H27: =+ENTEL!C42 -> 0.13214857 | K27: =+'EMBONOR B'!C61 -> 0.086046794 | M27: =+'EMBONOR B'!C57 -> 0.55905954 | O27: =+'EMBONOR B'!C59 -> 0.077328584 | Q27: =+'EMBONOR B'!D3/INDICE!$R$3 -> 1045.8209 | S27: =IF(F27<Q27,"considerar","esperar") -> esperar | T27: =+'EMBONOR B'!D3/INDICE!F28 -> 0.21097252 | V27: =+'EMBONOR B'!E3/INDICE!$W$3 -> 1191.6667 | X27: =IF(F27<V27,"considerar","esperar") -> esperar | Y27: =+'EMBONOR B'!E3/INDICE!F28 -> 0.27473583 | BC27: XC,,,,,,,,,,,,
B28: 18 | C28: AGUAS-A | D28: AGUAS | F28: =+'AGUAS-A'!B3 -> 347 | H28: =+BCI!C25 -> 0.13334469 | K28: =+'AGUAS-A'!C55 -> 0.031457807 | M28: =+'AGUAS-A'!C51 -> 0.82247372 | O28: =+'AGUAS-A'!C53 -> 0.075918712 | Q28: =+'AGUAS-A'!D3/INDICE!$R$3 -> 128.60005 | S28: =IF(F28<Q28,"considerar","esperar") -> esperar | T28: =+'AGUAS-A'!D3/INDICE!F29 -> 0.060013356 | V28: =+'AGUAS-A'!E3/INDICE!$R$3 -> 212.78576 | X28: =IF(F28<V28,"considerar","esperar") -> esperar | Y28: =+'AGUAS-A'!E3/INDICE!F29 -> 0.099300022
B29: 19 | C29: AGUAS-B | D29: AGUAS | F29: 150 | H29: =+COLBÚN!C44 -> 0.14668408 | K29: =+'AGUAS-B'!C55 -> 0.031456909 | M29: =+'AGUAS-B'!C51 -> 0.8224822 | O29: =+'AGUAS-B'!C53 -> 0.075895141 | Q29: =+'AGUAS-B'!D3/INDICE!$R$3 -> 128.60019 | S29: =IF(F29<Q29,"considerar","esperar") -> esperar | T29: =+'AGUAS-B'!D3/INDICE!F30 -> 0.12732692 | V29: =+'AGUAS-B'!E3/INDICE!$W$3 -> 186.18908 | X29: =IF(F29<V29,"considerar","esperar") -> considerar | Y29: =+'AGUAS-B'!E3/INDICE!F30 -> 0.21068072
B30: 16 | C30: ENELCHILE | D30: ELÉCTRICAS | F30: =+ENELCHILE!B3 -> 70.7 | H30: =+VOLCAN!C42 -> 0.14678967 | K30: =+ENELCHILE!C62 -> 0.10776466 | M30: =+ENELCHILE!C58 -> 1.0397965 | O30: =+ENELCHILE!C60 -> 0.069092385 | Q30: =+ENELCHILE!D3/INDICE!$R$3 -> 42.271429 | S30: =IF(F30<Q30,"considerar","esperar") -> esperar | T30: =+ENELCHILE!D3/INDICE!F31 -> 0.00028183637 | V30: =+ENELCHILE!E3/INDICE!$W$3 -> 36.9875 | X30: =IF(F30<V30,"considerar","esperar") -> esperar | Y30: =+ENELCHILE!E3/INDICE!F31 -> 0.00028183637
B31: 38 | C31: MOLYMET | D31: INDUSTRIAL | F31: =+MOLYMET!B3 -> 10499 | H31: =+SECURITY!C24 -> 0.14923317 | K31: =+MOLYMET!C59 -> 0.053417334 | M31: =+MOLYMET!C55 -> 0.49466284 | O31: =+MOLYMET!C57 -> 0.064150056 | Q31: =MOLYMET!D3/INDICE!$R$3 -> 2059.8524 | S31: =IF(F31<Q31,"considerar","esperar") -> esperar | T31: =MOLYMET!D3/INDICE!F32 -> 0.028580707 | V31: =MOLYMET!E3/INDICE!$W$3 -> 3010.6917 | X31: =IF(F31<V31,"considerar","esperar") -> esperar | Y31: =MOLYMET!E3/INDICE!F32 -> 0.047741394
B32: 26 | C32: CCU | D32: EMBOTELLADORA | F32: =CCU!B3 -> 5045 | H32: =+ILC!C44 -> 0.15240495 | K32: =+CCU!C61 -> 0.039631417 | M32: =+CCU!C57 -> 0.61404159 | O32: =+CCU!C59 -> 0.03470481 | Q32: =+CCU!D3/INDICE!$R$3 -> #REF! | S32: =IF(F32<Q32,"considerar","esperar") -> #REF! | T32: =+CCU!E3/INDICE!F33 -> #REF! | V32: =+CCU!E3/INDICE!$W$3 -> #REF! | X32: =IF(F32<V32,"considerar","esperar") -> #REF! | Y32: =+CCU!E3/INDICE!F33 -> #REF!
B33: 8 | C33: BSANTANDER | D33: BANCO | F33: =+SANTANDER!B3 -> 74.8 | H33: =+TRICAHUE!C42 -> 0.155339 | K33: =+SANTANDER!D39 -> 0.065266442 | M33: =+SANTANDER!D31 -> 0.66713322 | O33: =+SANTANDER!D41 -> 0.060412853 | Q33: =+SANTANDER!E3/INDICE!$R$3 -> 32.79 | S33: =IF(F33<Q33,"considerar","esperar") -> esperar | T33: =+SANTANDER!E3/INDICE!F34 -> 0.0136625 | V33: =+SANTANDER!F3/INDICE!$W$3 -> 28.69125 | X33: =IF(F33<V33,"considerar","esperar") -> esperar | Y33: =+SANTANDER!F3/INDICE!F34 -> 0.0136625
B34: 7 | C34: CHILE | D34: BANCO | F34: =+CHILE!B3 -> 168 | H34: =+ENELCHILE!C42 -> 0.1585192 | K34: =+CHILE!D39 -> 0.086165807 | M34: =+CHILE!D31 -> 0.64984823 | O34: =+CHILE!D41 -> 0.058619969 | Q34: =+CHILE!E3/INDICE!$R$3 -> 104.50078 | S34: =IF(F34<Q34,"considerar","esperar") -> esperar | T34: =+CHILE!E3/INDICE!F35 -> 0.061834778 | V34: =+CHILE!F3/INDICE!$W$3 -> 91.438179 | X34: =IF(F34<V34,"considerar","esperar") -> esperar | Y34: =+CHILE!F3/INDICE!F35 -> 0.061834778
B35: 37 | C35: MANQUEHUE | D35: INMOBILIARIA | F35: =+MANQUEHUE!B3 -> 118.3 | H35: =+'ANDINA A'!C42 -> 0.16433705 | K35: =+MANQUEHUE!C55 -> 0.035795706 | M35: =+MANQUEHUE!C51 -> 0.46550612 | O35: =+MANQUEHUE!C53 -> 0.05362564 | Q35: =MANQUEHUE!D3/INDICE!$R$3 -> 45.238095 | S35: =IF(F35<Q35,"considerar","esperar") -> esperar | T35: =MANQUEHUE!D3/INDICE!F36 -> 5.2341598e-05 | V35: =+MANQUEHUE!E3/INDICE!$W$3 -> 45.791667 | X35: =IF(F35<V35,"considerar","esperar") -> esperar | Y35: =MANQUEHUE!E3/INDICE!F36 -> 6.0550964e-05
B36: 9 | C36: BCI | D36: BANCO | F36: =+BCI!B3 -> 60500 | H36: =+FORUS!C42 -> 0.16607044 | K36: =+BCI!C27 -> 0.090565075 | M36: =+BCI!C19 -> 0.32755118 | O36: =+BCI!C29 -> 0.04800298 | Q36: =+BCI!D3/INDICE!$R$3 -> 15285.714 | S36: =IF(F36<Q36,"considerar","esperar") -> esperar | T36: =+BCI!D3/INDICE!F37 -> 1.2557948 | V36: =+BCI!E3/INDICE!$W$3 -> 13375 | X36: =IF(F36<V36,"considerar","esperar") -> esperar | Y36: =+BCI!E3/INDICE!F37 -> 1.2557948
B37: 27 | C37: CONCHATORO | D37: EMBOTELLADORA | F37: =+CONCHATORO!B3 -> 852.05 | H37: =+EDELMAG!C40 -> 0.1702768 | K37: =+CONCHATORO!C55 -> 0.066166197 | M37: =+CONCHATORO!C51 -> 0.39718171 | O37: =+CONCHATORO!C53 -> 0.039811528 | Q37: =+CONCHATORO!D3/INDICE!$R$3 -> 661.42857 | S37: =IF(F37<Q37,"considerar","esperar") -> esperar | T37: =+CONCHATORO!D3/INDICE!F38 -> 0.12861111 | V37: =+CONCHATORO!E3/INDICE!$W$3 -> 578.75 | X37: =IF(F37<V37,"considerar","esperar") -> esperar | Y37: =+CONCHATORO!E3/INDICE!F38 -> 0.12861111
B38: 40 | C38: FOSFOROS | D38: INDUSTRIAL | F38: =FOSFOROS!B3 -> 360 | H38: =+'EMBONOR A'!C42 -> 0.17189375 | K38: =+FOSFOROS!C55 -> 0.0057335833 | M38: =+FOSFOROS!C51 -> 0.61069473 | O38: =+FOSFOROS!C53 -> 0.020310092 | Q38: =FOSFOROS!D3/INDICE!$R$3 -> 256.54286 | S38: =IF(F38<Q38,"considerar","esperar") -> esperar | T38: =FOSFOROS!D3/INDICE!F39 -> 0.066511111 | V38: =FOSFOROS!E3/INDICE!$W$3 -> 224.475 | X38: =IF(F38<V38,"considerar","esperar") -> esperar | Y38: =FOSFOROS!E3/INDICE!F39 -> 0.066511111
B39: 17 | C39: CGE | D39: ELÉCTRICAS | F39: =CGE!B3 -> 270 | H39: =+'EMBONOR B'!C42 -> 0.17189375 | K39: =+CGE!C61 -> 0.0094653231 | M39: =+CGE!C57 -> 0.30013992 | O39: =+CGE!C59 -> 0.0074732157 | Q39: =+CGE!D3/INDICE!$R$3 -> 39.528571 | S39: =IF(F39<Q39,"considerar","esperar") -> esperar | T39: =+CGE!D3/INDICE!F40 -> 0.00014553966 | V39: =+CGE!E3/INDICE!$W$3 -> 34.5875 | X39: =IF(F39<V39,"considerar","esperar") -> esperar | Y39: =+CGE!E3/INDICE!F40 -> 0.00014553966
B40: 10 | C40: ITAUCL | D40: BANCO | F40: =+ITAU!B3 -> 19012 | H40: =+SANTANDER!D37 -> 0.17232311 | K40: =+ITAU!C26 -> 0.094895127 | M40: =+ITAU!C19 -> 0.061527814 | O40: =+ITAU!C28 -> 8.5686347e-06 | Q40: =ITAU!D3/INDICE!$R$3 -> 1.0441514 | S40: =IF(F40<Q40,"considerar","esperar") -> esperar | T40: =ITAU!D3/INDICE!F41 -> 0.00019133665 | V40: =ITAU!E3/INDICE!$W$3 -> 0.9136325 | X40: =IF(F40<V40,"considerar","esperar") -> esperar | Y40: =ITAU!D3/INDICE!F41 -> 0.00019133665
B41: 6 | C41: AAISA | D41: AFP | F41: =+AAISA!B3 -> 382 | H41: + | Q41: =+AAISA!H3/INDICE!$R$3 -> 83.928571 | S41: =IF(F41<Q41,"considerar","esperar") -> esperar | T41: =+AAISA!H3/INDICE!F42 -> 0.0022596154 | V41: =+AAISA!I3/INDICE!$W$3 -> 73.4375 | X41: =IF(F41<V41,"considerar","esperar") -> esperar | Y41: =+AAISA!I3/INDICE!F42 -> 0.0022596154
B42: 29 | C42: ANASAC | D42: FERTILIZANTES | F42: =+ANASAC!B3 -> 2600 | H42: =+SOQUICOM!C47 -> 0.19525774 | K42: 0 | Q42: =+ANASAC!D3/INDICE!$R$3 -> 2334.3694 | S42: =IF(F42<Q42,"considerar","esperar") -> esperar | T42: =+ANASAC!D3/INDICE!F43 -> 0.40547359 | V42: =+ANASAC!E3/INDICE!$W$3 -> 2903.2125 | X42: =IF(F42<V42,"considerar","esperar") -> considerar | Y42: =+ANASAC!E3/INDICE!F43 -> 0.5763201
B43: 30 | C43: BOLSASTGO | D43: FINANCIERA | F43: =+'BOLSA STGO'!B3 -> 403 | H43: =+AFPCAPITAL!C45 -> 0.20632989 | K43: 0 | Q43: =+'BOLSA STGO'!D3/INDICE!$R$3 -> 1680.6939 | S43: =IF(F43<Q43,"considerar","esperar") -> considerar | T43: =+'BOLSA STGO'!D3/INDICE!F44 -> 4.7863536 | V43: =+'BOLSA STGO'!E3/INDICE!$W$3 -> 1470.6071 | X43: =IF(F43<V43,"considerar","esperar") -> considerar | Y43: =+'BOLSA STGO'!E3/INDICE!F44 -> 4.7863536
B44: 33 | C44: ALMENDRAL | D44: HOLDING | F44: =+ALMENDRAL!B3 -> 24.58 | H44: =+'BOLSA STGO'!C42 -> 0.2102197 | K44: 0 | S44: =IF(F44<Q44,"considerar","esperar") -> esperar | X44: =IF(F44<V44,"considerar","esperar") -> esperar
H46: =+QUINENCO!C44 -> 0.21926271
B47: 42 | C47: EDELMAG | D47: ELÉCTRICAS | F47: =+EDELMAG!B3 -> 6221 | H47: =+BANVIDA!C37 -> 0.22884409 | K47: =+MINERA!C59 -> 0.038926328 | M47: =+EDELMAG!C55 -> 0 | O47: =+EDELMAG!C57 -> 0.073931455 | Q47: =EDELMAG!D3/INDICE!$R$3 -> 2452.381 | S47: =IF(F47<Q47,"considerar","esperar") -> esperar | T47: =EDELMAG!D3/INDICE!F47 -> 0.027594706 | V47: =EDELMAG!E3/INDICE!$W$3 -> 5012.5 | X47: =IF(F47<V47,"considerar","esperar") -> esperar | Y47: =EDELMAG!E3/INDICE!F47 -> 0.06445909
B48: 43 | C48: FORUS | D48: VESTUARIO | F48: =+FORUS!B3 -> 2300 | H48: =+LIPIGAS!C42 -> 0.23398219 | K48: =+FORUS!C55 -> 0.099642177 | M48: =+FORUS!C51 -> 0.40000045 | O48: =+FORUS!C53 -> 0.13105031 | Q48: =FORUS!D3/INDICE!$R$3 -> 621.5929 | S48: =IF(F48<Q48,"considerar","esperar") -> esperar | T48: =FORUS!D3/INDICE!F48 -> 0.018918045 | V48: =FORUS!E3/INDICE!$W$3 -> 1918.8938 | X48: =IF(F48<V48,"considerar","esperar") -> esperar | Y48: =FORUS!E3/INDICE!F48 -> 0.066744132
B49: 44 | C49: SONDA | D49: TELECOMUNICACIONES | F49: =+SONDA!B3 -> 290 | H49: =+CHILE!D37 -> 0.23844249 | K49: =+SONDA!C55 -> 0.028127601 | M49: =+SONDA!C51 -> 0.5853363 | O49: =+SONDA!C53 -> 0.067315468 | Q49: =SONDA!D3/INDICE!$R$3 -> 285.97143 | S49: =IF(F49<Q49,"considerar","esperar") -> esperar | T49: =SONDA!D3/INDICE!F49 -> 0.069027586 | V49: =SONDA!E3/INDICE!$W$3 -> 250.225 | X49: =IF(F49<V49,"considerar","esperar") -> esperar | Y49: =SONDA!E3/INDICE!F49 -> 0.069027586
B50: 45 | C50: ENELAM | D50: ELÉCTRICAS | F50: =+ENELAM!B3 -> 77.5 | H50: =+OXIQUIM!C43 -> 0.25338623 | K50: =+ENELAM!C58 -> 0.023920146 | M50: =+ENELAM!C54 -> -0.46386404 | O50: =+ENELAM!C56 -> 0.015535645 | Q50: =ENELAM!D3/INDICE!$R$3 -> 16.866667 | S50: =IF(F50<Q50,"considerar","esperar") -> esperar | T50: =ENELAM!D3/INDICE!F50 -> 0.015234409 | V50: =ENELAM!E3/INDICE!$W$3 -> 19.341667 | X50: =IF(F50<V50,"considerar","esperar") -> esperar | Y50: =ENELAM!E3/INDICE!F50 -> 0.019965591
B51: 46 | C51: ENELGXCH | D51: ELÉCTRICAS | F51: =+ENELGXCH!B3 -> 519 | H51: =+ZOFRI!C42 -> 0.31287341 | K51: =+ENELGXCH!C61 -> 0.11412167 | M51: =+ENELGXCH!C57 -> 0.39996529 | O51: =+ENELGXCH!C59 -> 0.087003464 | Q51: =ENELGXCH!D3/INDICE!$R$3 -> 546.80619 | S51: =IF(F51<Q51,"considerar","esperar") -> considerar | T51: =ENELGXCH!D3/INDICE!F51 -> 0.073750353 | V51: =ENELGXCH!E3/INDICE!$W$3 -> 352.90958 | X51: =IF(F51<V51,"considerar","esperar") -> esperar | Y51: =ENELGXCH!E3/INDICE!F51 -> 0.054398394
B52: 47 | C52: IAM | D52: AGUAS | F52: =+IAM!B3 -> 985 | H52: =+HABITAT!C46 -> 0.40456939 | K52: =+IAM!C55 -> 0.018023659 | M52: =+IAM!C51 -> 0.69696992 | O52: =+IAM!C53 -> 0.091614824 | Q52: =IAM!D3/INDICE!$R$3 -> 482.6 | S52: =IF(F52<Q52,"considerar","esperar") -> esperar | T52: =IAM!D3/INDICE!F52 -> 0.034296447 | V52: =IAM!E3/INDICE!$W$3 -> 556.76667 | X52: =IF(F52<V52,"considerar","esperar") -> esperar | Y52: =IAM!E3/INDICE!F52 -> 0.045219628
B53: 48 | C53: ELECMETAL | D53: INDUSTRIAL | F53: =+ELECMETAL!B3 -> 14961 | H53: =+PLANVITAL!C46 -> 0.43195851 | K53: =+ELECMETAL!C55 -> 0.048226816 | M53: =+ELECMETAL!C51 -> 0.41754159 | O53: =+ELECMETAL!C53 -> 0.028093877 | Q53: =ELECMETAL!D3/INDICE!$R$3 -> 4687.4286 | S53: =IF(F53<Q53,"considerar","esperar") -> esperar | T53: =ELECMETAL!D3/INDICE!F53 -> 0.021931689 | V53: =ELECMETAL!E3/INDICE!$W$3 -> 4101.5 | X53: =IF(F53<V53,"considerar","esperar") -> esperar | Y53: =ELECMETAL!E3/INDICE!F53 -> 0.021931689
B54: 49 | C54: GASCO | D54: GAS | F54: =+GASCO!B3 -> 1500 | H54: =+PEHUENCHE!C41 -> 0.90514575 | K54: =+GASCO!C61 -> 0.017930267 | M54: =+GASCO!C57 -> 0.61253843 | O54: =+GASCO!C59 -> 0.071379381 | Q54: =GASCO!D3/INDICE!$R$3 -> 1496.1905 | S54: =IF(F54<Q54,"considerar","esperar") -> esperar | T54: =GASCO!D3/INDICE!F54 -> 0.069822222 | V54: =GASCO!E3/INDICE!$W$3 -> 1496.6667 | X54: =IF(F54<V54,"considerar","esperar") -> esperar | Y54: =GASCO!E3/INDICE!F54 -> 0.079822222
B55: 50 | C55: CMPC | D55: CELULOSA | F55: =+CMPC!B3 -> 1160 | H55: ROE | K55: =+CMPC!C59 -> 0.039482652 | M55: =+CMPC!C55 -> 0.50138636 | O55: =+CMPC!C57 -> 0.092280844 | Q55: =CMPC!D3/INDICE!$R$3 -> 1886.4619 | S55: =IF(F55<Q55,"considerar","esperar") -> considerar | T55: =CMPC!D3/INDICE!F55 -> 0.11383822 | V55: =CMPC!E3/INDICE!$W$3 -> 1688.1542 | X55: =IF(F55<V55,"considerar","esperar") -> considerar | Y55: =CMPC!E3/INDICE!F55 -> 0.11642443
B56: 51 | C56: ENLASA | D56: ELÉCTRICAS | F56: =+ENLASA!B3 -> 945 | K56: =+ENLASA!C59 -> 0.014130447 | M56: =+ENLASA!C55 -> 0.80635943 | O56: =+ENLASA!C57 -> 0.16435458 | Q56: =ENLASA!D3/INDICE!$R$3 -> 1302.6571 | S56: =IF(F56<Q56,"considerar","esperar") -> considerar | T56: =ENLASA!D3/INDICE!F56 -> 0.096493122 | V56: =ENLASA!E3/INDICE!$W$3 -> 1576.3875 | X56: =IF(F56<V56,"considerar","esperar") -> considerar | Y56: =ENLASA!E3/INDICE!F56 -> 0.13345079
B57: 52 | C57: CAP | D57: MINERA | F57: =+'CAP (TIKR)'!B3 -> 6460 | K57: =+'CAP (TIKR)'!C58 -> 0.038623589 | M57: =+'CAP (TIKR)'!C54 -> 0.37047805 | O57: =+'CAP (TIKR)'!C56 -> 0.10182881 | Q57: ='CAP (TIKR)'!D3/INDICE!$R$3 -> 8155.9429 | S57: =IF(F57<Q57,"considerar","esperar") -> considerar | T57: ='CAP (TIKR)'!D3/INDICE!F57 -> 0.08837709 | V57: ='CAP (TIKR)'!E3/INDICE!$W$3 -> 8235.7437 | X57: =IF(F57<V57,"considerar","esperar") -> considerar | Y57: ='CAP (TIKR)'!E3/INDICE!F57 -> 0.10199063
B58: 53 | C58: BESALCO | D58: CONSTRUCTORA | F58: =+'BESALCO (TIKR)'!B3 -> 1270 | K58: =+'BESALCO (TIKR)'!C55 -> 0.060221104 | M58: =+'BESALCO (TIKR)'!C51 -> 0.40760211 | O58: =+'BESALCO (TIKR)'!C53 -> 0.033938067 | Q58: ='BESALCO (TIKR)'!D3/INDICE!$R$3 -> 153.49286 | S58: =IF(F58<Q58,"considerar","esperar") -> esperar | T58: ='BESALCO (TIKR)'!D3/INDICE!F58 -> 0.0084602362 | V58: ='BESALCO (TIKR)'!E3/INDICE!$W$3 -> 168.90625 | X58: =IF(F58<V58,"considerar","esperar") -> esperar | Y58: ='BESALCO (TIKR)'!E3/INDICE!F58 -> 0.010639764
B59: 54 | C59: SALFACORP | D59: CONSTRUCTORA | F59: =+'SALFACORP (TIKR)'!B3 -> 1300 | K59: =+'SALFACORP (TIKR)'!C55 -> 0.048795896 | M59: =+'SALFACORP (TIKR)'!C51 -> 0.29229273 | O59: =+'SALFACORP (TIKR)'!C53 -> 0.037145565 | Q59: ='SALFACORP (TIKR)'!D3/INDICE!$R$3 -> 246.89286 | S59: =IF(F59<Q59,"considerar","esperar") -> esperar | T59: ='SALFACORP (TIKR)'!D3/INDICE!F59 -> 0.013294231 | V59: ='SALFACORP (TIKR)'!E3/INDICE!$W$3 -> 216.03125 | X59: =IF(F59<V59,"considerar","esperar") -> esperar | Y59: ='SALFACORP (TIKR)'!E3/INDICE!F59 -> 0.013294231
B60: 55 | C60: EISA | D60: CONSTRUCTORA | F60: =+'EISA (TIKR)'!B3 -> 474 | K60: =+'EISA (TIKR)'!C55 -> 0.049902522 | M60: =+'EISA (TIKR)'!C51 -> 0.34696147 | O60: =+'EISA (TIKR)'!C53 -> 0.038213946 | Q60: ='EISA (TIKR)'!D3/INDICE!$R$3 -> 83.364286 | S60: =IF(F60<Q60,"considerar","esperar") -> esperar | T60: ='EISA (TIKR)'!D3/INDICE!F60 -> 0.012311181 | V60: ='EISA (TIKR)'!E3/INDICE!$W$3 -> 72.94375 | X60: =IF(F60<V60,"considerar","esperar") -> esperar | Y60: ='EISA (TIKR)'!E3/INDICE!F60 -> 0.012311181
B61: 56 | C61: BANVIDA | D61: ASEGURADORA | F61: =+BANVIDA!B3 -> 720.08 | K61: =+BANVIDA!C50 -> 0.10194032 | M61: =+BANVIDA!C46 -> 0.53247576 | O61: =+BANVIDA!C48 -> 0.14023856 | Q61: =BANVIDA!D3/INDICE!$R$3 -> 446.27143 | S61: =IF(F61<Q61,"considerar","esperar") -> esperar | T61: =BANVIDA!D3/INDICE!F61 -> 0.04338268 | V61: =BANVIDA!E3/INDICE!$W$3 -> 424.86563 | X61: =IF(F61<V61,"considerar","esperar") -> esperar | Y61: =BANVIDA!E3/INDICE!F61 -> 0.047202047
B62: 57 | C62: INGEVEC | D62: CONSTRUCTORA
B63: 58 | C63: MOLLER | D63: CONSTRUCTORA
B64: 59 | C64: SOCOVESA | D64: CONSTRUCTORA
B65: 60 | C65: COPEC | D65: CELULOSA
B66: 61 | C66: CENCOMALLS | D66: INMOBILIARIO
B67: 62 | C67: MALLPLAZA | D67: INMOBILIARIO
B68: 63 | C68: PARAUCO | D68: INMOBILIARIO
C73: PARA CURIOSEAR
C74: CENCOSUD | D74: RETAIL
C75: RIPLEY | D75: RETAIL
C76: FALABELLA | D76: RETAIL
C77: HITES | D77: RETAIL
C78: CAROZZI | D78: CONSUMO
C79: CIC | D79: CONSUMO
C80: MARINSA
C81: IANSA | D81: CONSUMO
C82: SQM | D82: MINERA
C83: ORO BLANCO (?) | D83: MINERA
C84: NORTE GRANDE (?) | D84: MINERA
C85: CFINRENTAS | D85: FONDO INMOBILIARIO
C86: CFIBTGRCA | D86: FONDO INMOBILIARIO
C87: CFILVPARI1 | D87: FONDO INMOBILIARIO
C88: BICECORP (?) | D88: SER. FINANCIEROS
C89: INVERCAP | D89: MINERA
BC194: .............................................................

Sheet AAISA
B2: =TODAY()-1 -> 46105 | H2: PROM DIVIDENDOS SIN ADIC/EVENT | I2: PROM DIVIDENDOS TOTALES
B3: {=_FV(B6,"Precio")} -> 382 | H3: =AVERAGE(G49:K49) -> 5.875 | I3: =AVERAGE(G48:K48) -> 5.875
B6: #VALUE! | C6: 2017 | D6: 2018 | E6: 2019 | F6: 2020 | G6: 2021 | H6: 2022 | I6: 2023 | J6: 2024 | K6: 2025 | L6: 2026
B7: Activos corrientes | G7: 105219190000 | H7: 89200440000 | I7: 101399288000 | J7: 132432966000
B8: INVENTARIOS | G8: 0
B9: Acitvos fijos | G9: 200385323000 | H9: 196482993000 | I9: 259862269000 | J9: 362584935000
B10: Encaje | G10: 132001721000 | H10: 124042038000 | I10: 178709698000 | J10: 274487986000
B11: INTANGIBLE | G11: 30790564000 | H11: 31787542000 | I11: 31564610000 | J11: 31638900000 | K11: 34477442000
B12: Activos totales | G12: =+G9+G7 -> 305604513000 | H12: 285683433000 | I12: 361261557000 | J12: =+J9+J7 -> 495017901000
B13: Pasivos corrientes | G13: 40978160000 | H13: 31633208000 | I13: 32025455000 | J13: 37677165000
B14: Pasivos no corrientes | G14: 18392022000 | H14: 14187174000 | I14: 36820323000 | J14: 135225198000
B15: Total Pasivos | G15: =+G14+G13 -> 59370182000 | H15: 45820382000 | I15: =+I13+I14 -> 68845778000 | J15: =+J13+J14 -> 172902363000
B16: Patrimonio | G16: 246234331000 | H16: 239863051000 | I16: =+I12-I15 -> 292415779000 | J16: =+J12-J15 -> 322115538000
B17: Patrimonio Sin Intangible | G17: =+G16-G11 -> 215443767000 | H17: =+H16-H11 -> 208075509000 | I17: =+I16-I11 -> 260851169000 | J17: =+J16-J11 -> 290476638000
B18: Cantidad de acciones | G18: 1000000000 | H18: 1000000000 | I18: 1000000000 | J18: 1000000000
B20: Valor libro | G20: =(G16/G18) -> 246.23433 | H20: =(H16/H18) -> 239.86305 | I20: =(I16/I18) -> 292.41578 | J20: =(J16/J18) -> 322.11554
B21: Valor Libro sin intangible | G21: =+G17/G18 -> 215.44377 | H21: =+H17/H18 -> 208.07551 | I21: =+I17/I18 -> 260.85117 | J21: =+J17/J18 -> 290.47664
B22: Valor sólo con Encaje | G22: =+G10/G18 -> 132.00172 | H22: =+H10/H18 -> 124.04204 | I22: =+I10/I18 -> 178.7097 | J22: =+J10/J18 -> 274.48799
B23: Precio FIN AÑO | H23: 132.1 | I23: 191.26 | J23: 214.94
B24: PER | G24: =+G23/G45 -> 0 | H24: =+H23/H44 -> 6.605 | I24: =+I23/I44 -> 6.1372183 | J24: =+J23/J44 -> 5.7473159
B25: Bolsa/Libro | G25: =+G23/G20 -> 0 | H25: =+H23/H20 -> 0.55073093 | I25: =+I23/I20 -> 0.65406867 | J25: =+J23/J20 -> 0.6672761
B26: GRAHAM | G26: =+G24*G25 -> 0 | H26: =+H24*H25 -> 3.6375778 | I26: =+I24*I25 -> 4.0141622 | J26: =+J24*J25 -> 3.8350466
B27: Bolsa Libro Banda Menor | G27: 0 | H27: 0 | I27: 0 | J27: 0
B28: Bolsa Libro Banda Mayor | G28: 1 | H28: 1 | I28: 1 | J28: 1
B29: Precio Objetivo Menor | G29: =+G27*G20 -> 0 | H29: =+H27*H20 -> 0 | I29: =+I27*I20 -> 0 | J29: =+J27*J20 -> 0
B30: Precio Obejtivo Promedio | G30: =AVERAGE(G29,G31) -> 123.11717 | H30: =AVERAGE(H29,H31) -> 119.93153 | I30: =AVERAGE(I29,I31) -> 146.20789 | J30: =AVERAGE(J29,J31) -> 161.05777
B31: Precio Objetivo Mayor | G31: =+G20*G28 -> 246.23433 | H31: =+H20*H28 -> 239.86305 | I31: =+I20*I28 -> 292.41578 | J31: =+J20*J28 -> 322.11554
B33: Capital de Trabajo | G33: =G7-G13 -> 64241030000 | H33: =H7-H13 -> 57567232000 | I33: =I7-I13 -> 69373833000 | J33: =J7-J13 -> 94755801000
B34: Razón corriente | G34: =G7/G13 -> 2.5676895 | H34: =H7/H13 -> 2.8198354 | I34: =I7/I13 -> 3.1662091 | J34: =J7/J13 -> 3.5149398
B35: Razón ácida | G35: =+(G7-G8)/G13 -> 2.5676895 | H35: =+(H7-H8)/H13 -> 2.8198354 | I35: =+(I7-I8)/I13 -> 3.1662091 | J35: =+(J7-J8)/J13 -> 3.5149398
B36: Razón de endeudamiento | G36: =G15/G12 -> 0.19427129 | H36: =H15/H12 -> 0.16038866 | I36: =I15/I12 -> 0.19057045 | J36: =J15/J12 -> 0.34928507
B39: Ingresos | G39: 10040660000 | H39: 68082093000 | I39: 111180751000 | J39: 148071321000
B40: EBITDA | G40: =+G39-4829551000 -> 5211109000 | H40: 19553316000 | I40: 40368677000 | J40: 50410265000
B41: Margen EBITDA | G41: =G40/G39 -> 0.51900064 | H41: =H40/H39 -> 0.28720204 | I41: =I40/I39 -> 0.36309052 | J41: =J40/J39 -> 0.34044584
B42: Utilidad neta | G42: 3897736000 | H42: 20154682000 | I42: 31163956000 | J42: 37398327000
B43: Margen neto porcentual | G43: =G42/G39 -> 0.3881952 | H43: =H42/H39 -> 0.29603499 | I43: =I42/I39 -> 0.28029992 | J43: =J42/J39 -> 0.25256969
B44: EPS | G44: =4*1000 -> 4000 | H44: 20 | I44: =+I42/I18 -> 31.163956 | J44: =+J42/J18 -> 37.398327
B45: ROE | G45: =G42/G16 -> 0.015829377 | H45: =H42/H16 -> 0.084025789 | I45: =I42/I16 -> 0.10657413 | J45: =J42/J16 -> 0.11610221
B46: ROE AJUSTADO | G46: =+G45/G25 -> #DIV/0! | H46: =+H45/H25 -> 0.1525714 | I46: =+I45/I25 -> 0.16294027 | J46: =+J45/J25 -> 0.17399426
B47: FCF | H47: 14167891000 | I47: 21107849000 | J47: 114613969000
B48: Dividendos calendario | G48: =SUM(G50:G54) -> 0 | H48: =SUM(H50:H54) -> 3.5 | I48: =SUM(I50:I54) -> 10 | J48: =SUM(J50:J54) -> 10
B49: Dividendos sin eventual Calendario | G49: =+G50+G51+G52+G53 -> 0 | H49: =+H50+H51+H52+H53 -> 3.5 | I49: =+I50+I51+I52+I53 -> 10 | J49: =+J50+J51+J52+J53 -> 10
B50: Definitivo año calendario | H50: 3.5 | I50: 10 | J50: 10 | K50: 11.5
B51: Provisorio calendario
B52: Adicional calendario
B53: Eventual calendario
B54: Dividendos
B55: Dividendos sin eventual
B56: Definitivo | H56: 10 | I56: 10 | J56: 11.5
B57: Provisorio
B58: Adicional
B59: Eventual
B61: PAY OUT | G61: =(G51+G52+G53+H50)/G44 -> 0.000875 | H61: =(H51+H52+H53+I50)/H44 -> 0.5 | I61: =(I51+I52+I53+J50)/I44 -> 0.32088352 | J61: =(J51+J52+J53+K50)/J44 -> 0.30750039
B62: DIV/YIELD | G62: =+G48/G23 -> #DIV/0! | H62: =+H48/H23 -> 0.026495079 | I62: =+I48/I23 -> 0.052284848 | J62: =+J48/J23 -> 0.046524612
B63: G | H63: =+H45*(1-H61) -> 0.042012894 | I63: =+I45*(1-I61) -> 0.072376245 | J63: =+J45*(1-J61) -> 0.080400738
B64: PRECIO | C64: =B3 -> 382

Sheet AFPCAPITAL
B2: =TODAY()-1 -> 46105 | D2: PROM DIVIDENDOS SIN ADIC/EVENT | E2: PROM DIVIDENDOS TOTALES
B3: {=_FV(B6,"Precio")} -> 272.25 | D3: =AVERAGE(G48:I48) -> 17.971333 | E3: =AVERAGE(G47:I47) -> 23.306667
B6: #VALUE! | C6: 2017 | D6: 2018 | E6: 2019 | F6: 2020 | G6: 2021 | H6: 2022 | I6: 2023 | J6: 2024 | K6: 2025 | L6: 2026 | M6: 2027 | N6: 2028
B7: Activos corrientes | C7: =+C71 -> 106835735000 | D7: =+D71 -> 74152970000 | E7: =+E71 -> 75692564000 | F7: =+F71 -> 90664627000 | G7: =+G71 -> 63045514000 | H7: =+H71 -> 47079707000 | I7: =+I71 -> 95023798000 | J7: =+J71 -> 122681361000 | ... N7: =+N71 -> 0
B8: INVENTARIOS | C8: 0 | D8: 0 | E8: 0 | F8: 0 | G8: 0 | H8: 0 | I8: 0 | J8: 0 | K8: 0 | L8: 0 | M8: 0 | N8: 0
B9: Acitvos fijos | C9: =+C80 -> 452454294000 | D9: =+D80 -> 457699233000 | E9: =+E80 -> 516817122000 | F9: =+F80 -> 521204053000 | G9: =+G80 -> 494282056000 | H9: =+H80 -> 499374563000 | I9: =+I80 -> 522497691000 | J9: =+J80 -> 555132195000 | ... N9: =+N80 -> 0
B10: Encaje | C10: =+C81 -> 247403057000 | D10: =+D81 -> 254201735000 | E10: =+E81 -> 305961667000 | F10: =+F81 -> 308725396000 | G10: =+G81 -> 284461896000 | H10: =+H81 -> 295637992000 | I10: =+I81 -> 321203585000 | J10: =+J81 -> 346285329000 | ... N10: =+N81 -> 0
B11: INTANGIBLE | C11: =+C84 -> 187962187000 | D11: =+D84 -> 187572055000 | E11: =+E84 -> 187542539000 | F11: =+F84 -> 188298526000 | G11: =+G84 -> 188191450000 | H11: =+H84 -> 188000173000 | I11: =+I84 -> 188488444000 | J11: =+J84 -> 187630376000 | ... N11: =+N84 -> 0
B12: Activos totales | C12: =+C7+C9 -> 559290029000 | D12: =+D7+D9 -> 531852203000 | E12: =+E7+E9 -> 592509686000 | F12: =+F7+F9 -> 611868680000 | G12: =+G7+G9 -> 557327570000 | H12: =+H7+H9 -> 546454270000 | I12: =+I7+I9 -> 617521489000 | J12: =+J7+J9 -> 677813556000 | ... N12: =+N7+N9 -> 0
B13: Pasivos corrientes | C13: =+C93 -> 49180754000 | D13: =+D93 -> 51453291000 | E13: =+E93 -> 62973146000 | F13: =+F93 -> 122980590000 | G13: =+G93 -> 75496876000 | H13: =+H93 -> 55396016000 | I13: =+I93 -> 95915328000 | J13: =+J93 -> 121562114000 | ... N13: =+N93 -> 0
B14: Pasivos no corrientes | C14: =+C102 -> 50100031000 | D14: =+D102 -> 51014275000 | E14: =+E102 -> 69621044000 | F14: =+F102 -> 72124110000 | G14: =+G102 -> 66972919000 | H14: =+H102 -> 64324540000 | I14: =+I102 -> 69239170000 | J14: =+J102 -> 81498345000 | ... N14: =+N102 -> 0
B15: Total Pasivos | C15: =+C14+C13 -> 99280785000 | D15: =+D14+D13 -> 102467566000 | E15: =+E14+E13 -> 132594190000 | F15: =+F14+F13 -> 195104700000 | G15: =+G14+G13 -> 142469795000 | H15: =+H14+H13 -> 119720556000 | I15: =+I14+I13 -> 165154498000 | J15: =+J14+J13 -> 203060459000 | ... N15: =+N14+N13 -> 0
B16: Patrimonio | C16: =+C114 -> 461009244000 | D16: =+D114 -> 429384637000 | E16: =+E114 -> 459915496000 | F16: =+F114 -> 416763980000 | G16: =+G114 -> 414857775000 | H16: =+H114 -> 426733714000 | I16: =+I114 -> 452366991000 | J16: =+J114 -> 474753097000 | ... N16: =+N114 -> 0
B17: Patrimonio Sin Intangible | C17: =+C16-C11 -> 273047057000 | D17: =+D16-D11 -> 241812582000 | E17: =+E16-E11 -> 272372957000 | F17: =+F16-F11 -> 228465454000 | G17: =+G16-G11 -> 226666325000 | H17: =+H16-H11 -> 238733541000 | I17: =+I16-I11 -> 263878547000 | J17: =+J16-J11 -> 287122721000 | ... N17: =+N16-N11 -> 0
B18: Cantidad de acciones | C18: 3123767502 | D18: 3123767502 | E18: 3123767502 | F18: 3123767502 | G18: 3123767502 | H18: 3123767502 | I18: 3123767502 | J18: 3123767502
B20: Valor libro | C20: =(C16/C18) -> 147.58116 | D20: =(D16/D18) -> 137.4573 | E20: =(E16/E18) -> 147.23103 | F20: =(F16/F18) -> 133.41709 | G20: =(G16/G18) -> 132.80687 | H20: =(H16/H18) -> 136.60867 | I20: =(I16/I18) -> 144.81455 | J20: =(J16/J18) -> 151.98093 | ... N20: =(N16/N18) -> #DIV/0!
B21: Valor Libro sin intangible | C21: =+C17/C18 -> 87.409533 | D21: =+D17/D18 -> 77.410557 | E21: =+E17/E18 -> 87.193735 | F21: =+F17/F18 -> 73.137791 | G21: =+G17/G18 -> 72.561842 | H21: =+H17/H18 -> 76.424875 | I21: =+I17/I18 -> 84.474452 | J21: =+J17/J18 -> 91.915522 | ... N21: =+N17/N18 -> #DIV/0!
B22: Valor sólo con Encaje | C22: =+C10/C18 -> 79.200215 | D22: =+D10/D18 -> 81.37665 | E22: =+E10/E18 -> 97.946363 | F22: =+F10/F18 -> 98.831106 | G22: =+G10/G18 -> 91.063722 | H22: =+H10/H18 -> 94.641484 | I22: =+I10/I18 -> 102.8257 | J22: =+J10/J18 -> 110.85503 | ... N22: =+N10/N18 -> #DIV/0!
B23: Precio FIN AÑO | C23: 215.02 | D23: 307.42 | E23: 275.32 | F23: 250.67 | G23: 250.67 | H23: 250.67 | I23: 250.67 | J23: 250.67
B24: PER | C24: =+C23/C43 -> 10.4328 | D24: =+D23/D43 -> 17.069406 | E24: =+E23/E43 -> 9.8787226 | F24: =+F23/F43 -> 13.069343 | G24: =+G23/G43 -> 10.703245 | H24: =+H23/H43 -> 8.8669968 | I24: =+I23/I43 -> 7.3424136 | J24: =+J23/J43 -> 7.5960606 | ... N24: =+N23/N43 -> #DIV/0!
B25: Bolsa Libro | C25: =+C23/C20 -> 1.456961 | D25: =+D23/D20 -> 2.2364764 | E25: =+E23/E20 -> 1.8699863 | F25: =+F23/F20 -> 1.8788447 | G25: =+G23/G20 -> 1.8874777 | H25: =+H23/H20 -> 1.8349495 | I25: =+I23/I20 -> 1.7309725 | J25: =+J23/J20 -> 1.6493516 | ... N25: =+N23/N20 -> #DIV/0!
B26: GRAHAM | C26: =+C24*C25 -> 15.200182 | D26: =+D24*D25 -> 38.175323 | E26: =+E24*E25 -> 18.473076 | F26: =+F24*F25 -> 24.555266 | G26: =+G24*G25 -> 20.202136 | H26: =+H24*H25 -> 16.270491 | I26: =+I24*I25 -> 12.709516 | J26: =+J24*J25 -> 12.528575 | ... N26: =+N24*N25 -> #DIV/0!
B27: Bolsa Libro Banda Menor | C27: 1 | D27: 1 | E27: 2 | F27: 1 | G27: 2 | H27: 2 | I27: 2 | J27: 2
B28: Bolsa Libro Banda Mayor | C28: 2 | D28: 2 | E28: 2.5 | F28: 2 | G28: 2.5 | H28: 2.5 | I28: 2.5 | J28: 2.5
B29: Precio Objetivo Menor | C29: =+C27*C20 -> 147.58116 | D29: =+D27*D20 -> 137.4573 | E29: =+E27*E20 -> 294.46205 | F29: =+F27*F20 -> 133.41709 | G29: =+G27*G20 -> 265.61373 | H29: =+H27*H20 -> 273.21733 | I29: =+I27*I20 -> 289.6291 | J29: =+J27*J20 -> 303.96186 | ... N29: =+N27*N20 -> #DIV/0!
B30: Precio Obejtivo Promedio | C30: =AVERAGE(C29,C31) -> 221.37175 | D30: =AVERAGE(D29,D31) -> 206.18595 | E30: =AVERAGE(E29,E31) -> 331.26981 | F30: =AVERAGE(F29,F31) -> 200.12564 | G30: =AVERAGE(G29,G31) -> 298.81545 | H30: =AVERAGE(H29,H31) -> 307.3695 | I30: =AVERAGE(I29,I31) -> 325.83274 | J30: =AVERAGE(J29,J31) -> 341.9571 | ... N30: =AVERAGE(N29,N31) -> #DIV/0!
B31: Precio Objetivo Mayor | C31: =+C20*C28 -> 295.16233 | D31: =+D20*D28 -> 274.91459 | E31: =+E20*E28 -> 368.07757 | F31: =+F20*F28 -> 266.83419 | G31: =+G20*G28 -> 332.01717 | H31: =+H20*H28 -> 341.52167 | I31: =+I20*I28 -> 362.03638 | J31: =+J20*J28 -> 379.95233 | ... N31: =+N20*N28 -> #DIV/0!
B33: Capital de Trabajo | C33: =C7-C13 -> 57654981000 | D33: =D7-D13 -> 22699679000 | E33: =E7-E13 -> 12719418000 | F33: =F7-F13 -> -32315963000 | G33: =G7-G13 -> -12451362000 | H33: =H7-H13 -> -8316309000 | I33: =I7-I13 -> -891530000 | J33: =J7-J13 -> 1119247000 | ... N33: =N7-N13 -> 0
B34: Razón corriente | C34: =C7/C13 -> 2.1723078 | D34: =D7/D13 -> 1.4411706 | E34: =E7/E13 -> 1.2019816 | F34: =F7/F13 -> 0.73722713 | G34: =G7/G13 -> 0.83507447 | H34: =H7/H13 -> 0.84987532 | I34: =I7/I13 -> 0.99070503 | J34: =J7/J13 -> 1.0092072 | ... N34: =N7/N13 -> #DIV/0!
B35: Razón ácida | C35: =+(C7-C8)/C13 -> 2.1723078 | D35: =+(D7-D8)/D13 -> 1.4411706 | E35: =+(E7-E8)/E13 -> 1.2019816 | F35: =+(F7-F8)/F13 -> 0.73722713 | G35: =+(G7-G8)/G13 -> 0.83507447 | H35: =+(H7-H8)/H13 -> 0.84987532 | I35: =+(I7-I8)/I13 -> 0.99070503 | J35: =+(J7-J8)/J13 -> 1.0092072 | ... N35: =+(N7-N8)/N13 -> #DIV/0!
B36: Razón de endeudamiento | C36: =C15/C12 -> 0.17751217 | D36: =D15/D12 -> 0.19266173 | E36: =E15/E12 -> 0.223784 | F36: =F15/F12 -> 0.31886695 | G36: =G15/G12 -> 0.25563027 | H36: =H15/H12 -> 0.21908614 | I36: =I15/I12 -> 0.26744737 | J36: =J15/J12 -> 0.29958158 | ... N36: =N15/N12 -> #DIV/0!
B38: Ingresos | C38: =+C118+C119 -> 153081797000 | D38: =+D118+D119 -> 143493133000 | E38: =+E118+E119 -> 189509366000 | F38: =+F118+F119 -> 167313902000 | G38: =+G118+G119 -> 175110953000 | H38: =+H118+H119 -> 191817950000 | I38: =+I118+I119 -> 221149543000 | J38: =+J118+J119 -> 232088060000 | ... N38: =+N118+N119 -> 0
B39: EBITDA | C39: =+C118+C119+C120+C123 -> 80444186000 | D39: =+D118+D119+D120+D123 -> 69089992000 | E39: =+E118+E119+E120+E123 -> 113115060000 | F39: =+F118+F119+F120+F123 -> 85367914000 | G39: =+G118+G119+G120+G123 -> 94674230000 | H39: =+H118+H119+H120+H123 -> 108835835000 | I39: =+I118+I119+I120+I123 -> 135181649000 | J39: =+J118+J119+J120+J123 -> 137691293000 | ... N39: =+N118+N119+N120+N123 -> 0
B40: Margen EBITDA | C40: =C39/C38 -> 0.52549805 | D40: =D39/D38 -> 0.4814864 | E40: =E39/E38 -> 0.59688374 | F40: =F39/F38 -> 0.51022607 | G40: =G39/G38 -> 0.54065282 | H40: =H39/H38 -> 0.56739129 | I40: =I39/I38 -> 0.61126805 | J40: =J39/J38 -> 0.59327177 | ... N40: =N39/N38 -> #DIV/0!
B41: Utilidad neta | C41: =+C134 -> 64365815000 | D41: =+D134 -> 56257053000 | E41: =+E134 -> 87047237000 | F41: =+F134 -> 59912751000 | G41: =+G134 -> 73164253000 | H41: =+H134 -> 88294898000 | I41: =+I134 -> 106632475000 | J41: =+J134 -> 102713160000 | ... N41: =+N134 -> 0
B42: Margen neto porcentual | C42: =C41/C38 -> 0.42046681 | D42: =D41/D38 -> 0.39205397 | E42: =E41/E38 -> 0.45932947 | F42: =F41/F38 -> 0.35808591 | G42: =G41/G38 -> 0.41781654 | H42: =H41/H38 -> 0.46030571 | I42: =I41/I38 -> 0.48217362 | J42: =J41/J38 -> 0.44256116 | ... N42: =N41/N38 -> #DIV/0!
B43: EPS | C43: =+C135 -> 20.61 | D43: =+D135 -> 18.01 | E43: =+E135 -> 27.87 | F43: =+F135 -> 19.18 | G43: =+G135 -> 23.42 | H43: =+H135 -> 28.27 | I43: =+I135 -> 34.14 | J43: =+J135 -> 33 | ... N43: =+N135 -> 0
B44: ROE | C44: =C41/C16 -> 0.13961936 | D44: =D41/D16 -> 0.13101785 | E44: =E41/E16 -> 0.18926789 | F44: =F41/F16 -> 0.14375703 | G44: =G41/G16 -> 0.17635985 | H44: =H41/H16 -> 0.20690865 | I44: =I41/I16 -> 0.23572117 | J44: =J41/J16 -> 0.21635069 | ... N44: =N41/N16 -> #DIV/0!
B45: ROE PROMEDIO 3 AÑOS | C45: =AVERAGE(G44:I44) -> 0.20632989
B46: FCF | C46: =+C148 -> 76354133000 | D46: =+D148 -> 42451140000 | E46: =+E148 -> 44868907000 | F46: =+F148 -> 112938995000 | G46: =+G148 -> -12149934000 | H46: =+H148 -> 68391131000 | I46: =+I148 -> 90202808000 | J46: =+J148 -> 83687787000 | ... N46: =+N148 -> 0
B47: Dividendos calendario | C47: =SUM(C49:C52) -> 7.14 | D47: =SUM(D49:D52) -> 28.59 | E47: =SUM(E49:E52) -> 15.1 | F47: =SUM(F49:F52) -> 35.58 | G47: =SUM(G49:G52) -> 22.721 | H47: =SUM(H49:H52) -> 23.033 | I47: =SUM(I49:I52) -> 24.166 | J47: =SUM(J49:J52) -> 26.089 | ... N47: =SUM(N49:N52) -> 0
B48: Dividendos sin eventual Calendario | C48: =+C49+C50+C51 -> 7.14 | D48: =+D49+D50+D51 -> 28.59 | E48: =+E49+E50+E51 -> 15.1 | F48: =+F49+F50+F51 -> 8.36 | G48: =+G49+G50+G51 -> 22.721 | H48: =+H49+H50+H51 -> 7.027 | I48: =+I49+I50+I51 -> 24.166 | J48: =+J49+J50+J51 -> 21.673 | ... N48: =+N49+N50+N51 -> 0
B49: Definitivo año calendario | C49: 7.14 | D49: 28.59 | E49: 15.1 | F49: 8.36 | G49: 5.754 | H49: 7.027 | I49: 8.48 | J49: =6.627+15.046 -> 21.673
B50: Provisorio calendario
B51: Adicional calendario | G51: 16.967 | I51: 15.686
B52: Eventual calendario | F52: 27.22 | H52: 16.006 | J52: 4.416
B53: Dividendos | C53: =SUM(C55:C58) -> 28.59 | D53: =SUM(D55:D58) -> 15.1 | E53: =SUM(E55:E58) -> 8.36 | F53: =SUM(F55:F58) -> 32.974 | G53: =SUM(G55:G58) -> 23.994 | H53: =SUM(H55:H58) -> 24.486 | I53: =SUM(I55:I58) -> 37.359 | J53: =SUM(J55:J58) -> 4.416 | ... N53: =SUM(N55:N58) -> 0
B54: Dividendos sin eventual | C54: =+C55+C56+C57 -> 28.59 | D54: =+D55+D56+D57 -> 15.1 | E54: =+E55+E56+E57 -> 8.36 | F54: =+F55+F56+F57 -> 5.754 | G54: =+G55+G56+G57 -> 23.994 | H54: =+H55+H56+H57 -> 8.48 | I54: =+I55+I56+I57 -> 37.359 | J54: =+J55+J56+J57 -> 0 | ... N54: =+N55+N56+N57 -> 0
B55: Definitivo | C55: 28.59 | D55: 15.1 | E55: 8.36 | F55: 5.754 | G55: 7.027 | H55: 8.48 | I55: =6.627+15.046 -> 21.673
B56: Provisorio
B57: Adicional | G57: 16.967 | I57: 15.686
B58: Eventual | F58: 27.22 | H58: 16.006 | J58: 4.416
B59: PAY OUT | C59: =(C55+C56+C57)/C43 -> 1.3871907 | D59: =(D55+D56+D57)/D43 -> 0.8384231 | E59: =(E55+E56+E57)/E43 -> 0.29996412 | F59: =(F55+F56+F57)/F43 -> 0.3 | G59: =(G55+G56+G57)/G43 -> 1.024509 | H59: =(H55+H56+H57)/H43 -> 0.29996463 | I59: =(I55+I56+I57)/I43 -> 1.0942882 | J59: =(J55+J56+J57)/J43 -> 0 | ... N59: =(N55+N56+N57)/N43 -> #DIV/0!
B60: PAY OUT PROMEDIO 3 AÑOS | C60: =AVERAGE(G59:I59) -> 0.80625394
B61: DIVIDEND YIELD AÑO | C61: =+C47/B23 -> #VALUE! | D61: =+D47/D23 -> 0.092999805 | E61: =+E47/E23 -> 0.054845271 | F61: =+F47/F23 -> 0.1419396 | G61: =+G47/G23 -> 0.090641082 | H61: =+H47/H23 -> 0.091885746 | I61: =+I47/I23 -> 0.096405633 | J61: =+J47/J23 -> 0.10407707 | K61: =+K47/K23 -> #DIV/0! | ... N61: =+N47/N23 -> #DIV/0!
B62: DIVIDEND YIEDL PROM 3 AÑOS | C62: =AVERAGE(H61:J61) -> 0.097456151
B63: G | C63: =+C44*(100%-C59) -> -0.054059315 | D63: =+D44*(100%-D59) -> 0.021169459 | E63: =+E44*(100%-E59) -> 0.13249432 | F63: =+F44*(100%-F59) -> 0.10062992 | G63: =+G44*(100%-G59) -> -0.0043223976 | H63: =+H44*(100%-H59) -> 0.14484338 | I63: =+I44*(100%-I59) -> -0.02222573 | J63: =+J44*(100%-J59) -> 0.21635069 | ... N63: =+N44*(100%-N59) -> #DIV/0!
B64: G PROMEDIO 3 AÑOS | C64: =AVERAGE(H63:J63) -> 0.11298945
B65: PRECIO | C65: =B3 -> 272.25
B67: ESTADO DE SITUACIÓN (BALANCE)
B69: AÑOS | C69: 2017 | D69: 2018 | E69: 2019 | F69: 2020 | G69: 2021 | H69: 2022 | I69: 2023 | J69: 2023 | K69: 2023 | L69: 2023 | M69: 2023 | N69: 2023
B70: ACTIVOS
B71: CORRIENTES (CIRCULANTES) | C71: 106835735000 | D71: 74152970000 | E71: 75692564000 | F71: 90664627000 | G71: 63045514000 | H71: 47079707000 | I71: 95023798000 | J71: 122681361000
B72: EFECTIVO Y EQUIVALENTE | C72: 100613794000 | D72: 57257018000 | E72: 51694904000 | F72: 66322752000 | G72: 28832104000 | H72: 32391568000 | I72: 49820636000 | J72: 57182645000
B73: ACTIVOS FINANCIEROS A VALOR RAZONABLE CON CAMBIOS EN RESULTADOS | H73: 0 | I73: 28246903000 | J73: 50462173000
B74: CUENTAS POR COBRAR CORRIENTES | C74: 2981045000 | D74: 3533256000 | E74: 3835771000 | F74: 7858108000 | G74: 10344488000 | H74: 12241330000 | I74: 12434324000 | J74: 13480702000
B75: CUENTAS POR COBRAR ENTIDADES RELACIONADAS | C75: 4096000 | G75: 0 | H75: 62928000 | I75: 2789784000 | J75: 30255000
B76: PAGOS ANTICIPADOS | C76: 1115282000 | D76: 1569723000 | E76: 2459604000 | F76: 1988906000 | G76: 1187311000 | H76: 2242157000 | I76: 1277855000 | J76: 1196354000
B77: CUENTAS POR COBRAR POR IMPUESTOS CORRIENTES | C77: 1955082000 | D77: 11311631000 | E77: 17382860000 | F77: 14090356000 | G77: 21713326000 | H77: 0 | I77: 0
B78: OTROS ACTIVOS CORRIENTES | C78: 166436000 | D78: 481342000 | E78: 319425000 | F78: 404505000 | G78: 968285000 | H78: 141724000 | I78: 454296000 | J78: 329232000
B79: OTROS CORRIENTES | C79: =+C71-C72-C74-C75-C76-C77-C78 -> 0 | D79: =+D71-D72-D74-D75-D76-D77-D78 -> 0 | E79: =+E71-E72-E74-E75-E76-E77-E78 -> 0 | F79: =+F71-F72-F74-F75-F76-F77-F78 -> 0 | G79: =+G71-G72-G74-G75-G76-G77-G78 -> 0 | H79: =+H71-H72-H74-H75-H76-H77-H78-H73 -> 0 | I79: =+I71-I72-I74-I75-I76-I77-I78-I73 -> 0 | J79: 0 | K79: =+K71-K72-K74-K75-K76-K77-K78 -> 0 | L79: =+L71-L72-L74-L75-L76-L77-L78 -> 0 | M79: =+M71-M72-M74-M75-M76-M77-M78 -> 0 | N79: =+N71-N72-N74-N75-N76-N77-N78 -> 0
B80: NO CORRIENTES (NO CIRCULANTES) | C80: 452454294000 | D80: 457699233000 | E80: 516817122000 | F80: 521204053000 | G80: 494282056000 | H80: 499374563000 | I80: 522497691000 | J80: 555132195000
B81: ENCAJE | C81: 247403057000 | D81: 254201735000 | E81: 305961667000 | F81: 308725396000 | G81: 284461896000 | H81: 295637992000 | I81: 321203585000 | J81: 346285329000
B82: Otros activos financieros | C82: 5104000 | D82: 4011000 | E82: 2782000 | F82: 1605000 | G82: 314000
B83: Inversiones en coligadas contabilizadas por el método de la participación | C83: 7135158000 | D83: 7146159000 | E83: 7636620000 | F83: 7962609000 | G83: 8551895000 | H83: 7946925000 | I83: 7558818000 | J83: 7985569000
B84: Activos intangibles, Neto | C84: 187962187000 | D84: 187572055000 | E84: 187542539000 | F84: 188298526000 | G84: 188191450000 | H84: 188000173000 | I84: 188488444000 | J84: 187630376000
B85: PROPIEDADES, PLANTAS Y EQUIPOS | C85: 5021394000 | D85: 4855969000 | E85: 10648564000 | F85: 10265233000 | G85: 8290403000 | H85: 6482818000 | I85: 4432321000 | J85: 12232266000
B86: Activos por impuestos diferidos | C86: 2734371000 | D86: 2106780000 | E86: 3471722000 | F86: 4327044000 | G86: 2996628000 | H86: 0 | I86: 0
B87: Pagos anticipados | C87: 2147940000 | D87: 1766598000 | E87: 1501062000 | F87: 1270285000 | G87: 1436805000 | H87: 1043602000 | I87: 556231000 | J87: 710228000
B88: Efectivo de utilización restringida o afectados en garantía | C88: 45083000 | D88: 45926000 | E88: 52166000 | F88: 353355000 | G88: 352665000 | H88: 263053000 | I88: 258292000 | J88: 288427000
B89: OTROS NO CORRIENTES | C89: =+C80-C83-C84-C85-C82-C81-C86-C87-C88 -> 0 | D89: =+D80-D83-D84-D85-D82-D81-D86-D87-D88 -> 0 | E89: =+E80-E83-E84-E85-E82-E81-E86-E87-E88 -> 0 | F89: =+F80-F83-F84-F85-F82-F81-F86-F87-F88 -> 0 | G89: =+G80-G83-G84-G85-G82-G81-G86-G87-G88 -> 0 | H89: =+H80-H83-H84-H85-H82-H81-H86-H87-H88 -> 0 | I89: =+I80-I83-I84-I85-I82-I81-I86-I87-I88 -> 0 | J89: 0 | K89: =+K80-K83-K84-K85-K82-K81-K86-K87-K88 -> 0 | L89: =+L80-L83-L84-L85-L82-L81-L86-L87-L88 -> 0 | M89: =+M80-M83-M84-M85-M82-M81-M86-M87-M88 -> 0 | N89: =+N80-N83-N84-N85-N82-N81-N86-N87-N88 -> 0
B90: TOTAL ACTIVOS | C90: =+C80+C71 -> 559290029000 | D90: =+D80+D71 -> 531852203000 | E90: =+E80+E71 -> 592509686000 | F90: =+F80+F71 -> 611868680000 | G90: =+G80+G71 -> 557327570000 | H90: =+H80+H71 -> 546454270000 | I90: =+I80+I71 -> 617521489000 | J90: 677813556000 | K90: =+K80+K71 -> 0 | L90: =+L80+L71 -> 0 | M90: =+M80+M71 -> 0 | N90: =+N80+N71 -> 0
B92: PASIVOS
B93: CORRIENTES (CIRCULANTES) | C93: 49180754000 | D93: 51453291000 | E93: 62973146000 | F93: 122980590000 | G93: 75496876000 | H93: 55396016000 | I93: 95915328000 | J93: 121562114000
B94: Préstamos que devengan intereses | C94: 362144000 | D94: 369308000 | E94: 205143000 | F94: 1688890000 | G94: 456554000 | H94: 1799208000 | I94: 636438000 | J94: 2545420000
B95: Acreedores comerciales y otras cuentas por pagar | C95: 11174095000 | D95: 11277812000 | E95: 11539257000 | F95: 78012988000 | G95: 17592620000 | H95: 20517783000 | I95: 49795001000 | J95: 77458983000
B96: cuentas por pagar a entidades relacionadas | C96: 275299000 | D96: 230251000 | E96: 565720000 | F96: 671477000 | G96: 143783000 | H96: 141080000 | I96: 135836000 | J96: 166669000
B97: Provisiones | C97: 3432439000 | D97: 3525823000 | E97: 3634438000 | F97: 4374405000 | G97: 5373753000 | H97: 5067543000 | I97: 5944316000 | J97: 7991459000
B98: Cuentas por pagar por impuestos corrientes | C98: 13358327000 | D98: 18084548000 | E98: 19654874000 | F98: 18883064000 | G98: 28679924000 | H98: 189671000 | I98: 5670395000 | J98: 984514000
B99: Otros pasivos corrientes | C99: 19360277000 | D99: 17063291000 | E99: 26294989000 | F99: 18055717000 | G99: 22063303000 | H99: 26618071000 | I99: 32110908000 | J99: 31017854000
B100: Pasivos acumulados (o devengados) | C100: 1218173000 | D100: 902258000 | E100: 1078725000 | F100: 1294049000 | G100: 1186939000 | H100: 1062660000 | I100: 1622434000 | J100: 1397215000
B101: Otros | C101: =+C93-C94-C95-C96-C97-C98-C100-C99 -> 0 | D101: =+D93-D94-D95-D96-D97-D98-D100-D99 -> 0 | E101: =+E93-E94-E95-E96-E97-E98-E100-E99 -> 0 | F101: =+F93-F94-F95-F96-F97-F98-F100-F99 -> 0 | G101: =+G93-G94-G95-G96-G97-G98-G100-G99 -> 0 | H101: =+H93-H94-H95-H96-H97-H98-H100-H99 -> 0 | I101: =+I93-I94-I95-I96-I97-I98-I100-I99 -> 0 | J101: 0 | K101: =+K93-K94-K95-K96-K97-K98-K100-K99 -> 0 | L101: =+L93-L94-L95-L96-L97-L98-L100-L99 -> 0 | M101: =+M93-M94-M95-M96-M97-M98-M100-M99 -> 0 | N101: =+N93-N94-N95-N96-N97-N98-N100-N99 -> 0
B102: NO CORRIENTES (NO CIRCULANTES) | C102: 50100031000 | D102: 51014275000 | E102: 69621044000 | F102: 72124110000 | G102: 66972919000 | H102: 64324540000 | I102: 69239170000 | J102: 81498345000
B103: Préstamos que devengan intereses | C103: 520126000 | D103: 180387000 | E103: 5636777000 | F103: 4308382000 | G103: 3020660000 | H103: 475082000 | I103: 85164000 | J103: 5948206000
B104: Pasivos por impuestos diferidos | C104: 49578669000 | D104: 50832455000 | E104: 63982795000 | F104: 67814216000 | G104: 63918300000 | H104: 63787826000 | I104: 69092550000 | J104: 75459116000
B105: Otros pasivos no corrientes | C105: 1236000 | D105: 1433000 | E105: 1472000 | F105: 1512000 | G105: 33959000 | H105: 61632000 | I105: 61456000 | J105: 91023000
B107: OTROS PASIVOS NO CORRIENTES | C107: =+C102-C103-C104-C105-C106 -> 0 | D107: =+D102-D103-D104-D105-D106 -> 0 | E107: =+E102-E103-E104-E105-E106 -> 0 | F107: =+F102-F103-F104-F105-F106 -> 0 | G107: =+G102-G103-G104-G105-G106 -> 0 | H107: =+H102-H103-H104-H105-H106 -> 0
B108: TOTAL PASIVOS | C108: =+C102+C93 -> 99280785000 | D108: =+D102+D93 -> 102467566000 | E108: =+E102+E93 -> 132594190000 | F108: =+F102+F93 -> 195104700000 | G108: =+G102+G93 -> 142469795000 | H108: =+H102+H93 -> 119720556000 | I108: =+I102+I93 -> 165154498000 | J108: 203060459000 | K108: =+K102+K93 -> 0 | L108: =+L102+L93 -> 0 | M108: =+M102+M93 -> 0 | N108: =+N102+N93 -> 0
B110: PATRIMONIO
B111: Capital | C111: 348671861000 | D111: 348671861000 | E111: 348671861000 | F111: 348671861000 | G111: 348671861000 | H111: 348671861000 | I111: 348671861000 | J111: 348671861000
...

Sheet AGUAS-A
B2: =TODAY()-1 -> 46105 | D2: PROM DIVIDENDOS SIN ADIC/EVENT | E2: PROM DIVIDENDOS TOTALES
B3: {=_FV(B6,"Precio")} -> 347 | D3: =AVERAGE(G45:I45) -> 9.0020033 | E3: =AVERAGE(G44:I44) -> 14.895003
B6: #VALUE! | C6: 2017 | D6: 2018 | E6: 2019 | F6: 2020 | G6: 2021 | H6: 2022 | I6: 2023 | J6: 2024 | K6: 2025 | L6: 2026 | M6: 2027 | N6: 2028
B7: Activos corrientes | C7: =+C61 -> 150618761000 | D7: =+D61 -> 168513972000 | E7: =+E61 -> 197676646000 | F7: =+F61 -> 302254499000 | G7: =+G61 -> 283854689000 | H7: =+H61 -> 324838124000 | I7: =+I61 -> 275000996000 | J7: =+J61 -> 0 | ... N7: =+N61 -> 0
B8: Cuentas por cobrar | C8: =+C65 -> 113515790000 | D8: =+D65 -> 116821062000 | E8: =+E65 -> 115937498000 | F8: =+F65 -> 87482681000 | G8: =+G65 -> 101105786000 | H8: =+H65 -> 122777327000 | I8: =+I65 -> 132007468000 | J8: =+J65 -> 0 | ... N8: =+N65 -> 0
B9: Inventario | C9: =+C67 -> 3925378000 | D9: =+D67 -> 3636388000 | E9: =+E67 -> 3810599000 | F9: =+F67 -> 3954953000 | G9: =+G67 -> 5185858000 | H9: =+H67 -> 12790532000 | I9: =+I67 -> 12812483000 | J9: =+J67 -> 0 | ... N9: =+N67 -> 0
B10: Acitvos no corrientes (no circulantes o fijos) | C10: =+C70 -> 1646261375000 | D10: =+D70 -> 1737538127000 | E10: =+E70 -> 1803767656000 | F10: =+F70 -> 1842181989000 | G10: =+G70 -> 1945366921000 | H10: =+H70 -> 2054511436000 | I10: =+I70 -> 2148343319000 | J10: =+J70 -> 0 | ... N10: =+N70 -> 0
B11: Activos totales | C11: =+C10+C7 -> 1796880136000 | D11: =+D10+D7 -> 1906052099000 | E11: =+E10+E7 -> 2001444302000 | F11: =+F10+F7 -> 2144436488000 | G11: =+G10+G7 -> 2229221610000 | H11: =+H10+H7 -> 2379349560000 | I11: =+I10+I7 -> 2423344315000 | J11: =+J10+J7 -> 0 | ... N11: =+N10+N7 -> 0
B12: Pasivos corrientes | C12: =+C84 -> 237111903000 | D12: =+D84 -> 242318524000 | E12: =+E84 -> 242137717000 | F12: =+F84 -> 244032589000 | G12: =+G84 -> 248642211000 | H12: =+H84 -> 265797147000 | I12: =+I84 -> 361668126000 | J12: =+J84 -> 0 | ... N12: =+N84 -> 0
B13: Pasivos no corrientes | C13: =+C94 -> 866468756000 | D13: =+D94 -> 976742178000 | E13: =+E94 -> 1071833122000 | F13: =+F94 -> 1059655092000 | G13: =+G94 -> 1138031686000 | H13: =+H94 -> 1274661314000 | I13: =+I94 -> 1175540305000 | J13: =+J94 -> 0 | ... N13: =+N94 -> 0
B14: Total Pasivos | C14: =+C12+C13 -> 1103580659000 | D14: =+D12+D13 -> 1219060702000 | E14: =+E12+E13 -> 1313970839000 | F14: =+F12+F13 -> 1303687681000 | G14: =+G12+G13 -> 1386673897000 | H14: =+H12+H13 -> 1540458461000 | I14: =+I12+I13 -> 1537208431000 | J14: =+J12+J13 -> 0 | ... N14: =+N12+N13 -> 0
B15: Patrimonio | C15: =+C109 -> 642630776000 | D15: =+D109 -> 638620196000 | E15: =+E109 -> 644453334000 | F15: =+F109 -> 840723242000 | G15: =+G109 -> 842520215000 | H15: =+H109 -> 838861526000 | I15: =+I109 -> 886107830000 | J15: =+J109 -> 0 | ... N15: =+N109 -> 0
B16: Cantidad de acciones | C16: 6118965160 | D16: 6118965160 | E16: 6118965160 | F16: 6118965160 | G16: 6118965160 | H16: 6118965160 | I16: 6118965160
B18: Valor libro | C18: =(C15/C16) -> 105.02279 | D18: =(D15/D16) -> 104.36735 | E18: =(E15/E16) -> 105.32064 | F18: =(F15/F16) -> 137.39631 | G18: =(G15/G16) -> 137.68998 | H18: =(H15/H16) -> 137.09206 | I18: =(I15/I16) -> 144.81335 | J18: =(J15/J16) -> #DIV/0! | ... N18: =(N15/N16) -> #DIV/0!
B19: Precio FIN AÑO | C19: 407.5 | D19: 382 | E19: 319 | F19: 229 | G19: 155 | H19: 196 | I19: 284.6
B20: PER | C20: =+C19/C40 -> 17.858708 | D20: =+D19/D40 -> 17.180121 | E20: =+E19/E40 -> 13.771369 | F20: =+F19/F40 -> 14.198028 | G20: =+G19/G40 -> 9.4236381 | H20: =+H19/H40 -> 14.068332 | I20: =+I19/I40 -> 13.055046 | J20: =+J19/J40 -> #DIV/0! | ... N20: =+N19/N40 -> #DIV/0!
B21: Bolsa/Libro | C21: =+C19/C18 -> 3.8801103 | D21: =+D19/D18 -> 3.6601484 | E21: =+E19/E18 -> 3.028846 | F21: =+F19/F18 -> 1.6667114 | G21: =+G19/G18 -> 1.1257173 | H21: =+H19/H18 -> 1.4296962 | I21: =+I19/I18 -> 1.9652885 | J21: =+J19/J18 -> #DIV/0! | ... N21: =+N19/N18 -> #DIV/0!
B22: GRAHAM | C22: =+C20*C21 -> 69.293757 | D22: =+D20*D21 -> 62.881794 | E22: =+E20*E21 -> 41.711357 | F22: =+F20*F21 -> 23.664016 | G22: =+G20*G21 -> 10.608353 | H22: =+H20*H21 -> 20.113441 | I22: =+I20*I21 -> 25.656931 | J22: =+J20*J21 -> #DIV/0! | ... N22: =+N20*N21 -> #DIV/0!
B23: Bolsa Libro Banda Menor | C23: =IF(C41<10%,0,IF(15%<C41,2,1)) -> 2 | D23: =IF(D41<10%,0,IF(15%<D41,2,1)) -> 2 | E23: =IF(E41<10%,0,IF(15%<E41,2,1)) -> 2 | F23: =IF(F41<10%,0,IF(15%<F41,2,1)) -> 1 | G23: =IF(G41<10%,0,IF(15%<G41,2,1)) -> 1 | H23: =IF(H41<10%,0,IF(15%<H41,2,1)) -> 1 | I23: =IF(I41<10%,0,IF(15%<I41,2,1)) -> 2 | J23: =IF(J41<10%,0,IF(15%<J41,2,1)) -> #DIV/0! | ... N23: =IF(N41<10%,0,IF(15%<N41,2,1)) -> #DIV/0!
B24: Bolsa Libro Banda Mayor | C24: =IF(C41<10%,1,IF(15%<C41,2.5,2)) -> 2.5 | D24: =IF(D41<10%,1,IF(15%<D41,2.5,2)) -> 2.5 | E24: =IF(E41<10%,1,IF(15%<E41,2.5,2)) -> 2.5 | F24: =IF(F41<10%,1,IF(15%<F41,2.5,2)) -> 2 | G24: =IF(G41<10%,1,IF(15%<G41,2.5,2)) -> 2 | H24: =IF(H41<10%,1,IF(15%<H41,2.5,2)) -> 2 | I24: =IF(I41<10%,1,IF(15%<I41,2.5,2)) -> 2.5 | J24: =IF(J41<10%,1,IF(15%<J41,2.5,2)) -> #DIV/0! | ... N24: =IF(N41<10%,1,IF(15%<N41,2.5,2)) -> #DIV/0!
B25: Precio Objetivo Menor | C25: =+C23*C18 -> 210.04557 | D25: =+D23*D18 -> 208.73471 | E25: =+E23*E18 -> 210.64128 | F25: =+F23*F18 -> 137.39631 | G25: =+G23*G18 -> 137.68998 | H25: =+H23*H18 -> 137.09206 | I25: =+I23*I18 -> 289.6267 | J25: =+J23*J18 -> #DIV/0! | ... N25: =+N23*N18 -> #DIV/0!
B26: Precio Obejtivo Promedio | C26: =AVERAGE(C25,C27) -> 236.30127 | D26: =AVERAGE(D25,D27) -> 234.82654 | E26: =AVERAGE(E25,E27) -> 236.97144 | F26: =AVERAGE(F25,F27) -> 206.09447 | G26: =AVERAGE(G25,G27) -> 206.53498 | H26: =AVERAGE(H25,H27) -> 205.63809 | I26: =AVERAGE(I25,I27) -> 325.83003 | J26: =AVERAGE(J25,J27) -> #DIV/0! | ... N26: =AVERAGE(N25,N27) -> #DIV/0!
B27: Precio Objetivo Mayor | C27: =+C18*C24 -> 262.55697 | D27: =+D18*D24 -> 260.91838 | E27: =+E18*E24 -> 263.3016 | F27: =+F18*F24 -> 274.79262 | G27: =+G18*G24 -> 275.37997 | H27: =+H18*H24 -> 274.18412 | I27: =+I18*I24 -> 362.03337 | J27: =+J18*J24 -> #DIV/0! | ... N27: =+N18*N24 -> #DIV/0!
B29: Capital de Trabajo | C29: =C7-C12 -> -86493142000 | D29: =D7-D12 -> -73804552000 | E29: =E7-E12 -> -44461071000 | F29: =F7-F12 -> 58221910000 | G29: =G7-G12 -> 35212478000 | H29: =H7-H12 -> 59040977000 | I29: =I7-I12 -> -86667130000 | J29: =J7-J12 -> 0 | ... N29: =N7-N12 -> 0
B30: Razón corriente | C30: =C7/C12 -> 0.63522227 | D30: =D7/D12 -> 0.6954234 | E30: =E7/E12 -> 0.81638106 | F30: =F7/F12 -> 1.2385825 | G30: =G7/G12 -> 1.1416191 | H30: =H7/H12 -> 1.222128 | I30: =I7/I12 -> 0.76036835 | J30: =J7/J12 -> #DIV/0! | ... N30: =N7/N12 -> #DIV/0!
B31: Razón ácida | C31: =+(C7-C9)/C12 -> 0.61866731 | D31: =+(D7-D9)/D12 -> 0.68041676 | E31: =+(E7-E9)/E12 -> 0.80064374 | F31: =+(F7-F9)/F12 -> 1.2223759 | G31: =+(G7-G9)/G12 -> 1.1207624 | H31: =+(H7-H9)/H12 -> 1.1740066 | I31: =+(I7-I9)/I12 -> 0.72494227 | J31: =+(J7-J9)/J12 -> #DIV/0! | ... N31: =+(N7-N9)/N12 -> #DIV/0!
B32: Razón de endeudamiento | C32: =C14/C11 -> 0.61416487 | D32: =D14/D11 -> 0.63957365 | E32: =E14/E11 -> 0.65651132 | F32: =F14/F11 -> 0.60793952 | G32: =G14/G11 -> 0.62204399 | H32: =H14/H11 -> 0.64742839 | I32: =I14/I11 -> 0.63433348 | J32: =J14/J11 -> #DIV/0! | ... N32: =N14/N11 -> #DIV/0!
B35: Ingresos | C35: =+C114 -> 509540577000 | D35: =+D114 -> 530404680000 | E35: =+E114 -> 484329084000 | F35: =+F114 -> 478773563000 | G35: =+G114 -> 506459633000 | H35: =+H114 -> 575465445000 | I35: =+I114 -> 640855854000 | J35: =+J114 -> 0 | ... N35: =+N114 -> 0
B36: EBIT | C36: =+C122 -> 226819054000 | D36: =+D122 -> 233071676000 | E36: =+E122 -> 235636236000 | F36: =+F122 -> 162824880000 | G36: =+G122 -> 212947803000 | H36: =+H122 -> 228258340000 | I36: =+I122 -> 256251484000 | J36: =+J122 -> 0 | ... N36: =+N122 -> 0
B37: Margen EBIT | C37: =C36/C35 -> 0.44514424 | D37: =D36/D35 -> 0.43942236 | E37: =E36/E35 -> 0.48652093 | F37: =F36/F35 -> 0.34008745 | G37: =G36/G35 -> 0.42046353 | H37: =H36/H35 -> 0.39664995 | I37: =I36/I35 -> 0.39985822 | J37: =J36/J35 -> #DIV/0! | ... N37: =N36/N35 -> #DIV/0!
B38: Utilidad neta | C38: =+C133 -> 139620280000 | D38: =+D133 -> 136056517000 | E38: =+E133 -> 141737188000 | F38: =+F133 -> 98691668000 | G38: =+G133 -> 100644529000 | H38: =+H133 -> 85248734000 | I38: =+I133 -> 133390421000 | J38: =+J133 -> 0 | ... N38: =+N133 -> 0
B39: Margen neto porcentual | C39: =C38/C35 -> 0.27401209 | D39: =D38/D35 -> 0.25651455 | E39: =E38/E35 -> 0.29264645 | F39: =F38/F35 -> 0.20613433 | G39: =G38/G35 -> 0.19872172 | H39: =H38/H35 -> 0.14813875 | I39: =I38/I35 -> 0.20814419 | J39: =J38/J35 -> #DIV/0! | ... N39: =N38/N35 -> #DIV/0!
B40: EPS | C40: =+C134 -> 22.818 | D40: =+D134 -> 22.235 | E40: =+E134 -> 23.164 | F40: =+F134 -> 16.129 | G40: =+G134 -> 16.448 | H40: =+H134 -> 13.932 | I40: =+I134 -> 21.8 | J40: =+J134 -> 0 | ... N40: =+N134 -> 0
B41: ROE | C41: =C38/C15 -> 0.21726361 | D41: =D38/D15 -> 0.21304763 | E41: =E38/E15 -> 0.21993398 | F41: =F38/F15 -> 0.11738901 | G41: =G38/G15 -> 0.11945652 | H41: =H38/H15 -> 0.10162432 | I41: =I38/I15 -> 0.1505352 | J41: =J38/J15 -> #DIV/0! | ... N41: =N38/N15 -> #DIV/0!
B42: ROE PROMEDIO | C42: =AVERAGE(G41:I41) -> 0.12387201
B43: FCF | C43: =+C146 -> 101170091000 | D43: =+D146 -> 108261532000 | E43: =+E146 -> 94891034000 | F43: =+F146 -> 36288731000 | G43: =+G146 -> 69607469000 | H43: =+H146 -> 81536376000 | I43: =+I146 -> 79751783000 | J43: =+J146 -> 0 | ... N43: =+N146 -> 0
B44: Dividendos | C44: =SUM(C46:C49) -> 22.118 | D44: =SUM(D46:D49) -> 22.49966 | E44: =SUM(E46:E49) -> 21.7114 | F44: =SUM(F46:F49) -> 17.852 | G44: =SUM(G46:G49) -> 17.189 | H44: =SUM(H46:H49) -> 12.747 | I44: =SUM(I46:I49) -> 14.74901 | J44: =SUM(J46:J49) -> 0 | ... N44: =SUM(N46:N49) -> 0
B45: Dividendos sin Adic/Event | C45: =+C46+C47 -> 6.861 | D45: =+D46+D47 -> 22.49966 | E45: =+E46+E47 -> 21.7114 | F45: =+F46+F47 -> 17.852 | G45: =+G46+G47 -> 6.537 | H45: =+H46+H47 -> 5.72 | I45: =+I46+I47 -> 14.74901 | J45: =+J46+J47 -> 0 | ... N45: =+N46+N47 -> 0
B46: Definitivo | D46: 15.63866 | E46: 14.6474 | I46: 8.21196
B47: Provisorio | C47: 6.861 | D47: 6.861 | E47: 7.064 | F47: =10.59+7.262 -> 17.852 | G47: 6.537 | H47: 5.72 | I47: 6.53705
B48: Adicional | C48: 15.257 | G48: 4.371 | H48: 7.027
B49: Eventual | G49: 6.281
B50: PAY OUT | C50: =(C47+C48+D46)/C40 -> 1.6546875 | D50: =(D47+D48+E46)/D40 -> 0.96732179 | E50: =(E47+E48+F46)/E40 -> 0.30495597 | F50: =(F47+F48+G46)/F40 -> 1.1068262 | G50: =(G47+G48+H46)/G40 -> 0.66318093 | H50: =(H47+H48+I46)/H40 -> 1.5043755 | I50: =(I47+I48+J46)/I40 -> 0.29986468 | J50: =(J47+J48+K46)/J40 -> #DIV/0! | ... N50: =(N47+N48+O46)/N40 -> #DIV/0!
B51: PAY OUT PROMEDIO 3 AÑOS | C51: =AVERAGE(G50:I50) -> 0.82247372
B52: DIV/YIELD | C52: =+C44/C19 -> 0.054277301 | D52: =+D44/D19 -> 0.058899634 | E52: =+E44/E19 -> 0.068060815 | F52: =+F44/F19 -> 0.077956332 | G52: =+G44/G19 -> 0.11089677 | H52: =+H44/H19 -> 0.065035714 | I52: =+I44/I19 -> 0.051823647 | J52: =+J44/J19 -> #DIV/0! | ... N52: =+N44/N19 -> #DIV/0!
B53: DIVIDEND YIELD PROM 3 AÑOS | C53: =AVERAGE(G52:I52) -> 0.075918712
B54: G | C54: =+C41*(100%-C50) -> -0.14223977 | D54: =+D41*(100%-D50) -> 0.0069620151 | E54: =+E41*(100%-E50) -> 0.1528638 | F54: =+F41*(100%-F50) -> -0.012540223 | G54: =+G41*(100%-G50) -> 0.040235232 | H54: =+H41*(100%-H50) -> -0.051256822 | I54: =+I41*(100%-I50) -> 0.10539501 | J54: =+J41*(100%-J50) -> #DIV/0! | ... N54: =+N41*(100%-N50) -> #DIV/0!
B55: G PROMEDIO 3 AÑOS | C55: =AVERAGE(G54:I54) -> 0.031457807
B57: ESTADO DE SITUACIÓN (BALANCE)
B59: AÑOS | C59: 2017 | D59: 2018 | E59: 2019 | F59: 2020 | G59: 2021 | H59: 2022 | I59: 2023 | J59: 2024 | K59: 2025 | L59: 2026 | M59: 2027 | N59: 2028
B60: ACTIVOS
B61: CORRIENTES (CIRCULANTES) | C61: 150618761000 | D61: 168513972000 | E61: 197676646000 | F61: 302254499000 | G61: 283854689000 | H61: 324838124000 | I61: 275000996000
B62: Efectivo y equivalentes al efectivo
B63: Otros activos financieros, corrientes
B64: Otros activos no financieros, corrientes
B65: Deudores comerciales y otras cuentas por cobrar, corrientes | C65: 113515790000 | D65: 116821062000 | E65: 115937498000 | F65: 87482681000 | G65: 101105786000 | H65: 122777327000 | I65: 132007468000
B66: Cuentas por cobrar entidades relacionadas, corriente neto
B67: Inventarios, neto | C67: 3925378000 | D67: 3636388000 | E67: 3810599000 | F67: 3954953000 | G67: 5185858000 | H67: 12790532000 | I67: 12812483000
B68: Activos por impuestos corrientes
B69: OTROS CORRIENTES | C69: =+C61-C62-C67-C68-C66-C65-C64-C63 -> 33177593000 | D69: =+D61-D62-D67-D68-D66-D65-D64-D63 -> 48056522000 | E69: =+E61-E62-E67-E68-E66-E65-E64-E63 -> 77928549000 | F69: =+F61-F62-F67-F68-F66-F65-F64-F63 -> 210816865000 | G69: =+G61-G62-G67-G68-G66-G65-G64-G63 -> 177563045000 | H69: =+H61-H62-H67-H68-H66-H65-H64-H63 -> 189270265000 | I69: =+I61-I62-I67-I68-I66-I65-I64-I63 -> 130181045000
B70: NO CORRIENTES (NO CIRCULANTES) | C70: 1646261375000 | D70: 1737538127000 | E70: 1803767656000 | F70: 1842181989000 | G70: 1945366921000 | H70: 2054511436000 | I70: 2148343319000
B71: Otros activos financieros, no corrientes
B72: Otros activos no financieros, no corrientes
B73: Inversiones en asociadas
B74: Plusvalía
B75: Activos intangibles distintos a la plusvalía
B76: Propiedades, plantas y equipos | C76: 1351763816000 | D76: 1440093131000 | E76: 1495658317000 | F76: 1568189347000 | G76: 1660157909000 | H76: 1713896622000 | I76: 1805370932000
B77: Propiedades de inversión
B78: Activos por derecho de uso
B79: Activos por impuestos diferidos
B80: OTROS NO CORRIENTES | C80: =+C70-C77-C78-C76-C71-C79-C75-C74-C73-C72 -> 294497559000 | D80: =+D70-D77-D78-D76-D71-D79-D75-D74-D73-D72 -> 297444996000 | E80: =+E70-E77-E78-E76-E71-E79-E75-E74-E73-E72 -> 308109339000 | F80: =+F70-F77-F78-F76-F71-F79-F75-F74-F73-F72 -> 273992642000 | G80: =+G70-G77-G78-G76-G71-G79-G75-G74-G73-G72 -> 285209012000 | H80: =+H70-H77-H78-H76-H71-H79-H75-H74-H73-H72 -> 340614814000 | I80: =+I70-I77-I78-I76-I71-I79-I75-I74-I73-I72 -> 342972387000
B81: TOTAL ACTIVOS | C81: =+C70+C61 -> 1796880136000 | D81: =+D70+D61 -> 1906052099000 | E81: =+E70+E61 -> 2001444302000 | F81: =+F70+F61 -> 2144436488000 | G81: =+G70+G61 -> 2229221610000 | H81: =+H70+H61 -> 2379349560000 | I81: =+I70+I61 -> 2423344315000
B83: PASIVOS
B84: CORRIENTES (CIRCULANTES) | C84: 237111903000 | D84: 242318524000 | E84: 242137717000 | F84: 244032589000 | G84: 248642211000 | H84: 265797147000 | I84: 361668126000
B85: Otros pasivos financieros, corrientes | H85: 74347139000 | I85: 155416801000
B86: Pasivos por arrendamientos, corrientes
B87: Otros pasivos no financieros
B88: Cuentas por pagar comerciales y otras cuentas por pagar | C88: 105645880000 | D88: 136872967000 | E88: 132451851000 | F88: 98758134000 | G88: 126774156000 | H88: 138331675000 | I88: 177288051000
B89: Cuentas por pagar entidades relacionadas
B90: Otras provisiones
B91: Pasivos por impuestos corrientes
B92: Provisiones por beneficios a los empleados, corrientes
B93: Otros | C93: =+C84-C85-C91-C92-C90-C89-C88-C87-C86 -> 131466023000 | D93: =+D84-D85-D91-D92-D90-D89-D88-D87-D86 -> 105445557000 | E93: =+E84-E85-E91-E92-E90-E89-E88-E87-E86 -> 109685866000 | F93: =+F84-F85-F91-F92-F90-F89-F88-F87-F86 -> 145274455000 | G93: =+G84-G85-G91-G92-G90-G89-G88-G87-G86 -> 121868055000 | H93: =+H84-H85-H91-H92-H90-H89-H88-H87-H86 -> 53118333000 | I93: =+I84-I85-I91-I92-I90-I89-I88-I87-I86 -> 28963274000
B94: NO CORRIENTES (NO CIRCULANTES) | C94: 866468756000 | D94: 976742178000 | E94: 1071833122000 | F94: 1059655092000 | G94: 1138031686000 | H94: 1274661314000 | I94: 1175540305000
B95: Otros pasivos financieros, no corrientes
B96: Pasivos por arrendamientos, no corrientes
B97: Pasivos por impuestos diferidos, no corrientes
B98: Provisiones por beneficios a los empleados, no corrientes
B99: OTROS PASIVOS NO CORRIENTES | C99: =+C94-C95-C97-C98-C96 -> 866468756000 | D99: =+D94-D95-D97-D98-D96 -> 976742178000 | E99: =+E94-E95-E97-E98-E96 -> 1071833122000 | F99: =+F94-F95-F97-F98-F96 -> 1059655092000 | G99: =+G94-G95-G97-G98-G96 -> 1138031686000 | H99: =+H94-H95-H97-H98-H96 -> 1274661314000 | I99: 1125060897000
B100: TOTAL PASIVOS | C100: =+C94+C84 -> 1103580659000 | D100: =+D94+D84 -> 1219060702000 | E100: =+E94+E84 -> 1313970839000 | F100: =+F94+F84 -> 1303687681000 | G100: =+G94+G84 -> 1386673897000 | H100: =+H94+H84 -> 1540458461000 | I100: =+I94+I84 -> 1537208431000
B102: PATRIMONIO
B103: Capital Pagado | C103: 155567354000 | D103: 155567354000 | E103: 155567354000 | F103: 155567354000 | G103: 155567354000 | H103: 155567354000 | I103: 155567354000
B104: Ganancias Acumuladas | C104: 328964934000 | D104: 324954354000 | E104: 330787492000 | F104: 364961863000 | G104: 361776346000 | H104: 362648832000 | I104: 411044222000
B105: Primas de emisión | C105: 164064038000 | D105: 164064038000 | E105: 164064038000 | F105: 164064038000 | G105: 164064038000 | H105: 164064038000 | I105: 164064038000
B106: Otras participaciones en el patrimonio | C106: -5965550000 | D106: -5965550000 | E106: -5965550000 | F106: -5965550000 | G106: -5965550000 | H106: -5965550000 | I106: -5965550000
B107: Otras Reservas | E107: 0 | F107: 162095537000 | G107: 167078027000 | H107: 162546852000 | I107: 161397766000
B108: Participación NO controladora | C108: 50668701000 | D108: 48370742000 | E108: 43020129000 | F108: 25565000 | G108: 27498000 | H108: 29573000 | I108: 31468000
B109: TOTAL PATRIMONIO CONTROLADORA | C109: =+C103+C107+C104+C105+C106 -> 642630776000 | D109: =+D103+D107+D104+D105+D106 -> 638620196000 | E109: =+E103+E107+E104+E105+E106 -> 644453334000 | F109: =+F103+F107+F104+F105+F106 -> 840723242000 | G109: =+G103+G107+G104+G105+G106 -> 842520215000 | H109: =+H103+H107+H104+H105+H106 -> 838861526000 | I109: =+I103+I107+I104+I105+I106 -> 886107830000
B110: TOTAL PATRIMONIO | C110: =+C109+C108 -> 693299477000 | D110: =+D109+D108 -> 686990938000 | E110: =+E109+E108 -> 687473463000 | F110: =+F109+F108 -> 840748807000 | G110: =+G109+G108 -> 842547713000 | H110: =+H109+H108 -> 838891099000 | I110: =+I109+I108 -> 886139298000 | J110: =+J109+J108 -> 0 | ... N110: =+N109+N108 -> 0
B112: ESTADO DE RESULTADOS
...

Sheet AGUAS-B
B2: =TODAY()-1 -> 46105 | D2: PROM DIVIDENDOS SIN ADIC/EVENT | E2: PROM DIVIDENDOS TOTALES
B3: {=_FV(B6,"Precio")} -> #VALUE! | D3: =AVERAGE(G45:I45) -> 9.0020133 | E3: =AVERAGE(G44:I44) -> 14.895127
B6: #VALUE! | C6: 2017 | D6: 2018 | E6: 2019 | F6: 2020 | G6: 2021 | H6: 2022 | I6: 2023 | J6: 2024 | K6: 2025 | L6: 2026 | M6: 2027 | N6: 2028
B7: Activos corrientes | C7: =+C61 -> 150618761000 | D7: =+D61 -> 168513972000 | E7: =+E61 -> 197676646000 | F7: =+F61 -> 302254499000 | G7: =+G61 -> 283854689000 | H7: =+H61 -> 324838124000 | I7: =+I61 -> 275000996000 | J7: =+J61 -> 0 | ... N7: =+N61 -> 0
B8: Cuentas por cobrar | C8: =+C65 -> 113515790000 | D8: =+D65 -> 116821062000 | E8: =+E65 -> 115937498000 | F8: =+F65 -> 87482681000 | G8: =+G65 -> 101105786000 | H8: =+H65 -> 122777327000 | I8: =+I65 -> 132007468000 | J8: =+J65 -> 0 | ... N8: =+N65 -> 0
B9: Inventario | C9: =+C67 -> 3925378000 | D9: =+D67 -> 3636388000 | E9: =+E67 -> 3810599000 | F9: =+F67 -> 3954953000 | G9: =+G67 -> 5185858000 | H9: =+H67 -> 12790532000 | I9: =+I67 -> 12812483000 | J9: =+J67 -> 0 | ... N9: =+N67 -> 0
B10: Acitvos no corrientes (no circulantes o fijos) | C10: =+C70 -> 1646261375000 | D10: =+D70 -> 1737538127000 | E10: =+E70 -> 1803767656000 | F10: =+F70 -> 1842181989000 | G10: =+G70 -> 1945366921000 | H10: =+H70 -> 2054511436000 | I10: =+I70 -> 2148343319000 | J10: =+J70 -> 0 | ... N10: =+N70 -> 0
B11: Activos totales | C11: =+C10+C7 -> 1796880136000 | D11: =+D10+D7 -> 1906052099000 | E11: =+E10+E7 -> 2001444302000 | F11: =+F10+F7 -> 2144436488000 | G11: =+G10+G7 -> 2229221610000 | H11: =+H10+H7 -> 2379349560000 | I11: =+I10+I7 -> 2423344315000 | J11: =+J10+J7 -> 0 | ... N11: =+N10+N7 -> 0
B12: Pasivos corrientes | C12: =+C84 -> 237111903000 | D12: =+D84 -> 242318524000 | E12: =+E84 -> 242137717000 | F12: =+F84 -> 244032589000 | G12: =+G84 -> 248642211000 | H12: =+H84 -> 265797147000 | I12: =+I84 -> 361668126000 | J12: =+J84 -> 0 | ... N12: =+N84 -> 0
B13: Pasivos no corrientes | C13: =+C94 -> 866468756000 | D13: =+D94 -> 976742178000 | E13: =+E94 -> 1071833122000 | F13: =+F94 -> 1059655092000 | G13: =+G94 -> 1138031686000 | H13: =+H94 -> 1274661314000 | I13: =+I94 -> 1175540305000 | J13: =+J94 -> 0 | ... N13: =+N94 -> 0
B14: Total Pasivos | C14: =+C12+C13 -> 1103580659000 | D14: =+D12+D13 -> 1219060702000 | E14: =+E12+E13 -> 1313970839000 | F14: =+F12+F13 -> 1303687681000 | G14: =+G12+G13 -> 1386673897000 | H14: =+H12+H13 -> 1540458461000 | I14: =+I12+I13 -> 1537208431000 | J14: =+J12+J13 -> 0 | ... N14: =+N12+N13 -> 0
B15: Patrimonio | C15: =+C109 -> 642630776000 | D15: =+D109 -> 638620196000 | E15: =+E109 -> 644453334000 | F15: =+F109 -> 840723242000 | G15: =+G109 -> 842520215000 | H15: =+H109 -> 838861526000 | I15: =+I109 -> 886107830000 | J15: =+J109 -> 0 | ... N15: =+N109 -> 0
B16: Cantidad de acciones | C16: 6118965160 | D16: 6118965160 | E16: 6118965160 | F16: 6118965160 | G16: 6118965160 | H16: 6118965160 | I16: 6118965160
B18: Valor libro | C18: =(C15/C16) -> 105.02279 | D18: =(D15/D16) -> 104.36735 | E18: =(E15/E16) -> 105.32064 | F18: =(F15/F16) -> 137.39631 | G18: =(G15/G16) -> 137.68998 | H18: =(H15/H16) -> 137.09206 | I18: =(I15/I16) -> 144.81335 | J18: =(J15/J16) -> #DIV/0! | ... N18: =(N15/N16) -> #DIV/0!
B19: Precio FIN AÑO | C19: 407 | D19: 382 | E19: 319 | F19: 229 | G19: 155 | H19: 196 | I19: 285
B20: PER | C20: =+C19/C40 -> 17.836796 | D20: =+D19/D40 -> 17.180121 | E20: =+E19/E40 -> 13.771369 | F20: =+F19/F40 -> 14.198028 | G20: =+G19/G40 -> 9.4236381 | H20: =+H19/H40 -> 14.068332 | I20: =+I19/I40 -> 13.073394 | J20: =+J19/J40 -> #DIV/0! | ... N20: =+N19/N40 -> #DIV/0!
B21: Bolsa/Libro | C21: =+C19/C18 -> 3.8753494 | D21: =+D19/D18 -> 3.6601484 | E21: =+E19/E18 -> 3.028846 | F21: =+F19/F18 -> 1.6667114 | G21: =+G19/G18 -> 1.1257173 | H21: =+H19/H18 -> 1.4296962 | I21: =+I19/I18 -> 1.9680506 | J21: =+J19/J18 -> #DIV/0! | ... N21: =+N19/N18 -> #DIV/0!
B22: GRAHAM | C22: =+C20*C21 -> 69.123816 | D22: =+D20*D21 -> 62.881794 | E22: =+E20*E21 -> 41.711357 | F22: =+F20*F21 -> 23.664016 | G22: =+G20*G21 -> 10.608353 | H22: =+H20*H21 -> 20.113441 | I22: =+I20*I21 -> 25.729102 | J22: =+J20*J21 -> #DIV/0! | ... N22: =+N20*N21 -> #DIV/0!
B23: Bolsa Libro Banda Menor | C23: =IF(C41<10%,0,IF(15%<C41,2,1)) -> 2 | D23: =IF(D41<10%,0,IF(15%<D41,2,1)) -> 2 | E23: =IF(E41<10%,0,IF(15%<E41,2,1)) -> 2 | F23: =IF(F41<10%,0,IF(15%<F41,2,1)) -> 1 | G23: =IF(G41<10%,0,IF(15%<G41,2,1)) -> 1 | H23: =IF(H41<10%,0,IF(15%<H41,2,1)) -> 1 | I23: =IF(I41<10%,0,IF(15%<I41,2,1)) -> 2 | J23: =IF(J41<10%,0,IF(15%<J41,2,1)) -> #DIV/0! | ... N23: =IF(N41<10%,0,IF(15%<N41,2,1)) -> #DIV/0!
B24: Bolsa Libro Banda Mayor | C24: =IF(C41<10%,1,IF(15%<C41,2.5,2)) -> 2.5 | D24: =IF(D41<10%,1,IF(15%<D41,2.5,2)) -> 2.5 | E24: =IF(E41<10%,1,IF(15%<E41,2.5,2)) -> 2.5 | F24: =IF(F41<10%,1,IF(15%<F41,2.5,2)) -> 2 | G24: =IF(G41<10%,1,IF(15%<G41,2.5,2)) -> 2 | H24: =IF(H41<10%,1,IF(15%<H41,2.5,2)) -> 2 | I24: =IF(I41<10%,1,IF(15%<I41,2.5,2)) -> 2.5 | J24: =IF(J41<10%,1,IF(15%<J41,2.5,2)) -> #DIV/0! | ... N24: =IF(N41<10%,1,IF(15%<N41,2.5,2)) -> #DIV/0!
B25: Precio Objetivo Menor | C25: =+C23*C18 -> 210.04557 | D25: =+D23*D18 -> 208.73471 | E25: =+E23*E18 -> 210.64128 | F25: =+F23*F18 -> 137.39631 | G25: =+G23*G18 -> 137.68998 | H25: =+H23*H18 -> 137.09206 | I25: =+I23*I18 -> 289.6267 | J25: =+J23*J18 -> #DIV/0! | ... N25: =+N23*N18 -> #DIV/0!
B26: Precio Obejtivo Promedio | C26: =AVERAGE(C25,C27) -> 236.30127 | D26: =AVERAGE(D25,D27) -> 234.82654 | E26: =AVERAGE(E25,E27) -> 236.97144 | F26: =AVERAGE(F25,F27) -> 206.09447 | G26: =AVERAGE(G25,G27) -> 206.53498 | H26: =AVERAGE(H25,H27) -> 205.63809 | I26: =AVERAGE(I25,I27) -> 325.83003 | J26: =AVERAGE(J25,J27) -> #DIV/0! | ... N26: =AVERAGE(N25,N27) -> #DIV/0!
B27: Precio Objetivo Mayor | C27: =+C18*C24 -> 262.55697 | D27: =+D18*D24 -> 260.91838 | E27: =+E18*E24 -> 263.3016 | F27: =+F18*F24 -> 274.79262 | G27: =+G18*G24 -> 275.37997 | H27: =+H18*H24 -> 274.18412 | I27: =+I18*I24 -> 362.03337 | J27: =+J18*J24 -> #DIV/0! | ... N27: =+N18*N24 -> #DIV/0!
B29: Capital de Trabajo | C29: =C7-C12 -> -86493142000 | D29: =D7-D12 -> -73804552000 | E29: =E7-E12 -> -44461071000 | F29: =F7-F12 -> 58221910000 | G29: =G7-G12 -> 35212478000 | H29: =H7-H12 -> 59040977000 | I29: =I7-I12 -> -86667130000 | J29: =J7-J12 -> 0 | ... N29: =N7-N12 -> 0
B30: Razón corriente | C30: =C7/C12 -> 0.63522227 | D30: =D7/D12 -> 0.6954234 | E30: =E7/E12 -> 0.81638106 | F30: =F7/F12 -> 1.2385825 | G30: =G7/G12 -> 1.1416191 | H30: =H7/H12 -> 1.222128 | I30: =I7/I12 -> 0.76036835 | J30: =J7/J12 -> #DIV/0! | ... N30: =N7/N12 -> #DIV/0!
B31: Razón ácida | C31: =+(C7-C9)/C12 -> 0.61866731 | D31: =+(D7-D9)/D12 -> 0.68041676 | E31: =+(E7-E9)/E12 -> 0.80064374 | F31: =+(F7-F9)/F12 -> 1.2223759 | G31: =+(G7-G9)/G12 -> 1.1207624 | H31: =+(H7-H9)/H12 -> 1.1740066 | I31: =+(I7-I9)/I12 -> 0.72494227 | J31: =+(J7-J9)/J12 -> #DIV/0! | ... N31: =+(N7-N9)/N12 -> #DIV/0!
B32: Razón de endeudamiento | C32: =C14/C11 -> 0.61416487 | D32: =D14/D11 -> 0.63957365 | E32: =E14/E11 -> 0.65651132 | F32: =F14/F11 -> 0.60793952 | G32: =G14/G11 -> 0.62204399 | H32: =H14/H11 -> 0.64742839 | I32: =I14/I11 -> 0.63433348 | J32: =J14/J11 -> #DIV/0! | ... N32: =N14/N11 -> #DIV/0!
B35: Ingresos | C35: =+C114 -> 509540577000 | D35: =+D114 -> 530404680000 | E35: =+E114 -> 484329084000 | F35: =+F114 -> 478773563000 | G35: =+G114 -> 506459633000 | H35: =+H114 -> 575465445000 | I35: =+I114 -> 640855854000 | J35: =+J114 -> 0 | ... N35: =+N114 -> 0
B36: EBIT | C36: =+C122 -> 226819054000 | D36: =+D122 -> 233071676000 | E36: =+E122 -> 235636236000 | F36: =+F122 -> 162824880000 | G36: =+G122 -> 212947803000 | H36: =+H122 -> 228258340000 | I36: =+I122 -> 256251484000 | J36: =+J122 -> 0 | ... N36: =+N122 -> 0
B37: Margen EBIT | C37: =C36/C35 -> 0.44514424 | D37: =D36/D35 -> 0.43942236 | E37: =E36/E35 -> 0.48652093 | F37: =F36/F35 -> 0.34008745 | G37: =G36/G35 -> 0.42046353 | H37: =H36/H35 -> 0.39664995 | I37: =I36/I35 -> 0.39985822 | J37: =J36/J35 -> #DIV/0! | ... N37: =N36/N35 -> #DIV/0!
B38: Utilidad neta | C38: =+C133 -> 139620280000 | D38: =+D133 -> 136056517000 | E38: =+E133 -> 141737188000 | F38: =+F133 -> 98691668000 | G38: =+G133 -> 100644529000 | H38: =+H133 -> 85248734000 | I38: =+I133 -> 133390421000 | J38: =+J133 -> 0 | ... N38: =+N133 -> 0
B39: Margen neto porcentual | C39: =C38/C35 -> 0.27401209 | D39: =D38/D35 -> 0.25651455 | E39: =E38/E35 -> 0.29264645 | F39: =F38/F35 -> 0.20613433 | G39: =G38/G35 -> 0.19872172 | H39: =H38/H35 -> 0.14813875 | I39: =I38/I35 -> 0.20814419 | J39: =J38/J35 -> #DIV/0! | ... N39: =N38/N35 -> #DIV/0!
B40: EPS | C40: =+C134 -> 22.818 | D40: =+D134 -> 22.235 | E40: =+E134 -> 23.164 | F40: =+F134 -> 16.129 | G40: =+G134 -> 16.448 | H40: =+H134 -> 13.932 | I40: =+I134 -> 21.8 | J40: =+J134 -> 0 | ... N40: =+N134 -> 0
B41: ROE | C41: =C38/C15 -> 0.21726361 | D41: =D38/D15 -> 0.21304763 | E41: =E38/E15 -> 0.21993398 | F41: =F38/F15 -> 0.11738901 | G41: =G38/G15 -> 0.11945652 | H41: =H38/H15 -> 0.10162432 | I41: =I38/I15 -> 0.1505352 | J41: =J38/J15 -> #DIV/0! | ... N41: =N38/N15 -> #DIV/0!
B42: ROE PROMEDIO | C42: =AVERAGE(G41:I41) -> 0.12387201
B43: FCF | C43: =+C146 -> 101170091000 | D43: =+D146 -> 108261532000 | E43: =+E146 -> 94891034000 | F43: =+F146 -> 36288731000 | G43: =+G146 -> 69607469000 | H43: =+H146 -> 81536376000 | I43: =+I146 -> 79751783000 | J43: =+J146 -> 0 | ... N43: =+N146 -> 0
B44: Dividendos | C44: =SUM(C46:C49) -> 22.118 | D44: =SUM(D46:D49) -> 22.224866 | E44: =SUM(E46:E49) -> 21.7113 | F44: =SUM(F46:F49) -> 17.852 | G44: =SUM(G46:G49) -> 17.1891 | H44: =SUM(H46:H49) -> 12.74727 | I44: =SUM(I46:I49) -> 14.74901 | J44: =SUM(J46:J49) -> 0 | ... N44: =SUM(N46:N49) -> 0
B45: Dividendos sin Adic/Event | C45: =+C46+C47 -> 6.861 | D45: =+D46+D47 -> 22.224866 | E45: =+E46+E47 -> 21.7113 | F45: =+F46+F47 -> 17.852 | G45: =+G46+G47 -> 6.5371 | H45: =+H46+H47 -> 5.71993 | I45: =+I46+I47 -> 14.74901 | J45: =+J46+J47 -> 0 | ... N45: =+N46+N47 -> 0
B46: Definitivo | D46: 15.363866 | E46: 14.6474 | I46: 8.21196
B47: Provisorio | C47: 6.861 | D47: 6.861 | E47: 7.0639 | F47: =10.59+7.262 -> 17.852 | G47: 6.5371 | H47: 5.71993 | I47: 6.53705
B48: Adicional | C48: 15.257 | G48: 4.371 | H48: 7.02734
B49: Eventual | G49: 6.281
B50: PAY OUT | C50: =(C47+C48+D46)/C40 -> 1.6426447 | D50: =(D47+D48+E46)/D40 -> 0.96732179 | E50: =(E47+E48+F46)/E40 -> 0.30495165 | F50: =(F47+F48+G46)/F40 -> 1.1068262 | G50: =(G47+G48+H46)/G40 -> 0.66318701 | H50: =(H47+H48+I46)/H40 -> 1.5043949 | I50: =(I47+I48+J46)/I40 -> 0.29986468 | J50: =(J47+J48+K46)/J40 -> #DIV/0! | ... N50: =(N47+N48+O46)/N40 -> #DIV/0!
B51: PAY OUT PROMEDIO 3 AÑOS | C51: =AVERAGE(G50:I50) -> 0.8224822
B52: DIV/YIELD | C52: =+C44/C19 -> 0.05434398 | D52: =+D44/D19 -> 0.058180277 | E52: =+E44/E19 -> 0.068060502 | F52: =+F44/F19 -> 0.077956332 | G52: =+G44/G19 -> 0.11089742 | H52: =+H44/H19 -> 0.065037092 | I52: =+I44/I19 -> 0.051750912 | J52: =+J44/J19 -> #DIV/0! | ... N52: =+N44/N19 -> #DIV/0!
B53: DIVIDEND YIELD PROM 3 AÑOS | C53: =AVERAGE(G52:I52) -> 0.075895141
B54: G | C54: =+C41*(100%-C50) -> -0.1396233 | D54: =+D41*(100%-D50) -> 0.0069620151 | E54: =+E41*(100%-E50) -> 0.15286475 | F54: =+F41*(100%-F50) -> -0.012540223 | G54: =+G41*(100%-G50) -> 0.040234506 | H54: =+H41*(100%-H50) -> -0.051258792 | I54: =+I41*(100%-I50) -> 0.10539501 | J54: =+J41*(100%-J50) -> #DIV/0! | ... N54: =+N41*(100%-N50) -> #DIV/0!
B55: G PROMEDIO 3 AÑOS | C55: =AVERAGE(G54:I54) -> 0.031456909
B57: ESTADO DE SITUACIÓN (BALANCE)
B59: AÑOS | C59: 2017 | D59: 2018 | E59: 2019 | F59: 2020 | G59: 2021 | H59: 2022 | I59: 2023 | J59: 2024 | K59: 2025 | L59: 2026 | M59: 2027 | N59: 2028
B60: ACTIVOS
B61: CORRIENTES (CIRCULANTES) | C61: 150618761000 | D61: 168513972000 | E61: 197676646000 | F61: 302254499000 | G61: 283854689000 | H61: 324838124000 | I61: 275000996000
B62: Efectivo y equivalentes al efectivo
B63: Otros activos financieros, corrientes
B64: Otros activos no financieros, corrientes
B65: Deudores comerciales y otras cuentas por cobrar, corrientes | C65: 113515790000 | D65: 116821062000 | E65: 115937498000 | F65: 87482681000 | G65: 101105786000 | H65: 122777327000 | I65: 132007468000
B66: Cuentas por cobrar entidades relacionadas, corriente neto
B67: Inventarios, neto | C67: 3925378000 | D67: 3636388000 | E67: 3810599000 | F67: 3954953000 | G67: 5185858000 | H67: 12790532000 | I67: 12812483000
B68: Activos por impuestos corrientes
B69: OTROS CORRIENTES | C69: =+C61-C62-C67-C68-C66-C65-C64-C63 -> 33177593000 | D69: =+D61-D62-D67-D68-D66-D65-D64-D63 -> 48056522000 | E69: =+E61-E62-E67-E68-E66-E65-E64-E63 -> 77928549000 | F69: =+F61-F62-F67-F68-F66-F65-F64-F63 -> 210816865000 | G69: =+G61-G62-G67-G68-G66-G65-G64-G63 -> 177563045000 | H69: =+H61-H62-H67-H68-H66-H65-H64-H63 -> 189270265000 | I69: =+I61-I62-I67-I68-I66-I65-I64-I63 -> 130181045000
B70: NO CORRIENTES (NO CIRCULANTES) | C70: 1646261375000 | D70: 1737538127000 | E70: 1803767656000 | F70: 1842181989000 | G70: 1945366921000 | H70: 2054511436000 | I70: 2148343319000
B71: Otros activos financieros, no corrientes
B72: Otros activos no financieros, no corrientes
B73: Inversiones en asociadas
B74: Plusvalía
B75: Activos intangibles distintos a la plusvalía
B76: Propiedades, plantas y equipos | C76: 1351763816000 | D76: 1440093131000 | E76: 1495658317000 | F76: 1568189347000 | G76: 1660157909000 | H76: 1713896622000 | I76: 1805370932000
B77: Propiedades de inversión
B78: Activos por derecho de uso
B79: Activos por impuestos diferidos
B80: OTROS NO CORRIENTES | C80: =+C70-C77-C78-C76-C71-C79-C75-C74-C73-C72 -> 294497559000 | D80: =+D70-D77-D78-D76-D71-D79-D75-D74-D73-D72 -> 297444996000 | E80: =+E70-E77-E78-E76-E71-E79-E75-E74-E73-E72 -> 308109339000 | F80: =+F70-F77-F78-F76-F71-F79-F75-F74-F73-F72 -> 273992642000 | G80: =+G70-G77-G78-G76-G71-G79-G75-G74-G73-G72 -> 285209012000 | H80: =+H70-H77-H78-H76-H71-H79-H75-H74-H73-H72 -> 340614814000 | I80: =+I70-I77-I78-I76-I71-I79-I75-I74-I73-I72 -> 342972387000
B81: TOTAL ACTIVOS | C81: =+C70+C61 -> 1796880136000 | D81: =+D70+D61 -> 1906052099000 | E81: =+E70+E61 -> 2001444302000 | F81: =+F70+F61 -> 2144436488000 | G81: =+G70+G61 -> 2229221610000 | H81: =+H70+H61 -> 2379349560000 | I81: =+I70+I61 -> 2423344315000
B83: PASIVOS
B84: CORRIENTES (CIRCULANTES) | C84: 237111903000 | D84: 242318524000 | E84: 242137717000 | F84: 244032589000 | G84: 248642211000 | H84: 265797147000 | I84: 361668126000
B85: Otros pasivos financieros, corrientes | H85: 74347139000 | I85: 155416801000
B86: Pasivos por arrendamientos, corrientes
B87: Otros pasivos no financieros
B88: Cuentas por pagar comerciales y otras cuentas por pagar | C88: 105645880000 | D88: 136872967000 | E88: 132451851000 | F88: 98758134000 | G88: 126774156000 | H88: 138331675000 | I88: 177288051000
B89: Cuentas por pagar entidades relacionadas
B90: Otras provisiones
B91: Pasivos por impuestos corrientes
B92: Provisiones por beneficios a los empleados, corrientes
B93: Otros | C93: =+C84-C85-C91-C92-C90-C89-C88-C87-C86 -> 131466023000 | D93: =+D84-D85-D91-D92-D90-D89-D88-D87-D86 -> 105445557000 | E93: =+E84-E85-E91-E92-E90-E89-E88-E87-E86 -> 109685866000 | F93: =+F84-F85-F91-F92-F90-F89-F88-F87-F86 -> 145274455000 | G93: =+G84-G85-G91-G92-G90-G89-G88-G87-G86 -> 121868055000 | H93: =+H84-H85-H91-H92-H90-H89-H88-H87-H86 -> 53118333000 | I93: =+I84-I85-I91-I92-I90-I89-I88-I87-I86 -> 28963274000
B94: NO CORRIENTES (NO CIRCULANTES) | C94: 866468756000 | D94: 976742178000 | E94: 1071833122000 | F94: 1059655092000 | G94: 1138031686000 | H94: 1274661314000 | I94: 1175540305000
B95: Otros pasivos financieros, no corrientes
B96: Pasivos por arrendamientos, no corrientes
B97: Pasivos por impuestos diferidos, no corrientes
B98: Provisiones por beneficios a los empleados, no corrientes
B99: OTROS PASIVOS NO CORRIENTES | C99: =+C94-C95-C97-C98-C96 -> 866468756000 | D99: =+D94-D95-D97-D98-D96 -> 976742178000 | E99: =+E94-E95-E97-E98-E96 -> 1071833122000 | F99: =+F94-F95-F97-F98-F96 -> 1059655092000 | G99: =+G94-G95-G97-G98-G96 -> 1138031686000 | H99: =+H94-H95-H97-H98-H96 -> 1274661314000 | I99: 1125060897000
B100: TOTAL PASIVOS | C100: =+C94+C84 -> 1103580659000 | D100: =+D94+D84 -> 1219060702000 | E100: =+E94+E84 -> 1313970839000 | F100: =+F94+F84 -> 1303687681000 | G100: =+G94+G84 -> 1386673897000 | H100: =+H94+H84 -> 1540458461000 | I100: =+I94+I84 -> 1537208431000
B102: PATRIMONIO
B103: Capital Pagado | C103: 155567354000 | D103: 155567354000 | E103: 155567354000 | F103: 155567354000 | G103: 155567354000 | H103: 155567354000 | I103: 155567354000
B104: Ganancias Acumuladas | C104: 328964934000 | D104: 324954354000 | E104: 330787492000 | F104: 364961863000 | G104: 361776346000 | H104: 362648832000 | I104: 411044222000
B105: Primas de emisión | C105: 164064038000 | D105: 164064038000 | E105: 164064038000 | F105: 164064038000 | G105: 164064038000 | H105: 164064038000 | I105: 164064038000
B106: Otras participaciones en el patrimonio | C106: -5965550000 | D106: -5965550000 | E106: -5965550000 | F106: -5965550000 | G106: -5965550000 | H106: -5965550000 | I106: -5965550000
B107: Otras Reservas | E107: 0 | F107: 162095537000 | G107: 167078027000 | H107: 162546852000 | I107: 161397766000
B108: Participación NO controladora | C108: 50668701000 | D108: 48370742000 | E108: 43020129000 | F108: 25565000 | G108: 27498000 | H108: 29573000 | I108: 31468000
B109: TOTAL PATRIMONIO CONTROLADORA | C109: =+C103+C107+C104+C105+C106 -> 642630776000 | D109: =+D103+D107+D104+D105+D106 -> 638620196000 | E109: =+E103+E107+E104+E105+E106 -> 644453334000 | F109: =+F103+F107+F104+F105+F106 -> 840723242000 | G109: =+G103+G107+G104+G105+G106 -> 842520215000 | H109: =+H103+H107+H104+H105+H106 -> 838861526000 | I109: =+I103+I107+I104+I105+I106 -> 886107830000
B110: TOTAL PATRIMONIO | C110: =+C109+C108 -> 693299477000 | D110: =+D109+D108 -> 686990938000 | E110: =+E109+E108 -> 687473463000 | F110: =+F109+F108 -> 840748807000 | G110: =+G109+G108 -> 842547713000 | H110: =+H109+H108 -> 838891099000 | I110: =+I109+I108 -> 886139298000 | J110: =+J109+J108 -> 0 | ... N110: =+N109+N108 -> 0
B112: ESTADO DE RESULTADOS
...

Sheet ALMENDRAL
B2: =TODAY()-1 -> 46105
B3: {=_FV(B6,"Precio")} -> 24.58 | D3: Datos no siguen estructura solicitada
B6: #VALUE! | C6: SUBYACENTE = ENTEL | D6: 45170
B7: PRECIO SUBYACENTE | C7: PRECIO ENTEL | D7: 2931.1
B8: ACCIONES SUBYACENTE | C8: ACCIONES ENTEL | D8: 302017113
B9: % CONTROLADO | D9: 0.5476
B10: ACCIONES CONTROLADAS | C10: ACCIONES ENTEL x % CONTROLADO | D10: =+D8*D9 -> 1.6538457e+08
B11: MARKET CAP SUBYACENTE | C11: MC ENTEL | D11: =+D7*D8 -> 8.8524236e+11
B12: MC CONTROLADO | C12: % MC | D12: =+D11*D9 -> 4.8475872e+11
B13: CASH SUBYACENTE | C13: CASH ENTEL | D13: 206689544000
B14: CASH TOTAL HOLDING | C14: CASH ALMENDRAL | D14: 209811976000
B15: CASH REAL HOLDING | C15: HOLD - SUBYACENTE | D15: =+D14-D13 -> 3122432000
B16: DEUDA SUBYACENTE | C16: DEUDA ENTEL | D16: =2927866545000+1103117081000 -> 4030983626000
B17: DEUDA HOLDING | C17: DEUDA ALMENDRAL | D17: 4093061555000
B18: DEUDA REAL HOLDING | C18: HOLD - SUBYACENTE | D18: =+D17-D16 -> 62077929000
B19: DEUDA NETA HOLDING | C19: DEUDA REAL HOLD - CAJA HOLD | D19: =+D18-D15 -> 58955497000
B20: NAV FILIAL SUBYACENTE | C20: MC SUB - DEUDA NETA HOLD | D20: =+D12-D19 -> 4.2580322e+11
B21: ACCIONES HOLDING | D21: 18017579131
B22: NAV FILIAL/ ACCIONES HOLDING | C22: NAV FILIAL/ ACCIONES HOLDING | D22: =+D20/D21 -> 23.632654
B23: PRECIO HOLDING | D23: 21.35
B24: Diferencia | D24: =+D22-D23 -> 2.2826543
B25: Descuento | D25: =+D24/D23 -> 0.10691589

Sheet ANASAC
B2: =TODAY()-1 -> 46105 | D2: PROM DIVIDENDOS SIN ADIC/EVENT | E2: PROM DIVIDENDOS TOTALES
B3: {=_FV(B6,"Precio")} -> 2600 | D3: =AVERAGE(C44:J44) -> 163.40586 | E3: =AVERAGE(C43:J43) -> 232.257
B6: #VALUE! | C6: 2017 | D6: 2018 | E6: 2019 | F6: 2020 | G6: 2021 | H6: 2022 | I6: 2023 | J6: 2024 | K6: 2025 | L6: 2026
B7: Activos corrientes | C7: =+C58 -> 151879608000 | D7: =+D58 -> 171777619000 | E7: =+E58 -> 164884687000 | F7: =+F58 -> 173765217000 | G7: =+G58 -> 202868299000 | H7: =+H58 -> 234849123000 | I7: =+I58 -> 0
B8: Inventarios | C8: =+C64 -> 48155878000 | D8: =+D64 -> 54833575000 | E8: =+E64 -> 56383490000 | F8: =+F64 -> 59423360000 | G8: =+G64 -> 66994665000 | H8: =+H64 -> 89984406000 | I8: =+I64 -> 0
B9: Acitvos fijos | C9: =+C68 -> 48771960000 | D9: =+D68 -> 49853310000 | E9: =+E68 -> 56835988000 | F9: =+F68 -> 54210228000 | G9: =+G68 -> 59153916000 | H9: =+H68 -> 61542215000 | I9: =+I68 -> 0
B10: Activos totales | C10: =+C7+C9 -> 200651568000 | D10: =+D7+D9 -> 221630929000 | E10: =+E7+E9 -> 221720675000 | F10: =+F7+F9 -> 227975445000 | G10: =+G7+G9 -> 262022215000 | H10: =+H7+H9 -> 296391338000 | I10: =+I7+I9 -> 0 | J10: OK
B11: Pasivos corrientes | C11: =+C81 -> 88225173000 | D11: =+D81 -> 76085281000 | E11: =+E81 -> 60650736000 | F11: =+F81 -> 85606829000 | G11: =+G81 -> 80522199000 | H11: =+H81 -> 95952963000 | I11: =+I81 -> 0
B12: Pasivos no corrientes | C12: =+C90 -> 12099696000 | D12: =+D90 -> 38723216000 | E12: =+E90 -> 49182469000 | F12: =+F90 -> 22604867000 | G12: =+G90 -> 56087851000 | H12: =+H90 -> 65556118000 | I12: =+I90 -> 0
B13: Total Pasivos | C13: =SUM(C11:C12) -> 100324869000 | D13: =SUM(D11:D12) -> 114808497000 | E13: =SUM(E11:E12) -> 109833205000 | F13: =SUM(F11:F12) -> 108211696000 | G13: =SUM(G11:G12) -> 136610050000 | H13: =SUM(H11:H12) -> 161509081000 | I13: =SUM(I11:I12) -> 0
B14: Patrimonio (controladora) | C14: =+C102 -> 99102312000 | D14: =+D102 -> 105716809000 | E14: =+E102 -> 110559836000 | F14: =+F102 -> 118415550000 | G14: =+G102 -> 124234457000 | H14: =+H102 -> 133520577000 | I14: =+I102 -> 0 | J14: OK
B15: Cantidad de acciones | C15: 22000000 | D15: 22000000 | E15: 22000000 | F15: 22000000 | G15: 22000000 | H15: 22000000 | I15: 22000001
B17: Valor libro | C17: =(C14/C15) -> 4504.6505 | D17: =(D14/D15) -> 4805.3095 | E17: =(E14/E15) -> 5025.4471 | F17: =(F14/F15) -> 5382.525 | G17: =(G14/G15) -> 5647.0208 | H17: =(H14/H15) -> 6069.1171 | I17: =(I14/I15) -> 0
B18: Precio FIN AÑO | C18: 1801 | D18: 1801 | E18: 1801 | F18: 1801 | G18: 2302 | H18: 2302 | I18: 2303
B19: PER | C19: =+C18/C39 -> 4.3788309 | D19: =+D18/D39 -> 6.6960136 | E19: =+E18/E39 -> 9.6820669 | F19: =+F18/F39 -> 2.6619488 | G19: =+G18/G39 -> 2.592865 | H19: =+H18/H39 -> 2.9800819 | I19: =+I18/I39 -> #DIV/0!
B20: Bolsa / Libro | C20: =+C18/C17 -> 0.39980904 | D20: =+D18/D17 -> 0.37479376 | E20: =+E18/E17 -> 0.35837607 | F20: =+F18/F17 -> 0.33460133 | G20: =+G18/G17 -> 0.40764858 | H20: =+H18/H17 -> 0.37929734 | I20: =+I18/I17 -> #DIV/0!
B21: GRAHAM | C21: =+C19*C20 -> 1.7506962 | D21: =+D19*D20 -> 2.5096241 | E21: =+E19*E20 -> 3.4698211 | F21: =+F19*F20 -> 0.89069159 | G21: =+G19*G20 -> 1.0569777 | H21: =+H19*H20 -> 1.1303371 | I21: =+I19*I20 -> #DIV/0!
B22: Bolsa Libro Banda Menor | C22: =IF(C40<10%,0,IF(15%<C41,2,1)) -> 0 | D22: =IF(D40<10%,0,IF(15%<D41,2,1)) -> 0 | E22: =IF(E40<10%,0,IF(15%<E41,2,1)) -> 0 | F22: =IF(F40<10%,0,IF(15%<F41,2,1)) -> 1 | G22: =IF(G40<10%,0,IF(15%<G41,2,1)) -> 1 | H22: =IF(H40<10%,0,IF(15%<H41,2,1)) -> 1 | I22: =IF(I40<10%,0,IF(15%<I41,2,1)) -> #DIV/0!
B23: Bolsa Libro Banda Mayor | C23: =IF(C40<10%,1,IF(15%<C41,2.5,2)) -> 1 | D23: =IF(D40<10%,1,IF(15%<D41,2.5,2)) -> 1 | E23: =IF(E40<10%,1,IF(15%<E41,2.5,2)) -> 1 | F23: =IF(F40<10%,1,IF(15%<F41,2.5,2)) -> 2 | G23: =IF(G40<10%,1,IF(15%<G41,2.5,2)) -> 2 | H23: =IF(H40<10%,1,IF(15%<H41,2.5,2)) -> 2 | I23: =IF(I40<10%,1,IF(15%<I41,2.5,2)) -> #DIV/0!
B24: Precio Objetivo Menor | C24: =+C22*C17 -> 0 | D24: =+D22*D17 -> 0 | E24: =+E22*E17 -> 0 | F24: =+F22*F17 -> 5382.525 | G24: =+G22*G17 -> 5647.0208 | H24: =+H22*H17 -> 6069.1171 | I24: =+I22*I17 -> #DIV/0!
B25: Precio Obejtivo Promedio | C25: =AVERAGE(C24,C26) -> 2252.3253 | D25: =AVERAGE(D24,D26) -> 2402.6548 | E25: =AVERAGE(E24,E26) -> 2512.7235 | F25: =AVERAGE(F24,F26) -> 8073.7875 | G25: =AVERAGE(G24,G26) -> 8470.5312 | H25: =AVERAGE(H24,H26) -> 9103.6757 | I25: =AVERAGE(I24,I26) -> #DIV/0!
B26: Precio Objetivo Mayor | C26: =+C17*C23 -> 4504.6505 | D26: =+D17*D23 -> 4805.3095 | E26: =+E17*E23 -> 5025.4471 | F26: =+F17*F23 -> 10765.05 | G26: =+G17*G23 -> 11294.042 | H26: =+H17*H23 -> 12138.234 | I26: =+I17*I23 -> #DIV/0!
B28: Capital de Trabajo | C28: =C7-C11 -> 63654435000 | D28: =D7-D11 -> 95692338000 | E28: =E7-E11 -> 104233951000 | F28: =F7-F11 -> 88158388000 | G28: =G7-G11 -> 122346100000 | H28: =H7-H11 -> 138896160000 | I28: =I7-I11 -> 0
B29: Razón corriente | C29: =C7/C11 -> 1.7214997 | D29: =D7/D11 -> 2.2576984 | E29: =E7/E11 -> 2.7185933 | F29: =F7/F11 -> 2.0298056 | G29: =G7/G11 -> 2.5194083 | H29: =H7/H11 -> 2.4475443 | I29: =I7/I11 -> #DIV/0! | J29: OK
B30: Razón ácida | C30: =+(C7-C8)/C11 -> 1.1756705 | D30: =+(D7-D8)/D11 -> 1.5370127 | E30: =+(E7-E8)/E11 -> 1.788951 | F30: =+(F7-F8)/F11 -> 1.3356628 | G30: =+(G7-G8)/G11 -> 1.6874059 | H30: =+(H7-H8)/H11 -> 1.5097472 | I30: =+(I7-I8)/I11 -> #DIV/0! | J30: OK
B31: Razón de endeudamiento | C31: =C13/C10 -> 0.49999544 | D31: =D13/D10 -> 0.51801659 | E31: =E13/E10 -> 0.49536745 | F31: =F13/F10 -> 0.47466382 | G31: =G13/G10 -> 0.5213682 | H31: =H13/H10 -> 0.54491836 | I31: =I13/I10 -> #DIV/0! | J31: OK
B34: Ingresos | C34: =+C108 -> 172808914000 | D34: =+D108 -> 174580741000 | E34: =+E108 -> 186046901000 | F34: =+F108 -> 225071441000 | G34: =+G108 -> 248484804000 | H34: =+H108 -> 270058911000 | I34: =+I108 -> 0 | J34: OK
B35: EBIT | C35: =+C116 -> 15422202000 | D35: =+D116 -> 17369424000 | E35: =+E116 -> 15128605000 | F35: =+F116 -> 27418687000 | G35: =+G116 -> 31791243000 | H35: =+H116 -> 28337095000 | I35: =+I116 -> 0 | J35: OK
B36: Margen EBIT | C36: =C35/C34 -> 0.08924425 | D36: =D35/D34 -> 0.099492211 | E36: =E35/E34 -> 0.081316082 | F36: =F35/F34 -> 0.12182215 | G36: =G35/G34 -> 0.12794039 | H36: =H35/H34 -> 0.10492931 | I36: =I35/I34 -> #DIV/0!
B37: Utilidad neta | C37: =+C124 -> 9048525000 | D37: =+D124 -> 5917243000 | E37: =+E124 -> 4092299000 | F37: =+F124 -> 14884582000 | G37: =+G124 -> 19532052000 | H37: =+H124 -> 16994156000 | I37: =+I124 -> 0 | J37: OK
B38: Margen neto porcentual | C38: =C37/C34 -> 0.052361448 | D38: =D37/D34 -> 0.033894019 | E38: =E37/E34 -> 0.021996061 | F38: =F37/F34 -> 0.0661327 | G38: =G37/G34 -> 0.078604614 | H38: =H37/H34 -> 0.062927588 | I38: =I37/I34 -> #DIV/0!
B39: EPS / BPA / UPA | C39: =+C127 -> 411.297 | D39: =+D127 -> 268.966 | E39: =+E127 -> 186.014 | F39: =+F127 -> 676.572 | G39: =+G127 -> 887.821 | H39: =+H127 -> 772.462 | I39: =+I127 -> 0 | J39: OK
B40: ROE | C40: =C37/C14 -> 0.091304883 | D40: =D37/D14 -> 0.055972584 | E40: =E37/E14 -> 0.037014337 | F40: =F37/F14 -> 0.12569787 | G40: =G37/G14 -> 0.15721928 | H40: =H37/H14 -> 0.12727743 | I40: =I37/I14 -> #DIV/0! | J40: OK
B41: ROE PROMEDIO | C41: =AVERAGE(C40:H40) -> 0.099081064
B42: FCF | C42: =+C138 -> 29369000 | D42: =+D138 -> -632633000 | E42: =+E138 -> 21246162000 | F42: =+F138 -> 25933974000 | G42: =+G138 -> 11671072000 | H42: =+H138 -> -12673885000 | I42: =+I138 -> 0
B43: Dividendos Totales | C43: =SUM(C45:C49) -> 18.392 | D43: =SUM(D45:D49) -> 123.389 | E43: =SUM(E45:E49) -> 80.69 | F43: =SUM(F45:F49) -> 74.41 | G43: =SUM(G45:G49) -> 648.042 | H43: =SUM(H45:H49) -> 370.891 | I43: =SUM(I45:I49) -> 309.985
B44: Dividendos sin Adic/Event | C44: =+C45+C46+C47+C48 -> 18.392 | D44: =+D45+D46+D47+D48 -> 123.389 | E44: =+E45+E46+E47+E48 -> 80.69 | F44: =+F45+F46+F47+F48 -> 74.41 | G44: =+G45+G46+G47+G48 -> 270.629 | H44: =+H45+H46+H47+H48 -> 266.346 | I44: =+I45+I46+I47+I48 -> 309.985
B45: Definitivo | C45: 18.392 | D45: 123.389 | E45: 80.69 | F45: 74.41 | G45: 270.629 | H45: 266.346 | I45: 309.985
B46: Provisorio
B47: Provisorio
B48: Provisorio
B49: Adicional/Eventual | G49: 377.413 | H49: 104.545
B50: PAY OUT | C50: =(C46+C47+C48+D45+C49)/C39 -> 0.29999976 | D50: =(D46+D47+D48+E45+D49)/D39 -> 0.30000074 | E50: =(E46+E47+E48+F45+E49)/E39 -> 0.40002365 | F50: =(F46+F47+F48+G45+F49)/F39 -> 0.4000003 | G50: =(G46+G47+G48+H45+G49)/G39 -> 0.72509999 | H50: =(H46+H47+H48+I45+H49)/H39 -> 0.53663481 | I50: =(I46+I47+I48+J45+I49)/J39 -> #VALUE!
B51: Div/Yield | C51: =+C43/C18 -> 0.010212104 | D51: =+D43/D18 -> 0.068511383 | E51: =+E43/E18 -> 0.044802887 | F51: =+F43/F18 -> 0.041315936 | G51: =+G43/G18 -> 0.2815126 | H51: =+H43/H18 -> 0.16111685 | I51: =+I43/J18 -> #DIV/0!
B52: G | C52: =+C40*(100%-C50) -> 0.06391344 | D52: =+D40*(100%-D50) -> 0.039180767 | E52: =+E40*(100%-E50) -> 0.022207727 | F52: =+F40*(100%-F50) -> 0.075418683 | G52: =+G40*(100%-G50) -> 0.043219582 | H52: =+H40*(100%-H50) -> 0.058975931 | I52: =+I40*(100%-I50) -> #DIV/0!
B54: ESTADO DE SITUACIÓN (BALANCE)
B56: AÑOS (VALORES EN PESOS CHILENOS) | C56: 2017 | D56: 2018 | E56: 2019 | F56: 2020 | G56: 2021 | H56: 2022 | I56: 2023
B57: ACTIVOS
B58: CORRIENTES (CIRCULANTES) | C58: 151879608000 | D58: 171777619000 | E58: 164884687000 | F58: 173765217000 | G58: 202868299000 | H58: 234849123000
B59: Efectivo y equivalente al efectivo | C59: 8451241000 | D59: 9345448000 | E59: 9470988000 | F59: 17863795000 | G59: 11837751000 | H59: 11829143000
B60: Otros activos financieros corrientes | E60: 114291000 | F60: 1326363000 | G60: 536114000 | H60: 1008684000
B61: Otros activos no financieros corrientes | C61: 1681153000 | D61: 1244554000 | E61: 529807000 | F61: 391839000 | G61: 2741097000 | H61: 1760368000
B62: Deudores comerciales y otras cuentas por cobrar | C62: 85339759000 | D62: 98588611000 | E62: 90592302000 | F62: 86983408000 | G62: 109465809000 | H62: 117821206000
B63: Cuentas por cobrar a entidades relacionadas | C63: 383749000 | D63: 128773000 | E63: 103643000 | F63: 157613000 | G63: 184364000 | H63: 245098000
B64: Inventarios | C64: 48155878000 | D64: 54833575000 | E64: 56383490000 | F64: 59423360000 | G64: 66994665000 | H64: 89984406000
B65: Activos por impuestos corrientes | C65: 7303779000 | D65: 7248204000 | E65: 7418665000 | F65: 7576818000 | G65: 11086934000 | H65: 12121261000
B66: Activos no corrientes clasificados como mantenidos para la venta | C66: 564049000 | D66: 388454000 | E66: 271501000 | F66: 42021000 | G66: 21565000 | H66: 78957000
B67: OTROS ACTIVOS CORRIENTES | C67: =+C58-C59-C60-C62-C63-C64-C65-C66-C61 -> 0 | D67: =+D58-D59-D60-D62-D63-D64-D65-D66-D61 -> 0 | E67: =+E58-E59-E60-E62-E63-E64-E65-E66-E61 -> 0 | F67: =+F58-F59-F60-F62-F63-F64-F65-F66-F61 -> 0 | G67: =+G58-G59-G60-G62-G63-G64-G65-G66-G61 -> 0 | H67: =+H58-H59-H60-H62-H63-H64-H65-H66-H61 -> 0 | I67: =+I58-I59-I60-I62-I63-I64-I65-I66-I61 -> 0
B68: NO CORRIENTES (NO CIRCULANTES) | C68: 48771960000 | D68: 49853310000 | E68: 56835988000 | F68: 54210228000 | G68: 59153916000 | H68: 61542215000
B69: Otros activos no financieros , no corrientes | C69: 164237000 | D69: 133680000 | E69: 160840000 | F69: 158247000 | G69: 1089829000 | H69: 0
B70: Inversiones contabilizadas utilizando el método de la participación | C70: 242868000 | D70: 305777000 | E70: 436592000 | F70: 523576000 | G70: 678678000 | H70: 782584000
B71: Activos Intangibles distintos de la plusvalía | C71: 6766942000 | D71: 7318672000 | E71: 8018695000 | F71: 8037943000 | G71: 8947007000 | H71: 9339343000
B72: Plusvalía | C72: 1873096000 | D72: 1873096000 | E72: 1611124000 | F72: 1349150000 | G72: 1349150000 | H72: 1349150000
B73: Propiedades, Plantas y Equipos | C73: 38395642000 | D73: 39036020000 | E73: 27577213000 | F73: 26671079000 | G73: 28362703000 | H73: 29647614000
B74: Propiedades de inversión | C74: 0 | D74: 0 | E74: 136940000 | F74: 117722000 | G74: 120590000 | H74: 0
B75: Activos por derecho de uso | C75: 0 | D75: 0 | E75: 17677608000 | F75: 15943223000 | G75: 17108822000 | H75: 15635793000
B76: Activos por impuestos diferidos | C76: 1329175000 | D76: 1189065000 | E76: 1216976000 | F76: 1409288000 | G76: 1497137000 | H76: 4787731000
B77: OTROS ACTIVOS NO CORRIENTES | C77: =+C68-C71-C72-C70-C69-C73-C74-C75-C76 -> 0 | D77: =+D68-D71-D72-D70-D69-D73-D74-D75-D76 -> -3000000 | E77: =+E68-E71-E72-E70-E69-E73-E74-E75-E76 -> 0 | F77: =+F68-F71-F72-F70-F69-F73-F74-F75-F76 -> 0 | G77: =+G68-G71-G72-G70-G69-G73-G74-G75-G76 -> 0 | H77: =+H68-H71-H72-H70-H69-H73-H74-H75-H76 -> 0 | I77: =+I68-I71-I72-I70-I69-I73 -> 0
B78: TOTAL ACTIVOS | C78: =+C68+C58 -> 200651568000 | D78: =+D68+D58 -> 221630929000 | E78: =+E68+E58 -> 221720675000 | F78: =+F68+F58 -> 227975445000 | G78: =+G68+G58 -> 262022215000 | H78: =+H68+H58 -> 296391338000 | I78: =+I68+I58 -> 0
B80: PASIVOS
B81: CORRIENTES (CIRCULANTES) | C81: 88225173000 | D81: 76085281000 | E81: 60650736000 | F81: 85606829000 | G81: 80522199000 | H81: 95952963000
B82: Otros pasivos financieros corrientes | C82: 60205144000 | D82: 44157772000 | E82: 28425807000 | F82: 44437884000 | G82: 22734675000 | H82: 41783682000
B83: Pasivos por arrendamientos corrientes | C83: 0 | D83: 0 | E83: 2519295000 | F83: 2561672000 | G83: 3372704000 | H83: 3595489000
B84: Cuentas por pagar comerciales y otras cuentas por pagar | C84: 15308273000 | D84: 21616796000 | E84: 22079345000 | F84: 25007893000 | G84: 37176414000 | H84: 37928750000
B85: Cuentas por pagar a entidades relacionadas, corrientes | C85: 2681108000 | D85: 1756737000 | E85: 1215244000 | F85: 4412665000 | G85: 5791077000 | H85: 5036134000
B86: Otras provisiones a corto plazo | C86: 1211154000 | D86: 164577000 | E86: 109621000 | F86: 115945000 | G86: 166603000 | H86: 64249000
B87: Pasivos por impuestos corrientes | C87: 4636194000 | D87: 4257169000 | E87: 4326141000 | F87: 6777285000 | G87: 8620298000 | H87: 4630793000
B88: Provisiones corrientes por beneficios a los empleados | C88: 2020966000 | D88: 2060167000 | E88: 1884942000 | F88: 2242484000 | G88: 2660428000 | H88: 2913866000
B89: Otros pasivos no financieros corrientes | C89: =+C81-C82-C83-C84-C85-C86-C87-C88 -> 2162334000 | D89: =+D81-D82-D83-D84-D85-D86-D87-D88 -> 2072063000 | E89: =+E81-E82-E83-E84-E85-E86-E87-E88 -> 90341000 | F89: =+F81-F82-F83-F84-F85-F86-F87-F88 -> 51001000 | G89: =+G81-G82-G83-G84-G85-G86-G87-G88 -> 0 | H89: =+H81-H82-H83-H84-H85-H86-H87-H88 -> 0
B90: NO CORRIENTES (NO CIRCULANTES) | C90: 12099696000 | D90: 38723216000 | E90: 49182469000 | F90: 22604867000 | G90: 56087851000 | H90: 65556118000
B91: Otros pasivos financieros no corrientes | C91: 11448480000 | D91: 37723122000 | E91: 35777324000 | F91: 11516390000 | G91: 44356519000 | H91: 54712571000
B92: Pasivos por arrendamientos no corrientes | C92: 0 | D92: 0 | E92: 12386172000 | F92: 10560106000 | G92: 10945940000 | H92: 9028381000
B93: Pasivo por impuestos diferidos | C93: 651216000 | D93: 1000094000 | E93: 1018973000 | F93: 528371000 | G93: 785392000 | H93: 1815166000
B94: Otros pasivos no financieros no corrientes | C94: =+C90-C91-C92-C93 -> 0 | D94: =+D90-D91-D92-D93 -> 0 | E94: =+E90-E91-E92-E93 -> 0 | F94: =+F90-F91-F92-F93 -> 0 | G94: =+G90-G91-G92-G93 -> 0 | H94: =+H90-H91-H92-H93 -> 0
B95: TOTAL PASIVOS | C95: =+C89+C81 -> 90387507000 | D95: =+D89+D81 -> 78157344000 | E95: =+E89+E81 -> 60741077000 | F95: =+F89+F81 -> 85657830000 | G95: =+G89+G81 -> 80522199000 | H95: =+H89+H81 -> 95952963000
B97: PATRIMONIO
B98: Capital pagado | C98: 1914106000 | D98: 1914106000 | E98: 1914106000 | F98: 1914106000 | G98: 1914106000 | H98: 1914106000
B99: Resultados acumulados | C99: 96165470000 | D99: 100307540000 | E99: 103172035000 | F99: 113181981000 | G99: 115365959000 | H99: 124961868000
B100: Otras participaciones en el patrimonio | C100: 4071204000 | D100: 4071204000 | E100: 4071204000 | F100: 4071204000 | G100: 4071204000 | H100: 4071204000
B101: Otras reservas | C101: -3048468000 | D101: -576041000 | E101: 1402491000 | F101: -751741000 | G101: 2883188000 | H101: 2573399000
B102: TOTAL PATRIMONIO ATRIBUIBLE A LOS PROPIETARIOS DE LA CONTROLADORA | C102: =+C98+C99+C100+C101 -> 99102312000 | D102: =+D98+D99+D100+D101 -> 105716809000 | E102: =+E98+E99+E100+E101 -> 110559836000 | F102: =+F98+F99+F100+F101 -> 118415550000 | G102: =+G98+G99+G100+G101 -> 124234457000 | H102: =+H98+H99+H100+H101 -> 133520577000
B103: Participaciones no controladoras | C103: 1224387000 | D103: 1108623000 | E103: 1327634000 | F103: 1348199000 | G103: 1177708000 | H103: 1361680000
B104: TOTAL PATRIMONIO NETO | C104: =+C98+C100+C99+C103+C101 -> 100326699000 | D104: =+D98+D100+D99+D103+D101 -> 106825432000 | E104: =+E98+E100+E99+E103+E101 -> 111887470000 | F104: =+F98+F100+F99+F103+F101 -> 119763749000 | G104: =+G98+G100+G99+G103+G101 -> 125412165000 | H104: =+H98+H100+H99+H103+H101 -> 134882257000 | I104: =+I98+I101+I99+I103 -> 0
B106: ESTADO DE RESULTADOS
B107: AÑOS | C107: 2017 | D107: 2018 | E107: 2019 | F107: 2020 | G107: 2021 | H107: 2022 | I107: 2023
B108: INGRESOS POR VENTAS (Ingresos Ordinarios) | C108: 172808914000 | D108: 174580741000 | E108: 186046901000 | F108: 225071441000 | G108: 248484804000 | H108: 270058911000
B109: GASTOS POR BENEFICIOS A LOS EMPLEADOS | C109: -100954414000 | D109: -104130586000 | E109: -111627741000 | F109: -129055343000 | G109: -138882766000 | H109: -157988242000
B110: GANANCIA BRUTA | C110: =+C108+C109 -> 71854500000 | D110: =+D108+D109 -> 70450155000 | E110: =+E108+E109 -> 74419160000 | F110: =+F108+F109 -> 96016098000 | G110: =+G108+G109 -> 109602038000 | H110: =+H108+H109 -> 112070669000 | I110: =+I108+I109 -> 0
B111: Costos de distribución | C111: -10857799000 | D111: -10083140000 | E111: -12557627000 | F111: -14401736000 | G111: -15126572000 | H111: -18740216000
B112: Gastos de administración y ventas | C112: -42789254000 | D112: -43482462000 | E112: -46841058000 | F112: -54034028000 | G112: -62287954000 | H112: -65856187000
...

Sheet ANDINA A
B2: =TODAY()-1 -> 46105 | D2: PROM DIVIDENDOS SIN EVENT | E2: PROM DIVIDENDOS TOTALES
B3: {=_FV(B6,"Precio")} -> 3475 | D3: =AVERAGE(I45:K45) -> 156.66667 | E3: =AVERAGE(H44:J44) -> 200
B6: #VALUE! | C6: 2017 | D6: 2018 | E6: 2019 | F6: 2020 | G6: 2021 | H6: 2022 | I6: 2023 | J6: 2024 | K6: 2025 | L6: 2026 | M6: 2027 | N6: 2028
B7: Activos corrientes | C7: =+C68 -> 484010050000 | D7: =+D68 -> 481586454000 | E7: =+E68 -> 533474103000 | F7: =+F68 -> 797297716000 | G7: =+G68 -> 990986123000 | H7: =+H68 -> 1161729392000 | I7: =+I68 -> 981771027000 | J7: =+J68 -> 1013195740000 | ... N7: =+N68 -> 0
B8: Cuentas por cobrar | C8: =+C72 -> 191284680000 | D8: =+D72 -> 174113323000 | E8: =+E72 -> 191077588000 | F8: =+F72 -> 194021253000 | G8: =+G72 -> 265490626000 | H8: =+H72 -> 279770286000 | I8: =+I72 -> 298892164000 | J8: =+J72 -> 332831088000 | ... N8: =+N72 -> 0
B9: Inventario | C9: =+C74 -> 131363000000 | D9: =+D74 -> 151319709000 | E9: =+E74 -> 147641224000 | F9: =+F74 -> 127972650000 | G9: =+G74 -> 191350206000 | H9: =+H74 -> 245886656000 | I9: =+I74 -> 233053160000 | J9: =+J74 -> 299970909000 | ... N9: =+N74 -> 0
B10: Activos no corrientes | C10: =+C77 -> 1630849417000 | D10: =+D77 -> 1732918235000 | E10: =+E77 -> 1857474320000 | F10: =+F77 -> 1650766684000 | G10: =+G77 -> 1955120524000 | H10: =+H77 -> 1848971215000 | I10: =+I77 -> 1939749862000 | J10: =+J77 -> 2277908533000 | ... N10: =+N77 -> 0
B11: Activos totales | C11: =+C7+C10 -> 2114859467000 | D11: =+D7+D10 -> 2214504689000 | E11: =+E7+E10 -> 2390948423000 | F11: =+F7+F10 -> 2448064400000 | G11: =+G7+G10 -> 2946106647000 | H11: =+H7+H10 -> 3010700607000 | I11: =+I7+I10 -> 2921520889000 | J11: =+J7+J10 -> 3291104273000 | ... N11: =+N7+N10 -> 0
B12: Pasivos corrientes | C12: =+C91 -> 428287322000 | D12: =+D91 -> 419862101000 | E12: =+E91 -> 411658352000 | F12: =+F91 -> 378056186000 | G12: =+G91 -> 529567279000 | H12: =+H91 -> 949245134000 | I12: =+I91 -> 692871296000 | J12: =+J91 -> 906143994000 | ... N12: =+N91 -> 0
B13: Pasivos no corrientes | C13: =+C101 -> 873338796000 | D13: =+D101 -> 930927845000 | E13: =+E101 -> 1010386123000 | F13: =+F101 -> 1238447623000 | G13: =+G101 -> 1315125809000 | H13: =+H101 -> 1178052821000 | I13: =+I101 -> 1307664179000 | J13: =+J101 -> 1370563259000 | ... N13: =+N101 -> 0
B14: Total Pasivos | C14: =SUM(C12:C13) -> 1301626118000 | D14: =SUM(D12:D13) -> 1350789946000 | E14: =SUM(E12:E13) -> 1422044475000 | F14: =SUM(F12:F13) -> 1616503809000 | G14: =SUM(G12:G13) -> 1844693088000 | H14: =SUM(H12:H13) -> 2127297955000 | I14: =SUM(I12:I13) -> 2000535475000 | J14: =SUM(J12:J13) -> 2276707253000 | ... N14: =SUM(N12:N13) -> 0
B15: Patrimonio | C15: =+C117 -> 791310056000 | D15: =+D117 -> 843813126000 | E15: =+E117 -> 948649690000 | F15: =+F117 -> 811181114000 | G15: =+G117 -> 1076143804000 | H15: =+H117 -> 855260144000 | I15: =+I117 -> 886290527000 | J15: =+J117 -> 976409192000 | ... N15: =+N117 -> 0
B16: Cantidad de acciones | C16: 946570604 | D16: 946570604 | E16: 946570604 | F16: 946570604 | G16: 946570604 | H16: 946570604 | I16: 946570604 | J16: 946570604 | K16: 946570604
B18: Valor libro | C18: =(C15/C16) -> 835.97573 | D18: =(D15/D16) -> 891.44235 | E18: =(E15/E16) -> 1002.1964 | F18: =(F15/F16) -> 856.96842 | G18: =(G15/G16) -> 1136.887 | H18: =(H15/H16) -> 903.5355 | I18: =(I15/I16) -> 936.3174 | J18: =(J15/J16) -> 1031.5228 | ... N18: =(N15/N16) -> #DIV/0!
B19: Precio FIN AÑO | C19: 2580 | D19: 2250 | E19: 1880 | F19: 1581 | G19: 1600 | H19: 1641 | I19: 1746 | J19: 2398.2 | K19: 3561.8
B20: PER | C20: =+C19/C40 -> 21.761134 | D20: =+D19/D40 -> 23.148148 | E20: =+E19/E40 -> 10.755764 | F20: =+F19/F40 -> 10.150883 | G20: =+G19/G40 -> 10.279473 | H20: =+H19/H40 -> 12.995961 | I20: =+I19/I40 -> 10.122326 | J20: =+J19/J40 -> 10.244778 | ... N20: =+N19/N40 -> #DIV/0!
B21: Bolsa/Libro SERIE A | C21: =+C19/C18 -> 3.086214 | D21: =+D19/D18 -> 2.5239994 | E21: =+E19/E18 -> 1.8758797 | F21: =+F19/F18 -> 1.8448755 | G21: =+G19/G18 -> 1.4073518 | H21: =+H19/H18 -> 1.8161987 | I21: =+I19/I18 -> 1.8647523 | J21: =+J19/J18 -> 2.3249122 | ... N21: =+N19/N18 -> #DIV/0!
B22: GRAHAM SERIE A | C22: =+C20*C21 -> 67.159515 | D22: =+D20*D21 -> 58.425913 | E22: =+E20*E21 -> 20.17652 | F22: =+F20*F21 -> 18.727115 | G22: =+G20*G21 -> 14.466836 | H22: =+H20*H21 -> 23.603248 | I22: =+I20*I21 -> 18.87563 | J22: =+J20*J21 -> 23.818208 | ... N22: =+N20*N21 -> #DIV/0!
B23: Bolsa Libro Banda Menor | C23: =IF(C41<10%,0,IF(15%<C41,2,1)) -> 2 | D23: =IF(D41<10%,0,IF(15%<D41,2,1)) -> 1 | E23: =IF(E41<10%,0,IF(15%<E41,2,1)) -> 2 | F23: =IF(F41<10%,0,IF(15%<F41,2,1)) -> 2 | G23: 2 | H23: 2 | I23: 2 | J23: 2 | K23: 2 | L23: 2 | M23: 2 | N23: 2
B24: Bolsa Libro Banda Mayor | C24: =IF(C41<10%,1,IF(15%<C41,2.5,2)) -> 2.5 | D24: =IF(D41<10%,1,IF(15%<D41,2.5,2)) -> 2 | E24: =IF(E41<10%,1,IF(15%<E41,2.5,2)) -> 2.5 | F24: =IF(F41<10%,1,IF(15%<F41,2.5,2)) -> 2.5 | G24: 2.5 | H24: 2.5 | I24: 2.5 | J24: 2.5 | K24: 2.5 | L24: 2.5 | M24: 2.5 | N24: 2.5
B25: Precio Objetivo Menor | C25: =+C23*C18 -> 1671.9515 | D25: =+D23*D18 -> 891.44235 | E25: =+E23*E18 -> 2004.3929 | F25: =+F23*F18 -> 1713.9368 | G25: =+G23*G18 -> 2273.774 | H25: =+H23*H18 -> 1807.071 | I25: =+I23*I18 -> 1872.6348 | J25: =+J23*J18 -> 2063.0457 | ... N25: =+N23*N18 -> #DIV/0!
B26: Precio Obejtivo Promedio | C26: =AVERAGE(C25,C27) -> 1880.9454 | D26: =AVERAGE(D25,D27) -> 1337.1635 | E26: =AVERAGE(E25,E27) -> 2254.942 | F26: =AVERAGE(F25,F27) -> 1928.1789 | G26: =AVERAGE(G25,G27) -> 2557.9957 | H26: =AVERAGE(H25,H27) -> 2032.9549 | I26: =AVERAGE(I25,I27) -> 2106.7142 | J26: =AVERAGE(J25,J27) -> 2320.9264 | ... N26: =AVERAGE(N25,N27) -> #DIV/0!
B27: Precio Objetivo Mayor | C27: =+C18*C24 -> 2089.9393 | D27: =+D18*D24 -> 1782.8847 | E27: =+E18*E24 -> 2505.4911 | F27: =+F18*F24 -> 2142.421 | G27: =+G18*G24 -> 2842.2175 | H27: =+H18*H24 -> 2258.8388 | I27: =+I18*I24 -> 2340.7935 | J27: =+J18*J24 -> 2578.8071 | ... N27: =+N18*N24 -> #DIV/0!
B29: Capital de Trabajo | C29: =C7-C12 -> 55722728000 | D29: =D7-D12 -> 61724353000 | E29: =E7-E12 -> 121815751000 | F29: =F7-F12 -> 419241530000 | G29: =G7-G12 -> 461418844000 | H29: =H7-H12 -> 212484258000 | I29: =I7-I12 -> 288899731000 | J29: =J7-J12 -> 107051746000 | ... N29: =N7-N12 -> 0
B30: Razón corriente | C30: =C7/C12 -> 1.1301059 | D30: =D7/D12 -> 1.147011 | E30: =E7/E12 -> 1.2959147 | F30: =F7/F12 -> 2.1089397 | G30: =G7/G12 -> 1.871313 | H30: =H7/H12 -> 1.2238455 | I30: =I7/I12 -> 1.4169602 | J30: =J7/J12 -> 1.1181399 | ... N30: =N7/N12 -> #DIV/0!
B31: Razón ácida | C31: =+(C7-C9)/C12 -> 0.82338895 | D31: =+(D7-D9)/D12 -> 0.78660766 | E31: =+(E7-E9)/E12 -> 0.93726479 | F31: =+(F7-F9)/F12 -> 1.7704381 | G31: =+(G7-G9)/G12 -> 1.5099798 | H31: =+(H7-H9)/H12 -> 0.96481162 | I31: =+(I7-I9)/I12 -> 1.0806017 | J31: =+(J7-J9)/J12 -> 0.78709878 | ... N31: =+(N7-N9)/N12 -> #DIV/0!
B32: Razón de endeudamiento | C32: =C14/C11 -> 0.61546696 | D32: =D14/D11 -> 0.60997385 | E32: =E14/E11 -> 0.59476167 | F32: =F14/F11 -> 0.66031915 | G32: =G14/G11 -> 0.62614607 | H32: =H14/H11 -> 0.70657904 | I32: =I14/I11 -> 0.68475823 | J32: =J14/J11 -> 0.69177609 | ... N32: =N14/N11 -> #DIV/0!
B35: Ingresos | C35: =+C121 -> 1848878619000 | D35: =+D121 -> 1672915799000 | E35: =+E121 -> 1779025115000 | F35: =+F121 -> 1698281237000 | G35: =+G121 -> 2216732593000 | H35: =+H121 -> 2656878395000 | I35: =+I121 -> 2618437052000 | J35: =+J121 -> 3224233005000 | ... N35: =+N121 -> 0
B36: EBIT | C36: =+C129 -> 220038553000 | D36: =+D129 -> 209213234000 | E36: =+E129 -> 252548437000 | F36: =+F129 -> 230537954000 | G36: =+G129 -> 278553672000 | H36: =+H129 -> 321771470000 | I36: =+I129 -> 316296892000 | J36: =+J129 -> 411911208000 | ... N36: =+N129 -> 0
B37: Margen EBIT | C37: =C36/C35 -> 0.1190119 | D37: =D36/D35 -> 0.12505903 | E37: =E36/E35 -> 0.14195889 | F37: =F36/F35 -> 0.13574781 | G37: =G36/G35 -> 0.12565957 | H37: =H36/H35 -> 0.12110884 | I37: =I36/I35 -> 0.12079606 | J37: =J36/J35 -> 0.12775479 | ... N37: =N36/N35 -> #DIV/0!
B38: Utilidad neta | C38: =+C137 -> 119000725000 | D38: =+D137 -> 97450746000 | E38: =+E137 -> 175246225000 | F38: =+F137 -> 123117320000 | G38: =+G137 -> 157021668000 | H38: =+H137 -> 128458987000 | I38: =+I137 -> 174511487000 | J38: =+J137 -> 234644125000 | ... N38: =+N137 -> 0
B39: Margen neto porcentual | C39: =C38/C35 -> 0.06436373 | D39: =D38/D35 -> 0.058252033 | E39: =E38/E35 -> 0.098506886 | F39: =F38/F35 -> 0.072495248 | G39: =G38/G35 -> 0.070834736 | H39: =H38/H35 -> 0.048349592 | I39: =I38/I35 -> 0.066647196 | J39: =J38/J35 -> 0.072775176 | ... N39: =N38/N35 -> #DIV/0!
B40: EPS | C40: =+C139 -> 118.56 | D40: =+D139 -> 97.2 | E40: =+E139 -> 174.79 | F40: =+F139 -> 155.75 | G40: =+G139 -> 155.65 | H40: =+H139 -> 126.27 | I40: =+I139 -> 172.49 | J40: =+J139 -> 234.09 | ... N40: =+N139 -> 0
B41: ROE | C41: =C38/C15 -> 0.15038445 | D41: =D38/D15 -> 0.11548854 | E41: =E38/E15 -> 0.18473229 | F41: =F38/F15 -> 0.15177538 | G41: =G38/G15 -> 0.14591142 | H41: =H38/H15 -> 0.15019873 | I41: =I38/I15 -> 0.196901 | J41: =J38/J15 -> 0.24031331 | ... N41: =N38/N15 -> #DIV/0!
B42: ROE PROMEDIO | C42: =AVERAGE(G41:I41) -> 0.16433705
B43: FCF | C43: =+C151 -> 79102668000 | D43: =+D151 -> 114216089000 | E43: =+E151 -> 144465216000 | F43: =+F151 -> 192894040000 | G43: =+G151 -> 166198826000 | H43: =+H151 -> 210750245000 | I43: =+I151 -> 174122738000 | J43: =+J151 -> 65700300000 | ... N43: =+N151 -> 0
B44: Dividendos calendario | C44: =SUM(C46:C49) -> 76 | D44: =SUM(D46:D49) -> 107 | E44: =SUM(E46:E49) -> 86 | F44: =SUM(F46:F49) -> 100.6 | G44: =SUM(G46:G49) -> 107 | H44: =SUM(H46:H49) -> 276 | I44: =SUM(I46:I49) -> 166 | J44: =SUM(J46:J49) -> 158 | ... N44: =SUM(N46:N49) -> 0
B45: Dividendos sin eventual Calendario | C45: =+C46+C47+C48 -> 76 | D45: =+D46+D47+D48 -> 86 | E45: =+E46+E47+E48 -> 86 | F45: =+F46+F47+F48 -> 100.6 | G45: =+G46+G47+G48 -> 107 | H45: =+H46+H47+H48 -> 116 | I45: =+I46+I47+I48 -> 116 | J45: =+J46+J47+J48 -> 158 | ... N45: =+N46+N47+N48 -> 0
B46: Definitivo año calendario | C46: 19 | D46: 21.5 | E46: 21.5 | F46: 26 | G46: 26 | J46: =32+32+30 -> 94 | L46: 102
B47: Provisorio calendario | C47: =19+19 -> 38 | D47: =21.5+21.5 -> 43 | E47: =21.5+21.5 -> 43 | F47: =26+22.6 -> 48.6 | G47: =29+26 -> 55 | H47: =29+29+29 -> 87 | I47: =29+29+29 -> 87 | J47: =32+32 -> 64 | K47: =141+35+20 -> 196
B48: Adicional calendario | C48: 19 | D48: 21.5 | E48: 21.5 | F48: 26 | G48: 26 | H48: 29 | I48: 29
B49: Eventual calendario | D49: 21 | H49: 160 | I49: 50
B50: Dividendos | C50: =SUM(C52:C55) -> 81 | D50: =SUM(D52:D55) -> 86 | E50: =SUM(E52:E55) -> 91.6 | F50: =SUM(F52:F55) -> 104 | G50: =SUM(G52:G55) -> 273 | H50: =SUM(H52:H55) -> 166 | I50: =SUM(I52:I55) -> 152 | J50: =SUM(J52:J55) -> 205 | ... N50: =SUM(N52:N55) -> 0
B51: Dividendos sin eventual | C51: =+C52+C53+C54 -> 81 | D51: =+D52+D53+D54 -> 86 | E51: =+E52+E53+E54 -> 91.6 | F51: =+F52+F53+F54 -> 104 | G51: =+G52+G53+G54 -> 113 | H51: =+H52+H53+H54 -> 116 | I51: =+I52+I53+I54 -> 152 | J51: =+J52+J53+J54 -> 205 | ... N51: =+N52+N53+N54 -> 0
B52: Definitivo | C52: 21.5 | D52: 21.5 | E52: 26 | F52: 26 | I52: =30+32+32 -> 94 | K52: 102
B53: Provisorio | C53: =21.5+19 -> 40.5 | D53: =21.5+21.5 -> 43 | E53: =22.6+21.5 -> 44.1 | F53: =26+26 -> 52 | G53: =29+29 -> 58 | H53: =29+29+29 -> 87 | I53: =29+29 -> 58 | J53: =141+32+32 -> 205 | K53: =35+20 -> 55
B54: Adicional | C54: 19 | D54: 21.5 | E54: 21.5 | F54: 26 | G54: =29+26 -> 55 | H54: 29
B55: Eventual | G55: 160 | H55: 50
B56: PAY OUT | C56: =(C52+C53+C54)/C40 -> 0.68319838 | D56: =(D52+D53+D54)/D40 -> 0.88477366 | E56: =(E52+E53+E54)/E40 -> 0.52405744 | F56: =(F52+F53+F54)/F40 -> 0.66773676 | G56: =(G52+G53+G54)/G40 -> 0.72598779 | H56: =(H52+H53+H54)/H40 -> 0.91866635 | I56: =(I52+I53+I54)/I40 -> 0.8812105 | J56: =(J52+J53+J54)/J40 -> 0.87573156 | ... N56: =(N52+N53+N54)/N40 -> #DIV/0!
B57: PAY OUT PROMEDIO 3 AÑOS | C57: =AVERAGE(H56:J56) -> 0.89186947
B58: DIV/YIELD | C58: =+D45/C19 -> 0.033333333 | D58: =+E45/D19 -> 0.038222222 | E58: =+F45/E19 -> 0.053510638 | F58: =+G45/F19 -> 0.067678684 | G58: =+H45/G19 -> 0.0725 | H58: =+I45/H19 -> 0.070688605 | I58: =+J45/I19 -> 0.090492554 | J58: =+K45/J19 -> 0.081727963 | ... N58: =+O45/N19 -> #DIV/0!
B59: DIVIDEND YIELD PROM 3 AÑOS | C59: =AVERAGE(G58:I58) -> 0.07789372
B60: G | C60: =+C41*(100%-C56) -> 0.047642036 | D60: =+D41*(100%-D56) -> 0.013307321 | E60: =+E41*(100%-E56) -> 0.087921957 | F60: =+F41*(100%-F56) -> 0.050429379 | G60: =+G41*(100%-G56) -> 0.03998151 | H60: =+H41*(100%-H56) -> 0.012216211 | I60: =+I41*(100%-I56) -> 0.02338977 | J60: =+J41*(100%-J56) -> 0.029863361 | ... N60: =+N41*(100%-N56) -> #DIV/0!
B61: G PROMEDIO 3 AÑOS | C61: =AVERAGE(G60:I60) -> 0.02519583
B62: PRECIO | C62: =B3 -> 3475
B64: ESTADO DE SITUACIÓN (BALANCE)
B66: AÑOS | C66: 2017 | D66: 2018 | E66: 2019 | F66: 2020 | G66: 2021 | H66: 2022 | I66: 2023 | J66: 2024 | K66: 2025 | L66: 2026 | M66: 2027 | N66: 2028
B67: ACTIVOS
B68: CORRIENTES (CIRCULANTES) | C68: 484010050000 | D68: 481586454000 | E68: 533474103000 | F68: 797297716000 | G68: 990986123000 | H68: 1161729392000 | I68: 981771027000 | J68: 1013195740000 | K68: 1033052781000
B69: Efectivo y equivalentes al efectivo | C69: 136242116000 | D69: 137538613000 | E69: 157567986000 | F69: 309530699000 | G69: 304312020000 | H69: 291681987000 | I69: 303683683000 | J69: 248899004000 | K69: 296539709000
B70: Otros activos financieros, corrientes | C70: 14138161000 | D70: 683567000 | E70: 347278000 | F70: 140304853000 | G70: 195470749000 | H70: 263044869000 | I70: 67285793000 | J70: 76586583000 | K70: 45974709000
B71: Otros activos no financieros, corrientes | C71: 5611861000 | D71: 5948923000 | E71: 16188965000 | F71: 13374381000 | G71: 14719104000 | H71: 26957000000 | I71: 19311851000 | J71: 27260507000 | K71: 15985896000
B72: Deudores comerciales y otras cuentas por cobrar, corrientes | C72: 191284680000 | D72: 174113323000 | E72: 191077588000 | F72: 194021253000 | G72: 265490626000 | H72: 279770286000 | I72: 298892164000 | J72: 332831088000 | K72: 339778498000
B73: Cuentas por cobrar entidades relacionadas, corriente neto | C73: 5370232000 | D73: 9450263000 | E73: 10835768000 | F73: 11875408000 | G73: 9419050000 | H73: 15062167000 | I73: 16161318000 | J73: 9901543000 | K73: 15299187000
B74: Inventarios, neto | C74: 131363000000 | D74: 151319709000 | E74: 147641224000 | F74: 127972650000 | G74: 191350206000 | H74: 245886656000 | I74: 233053160000 | J74: 299970909000 | K74: 304550609000
B75: Activos por impuestos corrientes | D75: 2532056000 | E75: 9815294000 | F75: 218472000 | G75: 10224368000 | H75: 39326427000 | I75: 43383058000 | J75: 17746106000 | K75: 14924173000
B76: OTROS CORRIENTES | C76: =+C68-C69-C74-C75-C73-C72-C71-C70 -> 0 | D76: =+D68-D69-D74-D75-D73-D72-D71-D70 -> 0 | E76: =+E68-E69-E74-E75-E73-E72-E71-E70 -> 0 | F76: =+F68-F69-F74-F75-F73-F72-F71-F70 -> 0 | G76: =+G68-G69-G74-G75-G73-G72-G71-G70 -> 0 | H76: =+H68-H69-H74-H75-H73-H72-H71-H70 -> 0 | I76: =+I68-I69-I74-I75-I73-I72-I71-I70 -> 0 | J76: =+J68-J69-J74-J75-J73-J72-J71-J70 -> 0 | ... N76: =+N68-N69-N74-N75-N73-N72-N71-N70 -> 0
B77: NO CORRIENTES (NO CIRCULANTES) | C77: 1630849417000 | D77: 1732918235000 | E77: 1857474320000 | F77: 1650766684000 | G77: 1955120524000 | H77: 1848971215000 | I77: 1939749862000 | J77: 2277908533000 | K77: 2387352637000
B78: Otros activos financieros, no corrientes | C78: 74259085000 | D78: 97362295000 | E78: 110784311000 | F78: 162013278000 | G78: 296632012000 | H78: 94852711000 | I78: 93316339000 | J78: 169420303000 | K78: 164370936000
B79: Otros activos no financieros, no corrientes | C79: 47394345000 | D79: 34977264000 | E79: 125636150000 | F79: 90242672000 | G79: 70861616000 | H79: 59672266000 | I79: 59412482000 | J79: 79746695000 | K79: 82913107000
B80: Cuentas por cobrar | C80: 2395851000 | D80: 1270697000 | E80: 523769000 | F80: 73862000 | G80: 126464000 | H80: 539920000 | I80: 371401000 | J80: 335723000 | K80: 187644000
B81: Cuentas por cobrar a entidades relacionadas | C81: 156492000 | D81: 74340000 | E81: 283118000 | F81: 138346000 | G81: 98941000 | H81: 109318000 | I81: 108021000 | J81: 292931000 | K81: 8000924000
B82: Inversiones contabilizadas utilizando el método de la participación | C82: 86809069000 | D82: 102410945000 | E82: 99866733000 | F82: 87956354000 | G82: 91489194000 | H82: 92344598000 | I82: 91799267000 | J82: 85192710000 | K82: 87087871000
B83: Activos Intangibles distintos de plusvalía | C83: 663272878000 | D83: 668822553000 | E83: 675075375000 | F83: 604514165000 | G83: 659631543000 | H83: 671778888000 | I83: 695926565000 | J83: 693383630000 | K83: 719489720000
B84: Plusvalía | C84: 93598217000 | D84: 117229173000 | E84: 121221661000 | F84: 98325593000 | G84: 118042900000 | H84: 129023922000 | I84: 122103802000 | J84: 144681420000 | K84: 137128318000
B85: Propiedades, plantas y equipos | C85: 659750499000 | D85: 710770968000 | E85: 722718863000 | F85: 605576545000 | G85: 716379127000 | H85: 798221259000 | I85: 872388811000 | J85: 1097773572000 | K85: 1179385259000
B86: Activos por impuestos diferidos, no corrientes | C86: 3212981000 | D86: 0 | E86: 1364340000 | F86: 1925869000 | G86: 1858727000 | H86: 2428333000 | I86: 4323174000 | J86: 7081549000 | K86: 8788858000
B87: OTROS NO CORRIENTES | C87: =+C77-C84-C85-C83-C78-C86-C82-C81-C80-C79 -> 0 | D87: =+D77-D84-D85-D83-D78-D86-D82-D81-D80-D79 -> 0 | E87: =+E77-E84-E85-E83-E78-E86-E82-E81-E80-E79 -> 0 | F87: =+F77-F84-F85-F83-F78-F86-F82-F81-F80-F79 -> 0 | G87: =+G77-G84-G85-G83-G78-G86-G82-G81-G80-G79 -> 0 | H87: =+H77-H84-H85-H83-H78-H86-H82-H81-H80-H79 -> 0 | I87: =+I77-I84-I85-I83-I78-I86-I82-I81-I80-I79 -> 0 | J87: =+J77-J84-J85-J83-J78-J86-J82-J81-J80-J79 -> 0 | K87: $ - | L87: =+L77-L84-L85-L83-L78-L86-L82-L81-L80-L79 -> 0 | M87: =+M77-M84-M85-M83-M78-M86-M82-M81-M80-M79 -> 0 | N87: =+N77-N84-N85-N83-N78-N86-N82-N81-N80-N79 -> 0
B88: TOTAL ACTIVOS | C88: =+C77+C68 -> 2114859467000 | D88: =+D77+D68 -> 2214504689000 | E88: =+E77+E68 -> 2390948423000 | F88: =+F77+F68 -> 2448064400000 | G88: =+G77+G68 -> 2946106647000 | H88: =+H77+H68 -> 3010700607000 | I88: =+I77+I68 -> 2921520889000 | J88: =+J77+J68 -> 3291104273000 | ... N88: =+N77+N68 -> 0
B90: PASIVOS
B91: CORRIENTES (CIRCULANTES) | C91: 428287322000 | D91: 419862101000 | E91: 411658352000 | F91: 378056186000 | G91: 529567279000 | H91: 949245134000 | I91: 692871296000 | J91: 906143994000 | K91: 730412517000
B92: Otros pasivos financieros | C92: 67981405000 | D92: 56114977000 | E92: 40593878000 | F92: 38566724000 | G92: 47763039000 | H92: 367302080000 | I92: 52997001000 | J92: 110330460000 | K92: 62418990000
B93: Cuentas por pagar comerciales y otras cuentas por pagar | C93: 257519477000 | D93: 238109847000 | E93: 243700553000 | F93: 230445809000 | G93: 327409207000 | H93: 384801630000 | I93: 428911984000 | J93: 457074643000 | K93: 480396027000
B94: Cuenetas por pagar a entidades relacionadas | C94: 33961437000 | D94: 45827859000 | E94: 53637601000 | F94: 39541968000 | G94: 56103461000 | H94: 90248067000 | I94: 96045624000 | J94: 94376420000 | K94: 102102553000
B95: Otras provisiones | C95: 2676418000 | D95: 3485613000 | E95: 2068984000 | F95: 1335337000 | G95: 1528879000 | H95: 1591644000 | I95: 1314106000 | J95: 1522426000 | K95: 2433147000
B96: Pasivos por impuestos | C96: 3184965000 | D96: 9338612000 | E96: 6762267000 | F96: 8828599000 | G96: 30512787000 | H96: 14615447000 | I96: 13411621000 | J96: 28369276000 | K96: 14207862000
B97: Provisiones corrientes por beneficios a los empleados | C97: 35955643000 | D97: 33210979000 | E97: 38392854000 | F97: 31071019000 | G97: 35012072000 | H97: 48391806000 | I97: 57817800000 | J97: 72367187000 | K97: 68363971000
B98: Otros pasivos no financieros | C98: 27007977000 | D98: 33774214000 | E98: 26502215000 | F98: 28266730000 | G98: 31237834000 | H98: 42294460000 | I98: 42373160000 | J98: 142103582000 | K98: 489967000
B100: Otros | C100: =+C91-C92-C98-C99-C97-C96-C95-C94-C93 -> 0 | D100: =+D91-D92-D98-D99-D97-D96-D95-D94-D93 -> 0 | E100: =+E91-E92-E98-E99-E97-E96-E95-E94-E93 -> 0 | F100: =+F91-F92-F98-F99-F97-F96-F95-F94-F93 -> 0 | G100: =+G91-G92-G98-G99-G97-G96-G95-G94-G93 -> 0 | H100: =+H91-H92-H98-H99-H97-H96-H95-H94-H93 -> 0 | I100: =+I91-I92-I98-I99-I97-I96-I95-I94-I93 -> 0 | J100: =+J91-J92-J98-J99-J97-J96-J95-J94-J93 -> 0 | ... N100: =+N91-N92-N98-N99-N97-N96-N95-N94-N93 -> 0
B101: NO CORRIENTES (NO CIRCULANTES) | C101: 873338796000 | D101: 930927845000 | E101: 1010386123000 | F101: 1238447623000 | G101: 1315125809000 | H101: 1178052821000 | I101: 1307664179000 | J101: 1370563259000 | K101: 1493439053000
B102: Otros pasivos financieros | C102: 675767201000 | D102: 716563778000 | E102: 743327057000 | F102: 989829569000 | G102: 1041048972000 | H102: 904802058000 | I102: 1044325833000 | J102: 1066543247000 | K102: 1191795823000
B103: Cuentas por pagar comerciales y otras cuentas por pagar | C103: 1132926000 | D103: 735665000 | E103: 619587000 | F103: 295279000 | G103: 256273000 | H103: 3015284000 | I103: 2392555000 | J103: 2534836000 | K103: 685605000
B104: Cuentas por pagar a entidades relacionadas | E104: 19777812000 | F104: 10790089000 | G104: 11557723000 | H104: 10354296000 | I104: 6007041000 | J104: 380465000 | K104: 0
B105: Otras provisiones | C105: 62947748000 | D105: 58966913000 | E105: 67038566000 | F105: 48734936000 | G105: 55883527000 | H105: 47103783000 | I105: 53487790000 | J105: 53723373000 | K105: 55378062000
B106: Pasivos por impuestos diferidos | C106: 125204566000 | D106: 145245948000 | E106: 169449747000 | F106: 153669547000 | G106: 168454827000 | H106: 165778556000 | I106: 180470219000 | J106: 224967885000 | K106: 218673311000
B107: Provisiones no corrientes por beneficios a los empleados | C107: 8286355000 | D107: 9415541000 | E107: 10173354000 | F107: 13635558000 | G107: 14139670000 | H107: 17409793000 | I107: 18473946000 | J107: 20160468000 | K107: 23123294000
B108: Otros pasivos no finacieros | F108: 21472048000 | G108: 23784817000 | H108: 29589051000 | I108: 2506795000 | J108: 2252985000 | K108: 3782958000
B109: OTROS | C109: =+C101-C102-C103-C104-C105-C106-C107-C108 -> 0 | D109: =+D101-D102-D103-D104-D105-D106-D107-D108 -> 0 | E109: =+E101-E102-E103-E104-E105-E106-E107-E108 -> 0 | F109: =+F101-F102-F103-F104-F105-F106-F107-F108 -> 20597000 | G109: =+G101-G102-G103-G104-G105-G106-G107-G108 -> 0 | H109: =+H101-H102-H103-H104-H105-H106-H107-H108 -> 0 | I109: =+I101-I102-I103-I104-I105-I106-I107-I108 -> 0 | J109: =+J101-J102-J103-J104-J105-J106-J107-J108 -> 0 | ... N109: =+N101-N102-N103-N104-N105-N106-N107-N108 -> 0
B110: TOTAL PASIVOS | C110: =+C101+C91 -> 1301626118000 | D110: =+D101+D91 -> 1350789946000 | E110: =+E101+E91 -> 1422044475000 | F110: =+F101+F91 -> 1616503809000 | G110: =+G101+G91 -> 1844693088000 | H110: =+H101+H91 -> 2127297955000 | I110: =+I101+I91 -> 2000535475000 | J110: =+J101+J91 -> 2276707253000 | ... N110: =+N101+N91 -> 0
B112: PATRIMONIO
...

Sheet ANDINA B
B2: =TODAY()-1 -> 46105 | D2: PROM DIVIDENDOS SIN EVENT | E2: PROM DIVIDENDOS TOTALES
B3: {=_FV(B6,"Precio")} -> 3940 | D3: =AVERAGE(H45:J45) -> 143 | E3: =AVERAGE(H44:J44) -> 220
G4: victor
B6: #VALUE! | C6: 2017 | D6: 2018 | E6: 2019 | F6: 2020 | G6: 2021 | H6: 2022 | I6: 2023 | J6: 2024 | K6: 2025 | L6: 2026 | M6: 2027 | N6: 2028
B7: Activos corrientes | C7: =+C68 -> 484010050000 | D7: =+D68 -> 481586454000 | E7: =+E68 -> 533474103000 | F7: =+F68 -> 797297716000 | G7: =+G68 -> 990986123000 | H7: =+H68 -> 1161729392000 | I7: =+I68 -> 981771027000 | J7: =+J68 -> 1013195740000 | ... N7: =+N68 -> 0
B8: Cuentas por cobrar | C8: =+C72 -> 191284680000 | D8: =+D72 -> 174113323000 | E8: =+E72 -> 191077588000 | F8: =+F72 -> 194021253000 | G8: =+G72 -> 265490626000 | H8: =+H72 -> 279770286000 | I8: =+I72 -> 298892164000 | J8: =+J72 -> 332831088000 | ... N8: =+N72 -> 0
B9: Inventario | C9: =+C74 -> 131363000000 | D9: =+D74 -> 151319709000 | E9: =+E74 -> 147641224000 | F9: =+F74 -> 127972650000 | G9: =+G74 -> 191350206000 | H9: =+H74 -> 245886656000 | I9: =+I74 -> 233053160000 | J9: =+J74 -> 299970909000 | ... N9: =+N74 -> 0
B10: Acitvos no corrientes (no circulantes o fijos) | C10: =+C77 -> 1630849417000 | D10: =+D77 -> 1732918235000 | E10: =+E77 -> 1857474320000 | F10: =+F77 -> 1650766684000 | G10: =+G77 -> 1955120524000 | H10: =+H77 -> 1848971215000 | I10: =+I77 -> 1939749862000 | J10: =+J77 -> 2277908533000 | ... N10: =+N77 -> 0
B11: Activos totales | C11: =+C7+C10 -> 2114859467000 | D11: =+D7+D10 -> 2214504689000 | E11: =+E7+E10 -> 2390948423000 | F11: =+F7+F10 -> 2448064400000 | G11: =+G7+G10 -> 2946106647000 | H11: =+H7+H10 -> 3010700607000 | I11: =+I7+I10 -> 2921520889000 | J11: =+J7+J10 -> 3291104273000 | ... N11: =+N7+N10 -> 0
B12: Pasivos corrientes | C12: =+C91 -> 428287322000 | D12: =+D91 -> 419862101000 | E12: =+E91 -> 411658352000 | F12: =+F91 -> 378056186000 | G12: =+G91 -> 529567279000 | H12: =+H91 -> 949245134000 | I12: =+I91 -> 692871296000 | J12: =+J91 -> 906143994000 | ... N12: =+N91 -> 0
B13: Pasivos no corrientes | C13: =+C101 -> 873338796000 | D13: =+D101 -> 930927845000 | E13: =+E101 -> 1010386123000 | F13: =+F101 -> 1238447623000 | G13: =+G101 -> 1315125809000 | H13: =+H101 -> 1178052821000 | I13: =+I101 -> 1307664179000 | J13: =+J101 -> 1370563259000 | ... N13: =+N101 -> 0
B14: Total Pasivos | C14: =SUM(C12:C13) -> 1301626118000 | D14: =SUM(D12:D13) -> 1350789946000 | E14: =SUM(E12:E13) -> 1422044475000 | F14: =SUM(F12:F13) -> 1616503809000 | G14: =SUM(G12:G13) -> 1844693088000 | H14: =SUM(H12:H13) -> 2127297955000 | I14: =SUM(I12:I13) -> 2000535475000 | J14: =SUM(J12:J13) -> 2276707253000 | ... N14: =SUM(N12:N13) -> 0
B15: Patrimonio | C15: =+C117 -> 791310056000 | D15: =+D117 -> 843813126000 | E15: =+E117 -> 948649690000 | F15: =+F117 -> 811181114000 | G15: =+G117 -> 1076143804000 | H15: =+H117 -> 855260144000 | I15: =+I117 -> 886290527000 | J15: =+J117 -> 976409192000 | ... N15: =+N117 -> 0
B16: Cantidad de acciones | C16: 946570604 | D16: 946570604 | E16: 946570604 | F16: 946570604 | G16: 946570604 | H16: 946570604 | I16: 946570604 | J16: 946570604 | K16: 946570604
B18: Valor libro | C18: =(C15/C16) -> 835.97573 | D18: =(D15/D16) -> 891.44235 | E18: =(E15/E16) -> 1002.1964 | F18: =(F15/F16) -> 856.96842 | G18: =(G15/G16) -> 1136.887 | H18: =(H15/H16) -> 903.5355 | I18: =(I15/I16) -> 936.3174 | J18: =(J15/J16) -> 1031.5228 | ... N18: =(N15/N16) -> #DIV/0!
B19: Precio FIN AÑO | C19: 3074 | D19: 2598 | E19: 2179 | F19: 1832 | G19: 1850 | H19: 2083 | I19: 2200 | J19: 3025 | K19: 4220
B20: PER | C20: =+C19/C40 -> 23.570005 | D20: =+D19/D40 -> 24.298541 | E20: =+E19/E40 -> 11.333021 | F20: =+F19/F40 -> 13.56836 | G20: =+G19/G40 -> 10.805444 | H20: =+H19/H40 -> 14.99748 | I20: =+I19/I40 -> 11.594814 | J20: =+J19/J40 -> 11.747573 | ... N20: =+N19/N40 -> #DIV/0!
B21: Bolsa/Libro SERIE B | C21: =+C19/C18 -> 3.6771402 | D21: =+D19/D18 -> 2.914378 | E21: =+E19/E18 -> 2.1742244 | F21: =+F19/F18 -> 2.1377684 | G21: =+G19/G18 -> 1.6272506 | H21: =+H19/H18 -> 2.3053881 | I21: =+I19/I18 -> 2.3496306 | J21: =+J19/J18 -> 2.9325575 | ... N21: =+N19/N18 -> #DIV/0!
B22: GRAHAM SERIE B | C22: =+C20*C21 -> 86.670212 | D22: =+D20*D21 -> 70.815134 | E22: =+E20*E21 -> 24.640532 | F22: =+F20*F21 -> 29.006012 | G22: =+G20*G21 -> 17.583164 | H22: =+H20*H21 -> 34.575012 | I22: =+I20*I21 -> 27.243529 | J22: =+J20*J21 -> 34.450433 | ... N22: =+N20*N21 -> #DIV/0!
B23: Bolsa Libro Banda Menor | C23: =IF(C41<10%,0,IF(15%<C41,2,1)) -> 2 | D23: =IF(D41<10%,0,IF(15%<D41,2,1)) -> 1 | E23: =IF(E41<10%,0,IF(15%<E41,2,1)) -> 2 | F23: =IF(F41<10%,0,IF(15%<F41,2,1)) -> 2 | G23: 2 | H23: 2 | I23: 2 | J23: 2 | K23: 2 | L23: 2 | M23: 2 | N23: 2
B24: Bolsa Libro Banda Mayor | C24: =IF(C41<10%,1,IF(15%<C41,2.5,2)) -> 2.5 | D24: =IF(D41<10%,1,IF(15%<D41,2.5,2)) -> 2 | E24: =IF(E41<10%,1,IF(15%<E41,2.5,2)) -> 2.5 | F24: =IF(F41<10%,1,IF(15%<F41,2.5,2)) -> 2.5 | G24: 2.5 | H24: 2.5 | I24: 2.5 | J24: 2.5 | K24: 2.5 | L24: 2.5 | M24: 2.5 | N24: 2.5
B25: Precio Objetivo Menor | C25: =+C23*C18 -> 1671.9515 | D25: =+D23*D18 -> 891.44235 | E25: =+E23*E18 -> 2004.3929 | F25: =+F23*F18 -> 1713.9368 | G25: =+G23*G18 -> 2273.774 | H25: =+H23*H18 -> 1807.071 | I25: =+I23*I18 -> 1872.6348 | J25: =+J23*J18 -> 2063.0457 | ... N25: =+N23*N18 -> #DIV/0!
B26: Precio Obejtivo Promedio | C26: =AVERAGE(C25,C27) -> 1880.9454 | D26: =AVERAGE(D25,D27) -> 1337.1635 | E26: =AVERAGE(E25,E27) -> 2254.942 | F26: =AVERAGE(F25,F27) -> 1928.1789 | G26: =AVERAGE(G25,G27) -> 2557.9957 | H26: =AVERAGE(H25,H27) -> 2032.9549 | I26: =AVERAGE(I25,I27) -> 2106.7142 | J26: =AVERAGE(J25,J27) -> 2320.9264 | ... N26: =AVERAGE(N25,N27) -> #DIV/0!
B27: Precio Objetivo Mayor | C27: =+C18*C24 -> 2089.9393 | D27: =+D18*D24 -> 1782.8847 | E27: =+E18*E24 -> 2505.4911 | F27: =+F18*F24 -> 2142.421 | G27: =+G18*G24 -> 2842.2175 | H27: =+H18*H24 -> 2258.8388 | I27: =+I18*I24 -> 2340.7935 | J27: =+J18*J24 -> 2578.8071 | ... N27: =+N18*N24 -> #DIV/0!
B29: Capital de Trabajo | C29: =C7-C12 -> 55722728000 | D29: =D7-D12 -> 61724353000 | E29: =E7-E12 -> 121815751000 | F29: =F7-F12 -> 419241530000 | G29: =G7-G12 -> 461418844000 | H29: =H7-H12 -> 212484258000 | I29: =I7-I12 -> 288899731000 | J29: =J7-J12 -> 107051746000 | ... N29: =N7-N12 -> 0
B30: Razón corriente | C30: =C7/C12 -> 1.1301059 | D30: =D7/D12 -> 1.147011 | E30: =E7/E12 -> 1.2959147 | F30: =F7/F12 -> 2.1089397 | G30: =G7/G12 -> 1.871313 | H30: =H7/H12 -> 1.2238455 | I30: =I7/I12 -> 1.4169602 | J30: =J7/J12 -> 1.1181399 | ... N30: =N7/N12 -> #DIV/0!
B31: Razón ácida | C31: =+(C7-C9)/C12 -> 0.82338895 | D31: =+(D7-D9)/D12 -> 0.78660766 | E31: =+(E7-E9)/E12 -> 0.93726479 | F31: =+(F7-F9)/F12 -> 1.7704381 | G31: =+(G7-G9)/G12 -> 1.5099798 | H31: =+(H7-H9)/H12 -> 0.96481162 | I31: =+(I7-I9)/I12 -> 1.0806017 | J31: =+(J7-J9)/J12 -> 0.78709878 | ... N31: =+(N7-N9)/N12 -> #DIV/0!
B32: Razón de endeudamiento | C32: =C14/C11 -> 0.61546696 | D32: =D14/D11 -> 0.60997385 | E32: =E14/E11 -> 0.59476167 | F32: =F14/F11 -> 0.66031915 | G32: =G14/G11 -> 0.62614607 | H32: =H14/H11 -> 0.70657904 | I32: =I14/I11 -> 0.68475823 | J32: =J14/J11 -> 0.69177609 | ... N32: =N14/N11 -> #DIV/0!
B35: Ingresos | C35: =+C121 -> 1848878619000 | D35: =+D121 -> 1672915799000 | E35: =+E121 -> 1779025115000 | F35: =+F121 -> 1698281237000 | G35: =+G121 -> 2216732593000 | H35: =+H121 -> 2656878395000 | I35: =+I121 -> 2618437052000 | J35: =+J121 -> 3224233005000 | ... N35: =+N121 -> 0
B36: EBIT | C36: =+C129 -> 220038553000 | D36: =+D129 -> 209213234000 | E36: =+E129 -> 252548437000 | F36: =+F129 -> 230537954000 | G36: =+G129 -> 278553672000 | H36: =+H129 -> 321771470000 | I36: =+I129 -> 316296892000 | J36: =+J129 -> 411911208000 | ... N36: =+N129 -> 0
B37: Margen EBIT | C37: =C36/C35 -> 0.1190119 | D37: =D36/D35 -> 0.12505903 | E37: =E36/E35 -> 0.14195889 | F37: =F36/F35 -> 0.13574781 | G37: =G36/G35 -> 0.12565957 | H37: =H36/H35 -> 0.12110884 | I37: =I36/I35 -> 0.12079606 | J37: =J36/J35 -> 0.12775479 | ... N37: =N36/N35 -> #DIV/0!
B38: Utilidad neta | C38: =+C137 -> 119000725000 | D38: =+D137 -> 97450746000 | E38: =+E137 -> 175246225000 | F38: =+F137 -> 123117320000 | G38: =+G137 -> 157021668000 | H38: =+H137 -> 128458987000 | I38: =+I137 -> 174511487000 | J38: =+J137 -> 234644125000 | ... N38: =+N137 -> 0
B39: Margen neto porcentual | C39: =C38/C35 -> 0.06436373 | D39: =D38/D35 -> 0.058252033 | E39: =E38/E35 -> 0.098506886 | F39: =F38/F35 -> 0.072495248 | G39: =G38/G35 -> 0.070834736 | H39: =H38/H35 -> 0.048349592 | I39: =I38/I35 -> 0.066647196 | J39: =J38/J35 -> 0.072775176 | ... N39: =N38/N35 -> #DIV/0!
B40: EPS | C40: =+C139 -> 130.42 | D40: =+D139 -> 106.92 | E40: =+E139 -> 192.27 | F40: =+F139 -> 135.02 | G40: =+G139 -> 171.21 | H40: =+H139 -> 138.89 | I40: =+I139 -> 189.74 | J40: =+J139 -> 257.5 | ... N40: =+N139 -> 0
B41: ROE | C41: =C38/C15 -> 0.15038445 | D41: =D38/D15 -> 0.11548854 | E41: =E38/E15 -> 0.18473229 | F41: =F38/F15 -> 0.15177538 | G41: =G38/G15 -> 0.14591142 | H41: =H38/H15 -> 0.15019873 | I41: =I38/I15 -> 0.196901 | J41: =J38/J15 -> 0.24031331 | ... N41: =N38/N15 -> #DIV/0!
B42: ROE PROMEDIO | C42: =AVERAGE(E41:I41) -> 0.16590376
B43: FCF | C43: =+C151 -> 79102668000 | D43: =+D151 -> 114216089000 | E43: =+E151 -> 144465216000 | F43: =+F151 -> 192894040000 | G43: =+G151 -> 166198826000 | H43: =+H151 -> 210750245000 | I43: =+I151 -> 174122738000 | J43: =+J151 -> 65700300000 | ... N43: =+N151 -> 0
B44: Dividendos calendario | C44: =SUM(C46:C49) -> 83.6 | D44: =SUM(D46:D49) -> 94.6 | E44: =SUM(E46:E49) -> 94.6 | F44: =SUM(F46:F49) -> 110.66 | G44: =SUM(G46:G49) -> 117.7 | H44: =SUM(H46:H49) -> 303.6 | I44: =SUM(I46:I49) -> 182.6 | J44: =SUM(J46:J49) -> 173.8 | ... N44: =SUM(N46:N49) -> 0
B45: Dividendos sin eventual Calendario | C45: =+C46+C47+C48 -> 83.6 | D45: =+D46+D47+D48 -> 94.6 | E45: =+E46+E47+E48 -> 94.6 | F45: =+F46+F47+F48 -> 110.66 | G45: =+G46+G47+G48 -> 117.7 | H45: =+H46+H47+H48 -> 127.6 | I45: =+I46+I47+I48 -> 127.6 | J45: =+J46+J47+J48 -> 173.8 | ... N45: =+N46+N47+N48 -> 0
B46: Definitivo año calendario | C46: 20.9 | D46: 23.65 | E46: 23.65 | F46: 28.6 | G46: 28.6 | J46: =35.2+33 -> 68.2 | L46: 112.2
B47: Provisorio calendario | C47: =20.9+20.9 -> 41.8 | D47: =23.65+23.65 -> 47.3 | E47: =23.65+23.65 -> 47.3 | F47: =28.6+24.86 -> 53.46 | G47: =31.9+28.6 -> 60.5 | H47: =31.9+31.9+31.9 -> 95.7 | I47: =31.9+31.9+31.9 -> 95.7 | J47: =35.2+35.2+35.2 -> 105.6 | K47: =155.1+38.5+22 -> 215.6
B48: Adicional calendario | C48: 20.9 | D48: 23.65 | E48: 23.65 | F48: 28.6 | G48: 28.6 | H48: 31.9 | I48: 31.9
B49: Eventual calendario | H49: 176 | I49: 55
B50: Dividendos | C50: =SUM(C52:C55) -> 91.85 | D50: =SUM(D52:D55) -> 94.6 | E50: =SUM(E52:E55) -> 100.76 | F50: =SUM(F52:F55) -> 114.4 | G50: =SUM(G52:G55) -> 300.2 | H50: =SUM(H52:H55) -> 182.6 | I50: =SUM(I52:I55) -> 167.2 | J50: =SUM(J52:J55) -> 225.5 | ... N50: =SUM(N52:N55) -> 0
B51: Dividendos sin eventual | C51: =+C52+C53+C54 -> 91.85 | D51: =+D52+D53+D54 -> 94.6 | E51: =+E52+E53+E54 -> 100.76 | F51: =+F52+F53+F54 -> 114.4 | G51: =+G52+G53+G54 -> 124.2 | H51: =+H52+H53+H54 -> 127.6 | I51: =+I52+I53+I54 -> 167.2 | J51: =+J52+J53+J54 -> 225.5 | ... N51: =+N52+N53+N54 -> 0
B52: Definitivo | C52: 23.65 | D52: 23.65 | E52: 28.6 | F52: 28.6 | I52: =33 + 35.2 -> 68.2 | K52: 112.2
B53: Provisorio | C53: =23.65*2 -> 47.3 | D53: =23.65*2 -> 47.3 | E53: =23.65+24.86 -> 48.51 | F53: =28.6*2 -> 57.2 | G53: =31.9*2 -> 63.8 | H53: =31.9*3 -> 95.7 | I53: =35.2 + 31.9 + 31.9 -> 99 | J53: =155.1 +35.2 + 35.2 -> 225.5 | K53: =38.5+22 -> 60.5
B54: Adicional | C54: 20.9 | D54: 23.65 | E54: 23.65 | F54: 28.6 | G54: =31.8 + 28.6 -> 60.4 | H54: 31.9
B55: Eventual | G55: 176 | H55: 55
B56: PAY OUT | C56: =(C52+C53+C54)/C40 -> 0.70426315 | D56: =(D52+D53+D54)/D40 -> 0.88477366 | E56: =(E52+E53+E54)/E40 -> 0.52405471 | F56: =(F52+F53+F54)/F40 -> 0.84728188 | G56: =(G52+G53+G54)/G40 -> 0.72542492 | H56: =(H52+H53+H54)/H40 -> 0.91871265 | I56: =(I52+I53+I54)/I40 -> 0.88120586 | J56: =(J52+J53+J54)/J40 -> 0.87572816 | ... N56: =(N52+N53+N54)/N40 -> #DIV/0!
B57: PAY OUT PROMEDIO 3 AÑOS | C57: =AVERAGE(G56:I56) -> 0.84178114 | I57: =AVERAGE(H56:J56) -> 0.89188222
B58: DIV/YIELD | C58: =+D44/C19 -> 0.030774236 | D58: =+E44/D19 -> 0.036412625 | E58: =+F44/E19 -> 0.050784764 | F58: =+G45/F19 -> 0.064246725 | G58: =+H45/G19 -> 0.068972973 | H58: =+I45/H19 -> 0.061257801 | I58: =+J45/I19 -> 0.079 | J58: =+K45/J19 -> 0.071272727 | K58: =+L45/K19 -> 0.026587678 | L58: =+M45/L19 -> #DIV/0! | M58: =+N45/M19 -> #DIV/0! | N58: =+O45/N19 -> #DIV/0!
B59: DIVIDEND YIELD PROM 3 AÑOS | C59: =AVERAGE(G58:I58) -> 0.069743591
B60: G | C60: =+C41*(100%-C56) -> 0.044474223 | D60: =+D41*(100%-D56) -> 0.013307321 | E60: =+E41*(100%-E56) -> 0.08792246 | F60: =+F41*(100%-F56) -> 0.02317885 | G60: =+G41*(100%-G56) -> 0.04006364 | H60: =+H41*(100%-H56) -> 0.012209257 | I60: =+I41*(100%-I56) -> 0.023390684 | J60: =+J41*(100%-J56) -> 0.029864178 | ... N60: =+N41*(100%-N56) -> #DIV/0!
B61: G PROMEDIO 3 AÑOS | C61: =AVERAGE(G60:I60) -> 0.025221194
B62: PRECIO | C62: =B3 -> 3940
B64: ESTADO DE SITUACIÓN (BALANCE)
B66: AÑOS | C66: 2017 | D66: 2018 | E66: 2019 | F66: 2020 | G66: 2021 | H66: 2022 | I66: 2023 | J66: 2024 | K66: 2025 | L66: 2026 | M66: 2027 | N66: 2028
B67: ACTIVOS
B68: CORRIENTES (CIRCULANTES) | C68: 484010050000 | D68: 481586454000 | E68: 533474103000 | F68: 797297716000 | G68: 990986123000 | H68: 1161729392000 | I68: 981771027000 | J68: 1013195740000 | K68: 1033052781000
B69: Efectivo y equivalentes al efectivo | C69: 136242116000 | D69: 137538613000 | E69: 157567986000 | F69: 309530699000 | G69: 304312020000 | H69: 291681987000 | I69: 303683683000 | J69: 248899004000 | K69: 296539709000
B70: Otros activos financieros, corrientes | C70: 14138161000 | D70: 683567000 | E70: 347278000 | F70: 140304853000 | G70: 195470749000 | H70: 263044869000 | I70: 67285793000 | J70: 76586583000 | K70: 45974709000
B71: Otros activos no financieros, corrientes | C71: 5611861000 | D71: 5948923000 | E71: 16188965000 | F71: 13374381000 | G71: 14719104000 | H71: 26957000000 | I71: 19311851000 | J71: 27260507000 | K71: 15985896000
B72: Deudores comerciales y otras cuentas por cobrar, corrientes | C72: 191284680000 | D72: 174113323000 | E72: 191077588000 | F72: 194021253000 | G72: 265490626000 | H72: 279770286000 | I72: 298892164000 | J72: 332831088000 | K72: 339778498000
B73: Cuentas por cobrar entidades relacionadas, corriente neto | C73: 5370232000 | D73: 9450263000 | E73: 10835768000 | F73: 11875408000 | G73: 9419050000 | H73: 15062167000 | I73: 16161318000 | J73: 9901543000 | K73: 15299187000
B74: Inventarios, neto | C74: 131363000000 | D74: 151319709000 | E74: 147641224000 | F74: 127972650000 | G74: 191350206000 | H74: 245886656000 | I74: 233053160000 | J74: 299970909000 | K74: 304550609000
B75: Activos por impuestos corrientes | D75: 2532056000 | E75: 9815294000 | F75: 218472000 | G75: 10224368000 | H75: 39326427000 | I75: 43383058000 | J75: 17746106000 | K75: 14924173000
B76: OTROS CORRIENTES | C76: =+C68-C69-C74-C75-C73-C72-C71-C70 -> 0 | D76: =+D68-D69-D74-D75-D73-D72-D71-D70 -> 0 | E76: =+E68-E69-E74-E75-E73-E72-E71-E70 -> 0 | F76: =+F68-F69-F74-F75-F73-F72-F71-F70 -> 0 | G76: =+G68-G69-G74-G75-G73-G72-G71-G70 -> 0 | H76: =+H68-H69-H74-H75-H73-H72-H71-H70 -> 0 | I76: =+I68-I69-I74-I75-I73-I72-I71-I70 -> 0 | J76: =+J68-J69-J74-J75-J73-J72-J71-J70 -> 0 | ... N76: =+N68-N69-N74-N75-N73-N72-N71-N70 -> 0
B77: NO CORRIENTES (NO CIRCULANTES) | C77: 1630849417000 | D77: 1732918235000 | E77: 1857474320000 | F77: 1650766684000 | G77: 1955120524000 | H77: 1848971215000 | I77: 1939749862000 | J77: 2277908533000 | K77: 2387352637000
B78: Otros activos financieros, no corrientes | C78: 74259085000 | D78: 97362295000 | E78: 110784311000 | F78: 162013278000 | G78: 296632012000 | H78: 94852711000 | I78: 93316339000 | J78: 169420303000 | K78: 164370936000
B79: Otros activos no financieros, no corrientes | C79: 47394345000 | D79: 34977264000 | E79: 125636150000 | F79: 90242672000 | G79: 70861616000 | H79: 59672266000 | I79: 59412482000 | J79: 79746695000 | K79: 82913107000
B80: Cuentas por cobrar | C80: 2395851000 | D80: 1270697000 | E80: 523769000 | F80: 73862000 | G80: 126464000 | H80: 539920000 | I80: 371401000 | J80: 335723000 | K80: 187644000
B81: Cuentas por cobrar a entidades relacionadas | C81: 156492000 | D81: 74340000 | E81: 283118000 | F81: 138346000 | G81: 98941000 | H81: 109318000 | I81: 108021000 | J81: 292931000 | K81: 8000924000
B82: Inversiones contabilizadas utilizando el método de la participación | C82: 86809069000 | D82: 102410945000 | E82: 99866733000 | F82: 87956354000 | G82: 91489194000 | H82: 92344598000 | I82: 91799267000 | J82: 85192710000 | K82: 87087871000
B83: Activos Intangibles distintos de plusvalía | C83: 663272878000 | D83: 668822553000 | E83: 675075375000 | F83: 604514165000 | G83: 659631543000 | H83: 671778888000 | I83: 695926565000 | J83: 693383630000 | K83: 719489720000
B84: Plusvalía | C84: 93598217000 | D84: 117229173000 | E84: 121221661000 | F84: 98325593000 | G84: 118042900000 | H84: 129023922000 | I84: 122103802000 | J84: 144681420000 | K84: 137128318000
B85: Propiedades, plantas y equipos | C85: 659750499000 | D85: 710770968000 | E85: 722718863000 | F85: 605576545000 | G85: 716379127000 | H85: 798221259000 | I85: 872388811000 | J85: 1097773572000 | K85: 1179385259000
B86: Activos por impuestos diferidos, no corrientes | C86: 3212981000 | D86: 0 | E86: 1364340000 | F86: 1925869000 | G86: 1858727000 | H86: 2428333000 | I86: 4323174000 | J86: 7081549000 | K86: 8788858000
B87: OTROS NO CORRIENTES | C87: =+C77-C84-C85-C83-C78-C86-C82-C81-C80-C79 -> 0 | D87: =+D77-D84-D85-D83-D78-D86-D82-D81-D80-D79 -> 0 | E87: =+E77-E84-E85-E83-E78-E86-E82-E81-E80-E79 -> 0 | F87: =+F77-F84-F85-F83-F78-F86-F82-F81-F80-F79 -> 0 | G87: =+G77-G84-G85-G83-G78-G86-G82-G81-G80-G79 -> 0 | H87: =+H77-H84-H85-H83-H78-H86-H82-H81-H80-H79 -> 0 | I87: =+I77-I84-I85-I83-I78-I86-I82-I81-I80-I79 -> 0 | J87: =+J77-J84-J85-J83-J78-J86-J82-J81-J80-J79 -> 0 | K87: $ - | L87: =+L77-L84-L85-L83-L78-L86-L82-L81-L80-L79 -> 0 | M87: =+M77-M84-M85-M83-M78-M86-M82-M81-M80-M79 -> 0 | N87: =+N77-N84-N85-N83-N78-N86-N82-N81-N80-N79 -> 0
B88: TOTAL ACTIVOS | C88: =+C77+C68 -> 2114859467000 | D88: =+D77+D68 -> 2214504689000 | E88: =+E77+E68 -> 2390948423000 | F88: =+F77+F68 -> 2448064400000 | G88: =+G77+G68 -> 2946106647000 | H88: =+H77+H68 -> 3010700607000 | I88: =+I77+I68 -> 2921520889000 | J88: =+J77+J68 -> 3291104273000 | ... N88: =+N77+N68 -> 0
B90: PASIVOS
B91: CORRIENTES (CIRCULANTES) | C91: 428287322000 | D91: 419862101000 | E91: 411658352000 | F91: 378056186000 | G91: 529567279000 | H91: 949245134000 | I91: 692871296000 | J91: 906143994000 | K91: 730412517000
B92: Otros pasivos financieros | C92: 67981405000 | D92: 56114977000 | E92: 40593878000 | F92: 38566724000 | G92: 47763039000 | H92: 367302080000 | I92: 52997001000 | J92: 110330460000 | K92: 62418990000
B93: Cuentas por pagar comerciales y otras cuentas por pagar | C93: 257519477000 | D93: 238109847000 | E93: 243700553000 | F93: 230445809000 | G93: 327409207000 | H93: 384801630000 | I93: 428911984000 | J93: 457074643000 | K93: 480396027000
B94: Cuenetas por pagar a entidades relacionadas | C94: 33961437000 | D94: 45827859000 | E94: 53637601000 | F94: 39541968000 | G94: 56103461000 | H94: 90248067000 | I94: 96045624000 | J94: 94376420000 | K94: 102102553000
B95: Otras provisiones | C95: 2676418000 | D95: 3485613000 | E95: 2068984000 | F95: 1335337000 | G95: 1528879000 | H95: 1591644000 | I95: 1314106000 | J95: 1522426000 | K95: 2433147000
B96: Pasivos por impuestos | C96: 3184965000 | D96: 9338612000 | E96: 6762267000 | F96: 8828599000 | G96: 30512787000 | H96: 14615447000 | I96: 13411621000 | J96: 28369276000 | K96: 14207862000
B97: Provisiones corrientes por beneficios a los empleados | C97: 35955643000 | D97: 33210979000 | E97: 38392854000 | F97: 31071019000 | G97: 35012072000 | H97: 48391806000 | I97: 57817800000 | J97: 72367187000 | K97: 68363971000
B98: Otros pasivos no financieros | C98: 27007977000 | D98: 33774214000 | E98: 26502215000 | F98: 28266730000 | G98: 31237834000 | H98: 42294460000 | I98: 42373160000 | J98: 142103582000 | K98: 489967000
B100: Otros | C100: =+C91-C92-C98-C99-C97-C96-C95-C94-C93 -> 0 | D100: =+D91-D92-D98-D99-D97-D96-D95-D94-D93 -> 0 | E100: =+E91-E92-E98-E99-E97-E96-E95-E94-E93 -> 0 | F100: =+F91-F92-F98-F99-F97-F96-F95-F94-F93 -> 0 | G100: =+G91-G92-G98-G99-G97-G96-G95-G94-G93 -> 0 | H100: =+H91-H92-H98-H99-H97-H96-H95-H94-H93 -> 0 | I100: =+I91-I92-I98-I99-I97-I96-I95-I94-I93 -> 0 | J100: =+J91-J92-J98-J99-J97-J96-J95-J94-J93 -> 0 | ... N100: =+N91-N92-N98-N99-N97-N96-N95-N94-N93 -> 0
B101: NO CORRIENTES (NO CIRCULANTES) | C101: 873338796000 | D101: 930927845000 | E101: 1010386123000 | F101: 1238447623000 | G101: 1315125809000 | H101: 1178052821000 | I101: 1307664179000 | J101: 1370563259000 | K101: 1493439053000
B102: Otros pasivos financieros | C102: 675767201000 | D102: 716563778000 | E102: 743327057000 | F102: 989829569000 | G102: 1041048972000 | H102: 904802058000 | I102: 1044325833000 | J102: 1066543247000 | K102: 1191795823000
B103: Cuentas por pagar comerciales y otras cuentas por pagar | C103: 1132926000 | D103: 735665000 | E103: 619587000 | F103: 295279000 | G103: 256273000 | H103: 3015284000 | I103: 2392555000 | J103: 2534836000 | K103: 685605000
B104: Cuentas por pagar a entidades relacionadas | E104: 19777812000 | F104: 10790089000 | G104: 11557723000 | H104: 10354296000 | I104: 6007041000 | J104: 380465000 | K104: 0
B105: Otras provisiones | C105: 62947748000 | D105: 58966913000 | E105: 67038566000 | F105: 48734936000 | G105: 55883527000 | H105: 47103783000 | I105: 53487790000 | J105: 53723373000 | K105: 55378062000
B106: Pasivos por impuestos diferidos | C106: 125204566000 | D106: 145245948000 | E106: 169449747000 | F106: 153669547000 | G106: 168454827000 | H106: 165778556000 | I106: 180470219000 | J106: 224967885000 | K106: 218673311000
B107: Provisiones no corrientes por beneficios a los empleados | C107: 8286355000 | D107: 9415541000 | E107: 10173354000 | F107: 13635558000 | G107: 14139670000 | H107: 17409793000 | I107: 18473946000 | J107: 20160468000 | K107: 23123294000
B108: Otros pasivos no finacieros | F108: 21472048000 | G108: 23784817000 | H108: 29589051000 | I108: 2506795000 | J108: 2252985000 | K108: 3782958000
B109: OTROS | C109: =+C101-C102-C103-C104-C105-C106-C107-C108 -> 0 | D109: =+D101-D102-D103-D104-D105-D106-D107-D108 -> 0 | E109: =+E101-E102-E103-E104-E105-E106-E107-E108 -> 0 | F109: =+F101-F102-F103-F104-F105-F106-F107-F108 -> 20597000 | G109: =+G101-G102-G103-G104-G105-G106-G107-G108 -> 0 | H109: =+H101-H102-H103-H104-H105-H106-H107-H108 -> 0 | I109: =+I101-I102-I103-I104-I105-I106-I107-I108 -> 0 | J109: =+J101-J102-J103-J104-J105-J106-J107-J108 -> 0 | ... N109: =+N101-N102-N103-N104-N105-N106-N107-N108 -> 0
B110: TOTAL PASIVOS | C110: =+C101+C91 -> 1301626118000 | D110: =+D101+D91 -> 1350789946000 | E110: =+E101+E91 -> 1422044475000 | F110: =+F101+F91 -> 1616503809000 | G110: =+G101+G91 -> 1844693088000 | H110: =+H101+H91 -> 2127297955000 | I110: =+I101+I91 -> 2000535475000 | J110: =+J101+J91 -> 2276707253000 | ... N110: =+N101+N91 -> 0
...

Sheet BANVIDA
B2: =+TODAY()-1 -> 46105 | D2: PROM DIV SIN ADIC/EVENT | E2: PROM DIV TOTALES
B3: {=_FV(B6,"Precio")} -> 720.08 | D3: =AVERAGE(G40:I40) -> 31.239 | E3: =AVERAGE(G39:J39) -> 33.98925
B6: #VALUE! | C6: 2017 | D6: 2018 | E6: 2019 | F6: 2020 | G6: 2021 | H6: 2022 | I6: 2023 | J6: 2024 | K6: 2025 | L6: 2026 | M6: 2027 | N6: 2028
B7: Activos corrientes | C7: =+C54 -> 31220069000 | D7: =+D54 -> 17142083000 | E7: =+E54 -> 21176416000 | F7: =+F54 -> 34040424000 | G7: =+G54 -> 30956769000 | H7: =+H54 -> 15681171000 | I7: =+I54 -> 22482787000 | J7: =+J54 -> 34518349000 | ... N7: =+N54 -> 0
B8: Activos no corrientes | C8: =+C58 -> 450331646000 | D8: =+D58 -> 431214357000 | E8: =+E58 -> 487901066000 | F8: =+F58 -> 538160661000 | G8: =+G58 -> 516689139000 | H8: =+H58 -> 612677495000 | I8: =+I58 -> 654316308000 | J8: =+J58 -> 683319047000 | ... N8: =+N58 -> 0
B9: Total Activos | C9: =SUM(C7:C8) -> 481551715000 | D9: =SUM(D7:D8) -> 448356440000 | E9: =SUM(E7:E8) -> 509077482000 | F9: =SUM(F7:F8) -> 572201085000 | G9: =SUM(G7:G8) -> 547645908000 | H9: =SUM(H7:H8) -> 628358666000 | I9: =SUM(I7:I8) -> 676799095000 | J9: =SUM(J7:J8) -> 717837396000 | ... N9: =SUM(N7:N8) -> 0
B10: Pasivos corrientes | C10: =+C63 -> 25364065000 | D10: =+D63 -> 9300309000 | E10: =+E63 -> 45840675000 | F10: =+F63 -> 25611305000 | G10: =+G63 -> 19989200000 | H10: =+H63 -> 7762295000 | I10: =+I63 -> 15047436000 | J10: =+J63 -> 27590125000 | ... N10: =+N63 -> 0
B11: Pasivos no corrientes | C11: =+C67 -> 61635722000 | D11: =+D67 -> 63401317000 | E11: =+E67 -> 65112862000 | F11: =+F67 -> 66861759000 | G11: =+G67 -> 71281002000 | H11: =+H67 -> 80755254000 | I11: =+I67 -> 77036919000 | J11: =+J67 -> 77673831000 | ... N11: =+N67 -> 0
B12: Total Pasivos | C12: =+C69 -> 86999787000 | D12: =+D69 -> 72701626000 | E12: =+E69 -> 110953537000 | F12: =+F69 -> 92473064000 | G12: =+G69 -> 91270202000 | H12: =+H69 -> 88517549000 | I12: =+I69 -> 92084355000 | J12: =+J69 -> 105263956000 | ... N12: =+N69 -> 0
B13: Patrimonio | C13: =+C78 -> 394551928000 | D13: =+D78 -> 375654814000 | E13: =+E78 -> 398123945000 | F13: =+F78 -> 479728021000 | G13: =+G78 -> 456375706000 | H13: =+H78 -> 539841117000 | I13: =+I78 -> 584715140000 | J13: =+J78 -> 612573440000 | ... N13: =+N78 -> 0
B14: Cantidad de acciones | C14: 1430000000 | D14: 1430000000 | E14: 1430000000 | F14: 1600065708 | G14: 1600065708 | H14: 1600065708 | I14: 1600065708 | J14: 1600065708
B16: Valor libro | C16: =(C13/C14) -> 275.91044 | D16: =(D13/D14) -> 262.69567 | E16: =(E13/E14) -> 278.40835 | F16: =(F13/F14) -> 299.8177 | G16: =(G13/G14) -> 285.2231 | H16: =(H13/H14) -> 337.38684 | I16: =(I13/I14) -> 365.43196 | J16: =(J13/J14) -> 382.84268 | ... N16: =(N13/N14) -> #DIV/0!
B17: Precio al FIN AÑO | C17: 279.43 | D17: 470.82 | E17: 237.66 | F17: 257.19 | G17: 258.16 | H17: 303 | I17: 381.72
B18: PER | C18: =+C17/C35 -> 4.770943 | D18: =+D17/D35 -> 22.207493 | E18: =+E17/E35 -> 8.6454164 | F18: =+F17/F35 -> 4.8620966 | G18: =+G17/G35 -> 3.0591111 | H18: =+H17/H35 -> 4.4031598 | I18: =+I17/I35 -> 5.5950901 | J18: =+J17/J35 -> 0 | ... N18: =+N17/N35 -> #DIV/0!
B19: Bolsa Libro | C19: =+C17/C16 -> 1.0127562 | D19: =+D17/D16 -> 1.792264 | E19: =+E17/E16 -> 0.85363818 | F19: =+F17/F16 -> 0.85782127 | G19: =+G17/G16 -> 0.90511602 | H19: =+H17/H16 -> 0.89807889 | I19: =+I17/I16 -> 1.044572 | J19: =+J17/J16 -> 0 | ... N19: =+N17/N16 -> #DIV/0!
B20: GRAHAM | C20: =+C18*C19 -> 4.831802 | D20: =+D18*D19 -> 39.80169 | E20: =+E18*E19 -> 7.3800575 | F20: =+F18*F19 -> 4.1708099 | G20: =+G18*G19 -> 2.7688505 | H20: =+H18*H19 -> 3.9543848 | I20: =+I18*I19 -> 5.8444746 | J20: =+J18*J19 -> 0 | ... N20: =+N18*N19 -> #DIV/0!
B21: Bolsa Libro Banda Menor | C21: 2 | D21: 2 | E21: 2 | F21: 2 | G21: 2 | H21: 2 | I21: 2
B22: Bolsa Libro Banda Mayor | C22: 2.5 | D22: 2.5 | E22: 2.5 | F22: 2.5 | G22: 2.5 | H22: 2.5 | I22: 2.5
B23: Precio Objetivo Menor | C23: =+C21*C16 -> 551.82088 | D23: =+D21*D16 -> 525.39135 | E23: =+E21*E16 -> 556.81671 | F23: =+F21*F16 -> 599.6354 | G23: =+G21*G16 -> 570.44621 | H23: =+H21*H16 -> 674.77368 | I23: =+I21*I16 -> 730.86391 | J23: =+J21*J16 -> 0 | ... N23: =+N21*N16 -> #DIV/0!
B24: Precio Obejtivo Promedio | C24: =AVERAGE(C23,C25) -> 620.79849 | D24: =AVERAGE(D23,D25) -> 591.06527 | E24: =AVERAGE(E23,E25) -> 626.41879 | F24: =AVERAGE(F23,F25) -> 674.58983 | G24: =AVERAGE(G23,G25) -> 641.75198 | H24: =AVERAGE(H23,H25) -> 759.1204 | I24: =AVERAGE(I23,I25) -> 822.2219 | J24: =AVERAGE(J23,J25) -> 0 | ... N24: =AVERAGE(N23,N25) -> #DIV/0!
B25: Precio Objetivo Mayor | C25: =+C16*C22 -> 689.7761 | D25: =+D16*D22 -> 656.73919 | E25: =+E16*E22 -> 696.02088 | F25: =+F16*F22 -> 749.54425 | G25: =+G16*G22 -> 713.05776 | H25: =+H16*H22 -> 843.46711 | I25: =+I16*I22 -> 913.57989 | J25: =+J16*J22 -> 0 | ... N25: =+N16*N22 -> #DIV/0!
B27: Capital de Trabajo | C27: =C7-C10 -> 5856004000 | D27: =D7-D10 -> 7841774000 | E27: =E7-E10 -> -24664259000 | F27: =F7-F10 -> 8429119000 | G27: =G7-G10 -> 10967569000 | H27: =H7-H10 -> 7918876000 | I27: =I7-I10 -> 7435351000 | J27: =J7-J10 -> 6928224000 | ... N27: =N7-N10 -> 0
B28: Razón corriente | C28: =C7/C10 -> 1.230878 | D28: =D7/D10 -> 1.8431735 | E28: =E7/E10 -> 0.4619569 | F28: =F7/F10 -> 1.3291171 | G28: =G7/G10 -> 1.5486747 | H28: =H7/H10 -> 2.020172 | I28: =I7/I10 -> 1.4941274 | J28: =J7/J10 -> 1.2511125 | ... N28: =N7/N10 -> #DIV/0!
B29: Razón ácida | C29: =+(C7)/C10 -> 1.230878 | D29: =+(D7)/D10 -> 1.8431735 | E29: =+(E7)/E10 -> 0.4619569 | F29: =+(F7)/F10 -> 1.3291171 | G29: =+(G7)/G10 -> 1.5486747 | H29: =+(H7)/H10 -> 2.020172 | I29: =+(I7)/I10 -> 1.4941274 | J29: =+(J7)/J10 -> 1.2511125 | ... N29: =+(N7)/N10 -> #DIV/0!
B30: Razón de endeudamiento | C30: =C12/C9 -> 0.18066551 | D30: =D12/D9 -> 0.1621514 | E30: =E12/E9 -> 0.2179502 | F30: =F12/F9 -> 0.16160938 | G30: =G12/G9 -> 0.16665915 | H30: =H12/H9 -> 0.14087106 | I30: =I12/I9 -> 0.13605863 | J30: =J12/J9 -> 0.14664039 | ... N30: =N12/N9 -> #DIV/0!
B32: Ingresos | C32: =+C82 -> 0 | D32: =+D82 -> 0 | E32: =+E82 -> 0 | F32: =+F82 -> 0 | G32: =+G82 -> 0 | H32: =+H82 -> 0 | I32: =+I82 -> 0 | J32: =+J82 -> 0 | ... N32: =+N82 -> 0
B33: EBITDA | C33: =+C86 -> -455164000 | D33: =+D86 -> -602945000 | E33: =+E86 -> -627613000 | F33: =+F86 -> -785026000 | G33: =+G86 -> -652185000 | H33: =+H86 -> -700840000 | I33: =+I86 -> -944074000 | J33: =+J86 -> -277924000
B34: Utilidad neta | C34: =+C94 -> 83753861000 | D34: =+D94 -> 30317362000 | E34: =+E94 -> 39310287000 | F34: =+F94 -> 84638569000 | G34: =+G94 -> 135030389000 | H34: =+H94 -> 110107272000 | I34: =+I94 -> 109163047000 | J34: =+J94 -> 39253894000 | ... N34: =+N94 -> 0
B35: EPS | C35: =+C95 -> 58.569134 | D35: =+D95 -> 21.200952 | E35: =+E95 -> 27.489711 | F35: =+F95 -> 52.896933 | G35: =+G95 -> 84.390527 | H35: =+H95 -> 68.814219 | I35: =+I95 -> 68.224103 | J35: =+J95 -> 24.532676 | ... N35: =+N95 -> 0
B36: ROE | C36: =C34/C13 -> 0.21227589 | D36: =D34/D13 -> 0.080705373 | E36: =E34/E13 -> 0.098738816 | F36: =F34/F13 -> 0.17643032 | G36: =G34/G13 -> 0.2958755 | H36: =H34/H13 -> 0.20396237 | I36: =I34/I13 -> 0.18669441 | J36: =J34/J13 -> 0.064080307 | ... N36: =N34/N13 -> #DIV/0!
B37: ROE PROMEDIO (últimos 3 años) | C37: =AVERAGE(G36:I36) -> 0.22884409
B38: FCF | C38: =+C110 -> 3947927000 | D38: =+D110 -> 4526234000 | E38: =+E110 -> 3206616000 | F38: =+F110 -> 2622088000 | G38: =+G110 -> 4590222000 | H38: =+H110 -> 34938338000 | I38: =+I110 -> 6628611000 | J38: =+J110 -> -408731000 | ... N38: =+N110 -> 0
B39: Dividendos | C39: =SUM(C41:C44) -> 17.5 | D39: =SUM(D41:D44) -> 29.7 | E39: =SUM(E41:E44) -> 12 | F39: =SUM(F41:F44) -> 8.25 | G39: =SUM(G41:G44) -> 59.78 | H39: =SUM(H41:H44) -> 28.317 | I39: =SUM(I41:I44) -> 36.53 | J39: =SUM(J41:J44) -> 11.33 | ... N39: =SUM(N41:N44) -> 0
B40: Dividendos sin Adic/Event | C40: =+C39-C43-C44 -> 13.97 | D40: =+D39-D43-D44 -> 29.7 | E40: =+E39-E43-E44 -> 12 | F40: =+F39-F43-F44 -> 8.25 | G40: =+G39-G43-G44 -> 28.87 | H40: =+H39-H43-H44 -> 28.317 | I40: =+I39-I43-I44 -> 36.53 | J40: =+J39-J43-J44 -> 11.33 | ... N40: =+N39-N43-N44 -> 0
B41: Definitivo | C41: 13.97 | D41: 29.7 | E41: 12 | F41: 8.25 | G41: 15.87 | H41: 12.317 | I41: 22.8 | J41: 11.33
B42: Provisorio | G42: 13 | H42: 16 | I42: 13.73
B43: Eventual | G43: 18
B44: Adicional | C44: 3.53 | G44: 12.91
B45: PAY OUT | C45: =(SUM(C42:C44)+D41)/C35 -> 0.56736369 | D45: =(SUM(D42:D44)+E41)/D35 -> 0.56601231 | E45: =(SUM(E42:E44)+F41)/E35 -> 0.30011228 | F45: =(SUM(F42:F44)+G41)/F35 -> 0.30001739 | G45: =(SUM(G42:G44)+H41)/G35 -> 0.66627146 | H45: =(SUM(H42:H44)+I41)/H35 -> 0.56383696 | I45: =(SUM(I42:I44)+J41)/I35 -> 0.36731887 | J45: =(SUM(J42:J44)+K41)/J35 -> 0 | ... N45: =(SUM(N42:N44)+O41)/N35 -> #DIV/0!
B46: PAY OUT PROMEDIO 3 AÑOS | C46: =AVERAGE(G45:I45) -> 0.53247576
B47: DIVIDEND YIELD AÑO | C47: =+C39/C17 -> 0.062627492 | D47: =+D39/D17 -> 0.063081432 | E47: =+E39/E17 -> 0.0504923 | F47: =+F39/F17 -> 0.032077452 | G47: =+G39/G17 -> 0.23156182 | H47: =+H39/H17 -> 0.093455446 | I47: =+I39/I17 -> 0.095698418 | J47: =+J39/J17 -> #DIV/0! | ... N47: =+N39/N17 -> #DIV/0!
B48: DIVIDEND YELD PROMEDIO 3 AÑOS | C48: =AVERAGE(G47:I47) -> 0.14023856
B49: G | C49: =+C36*(100%-C45) -> 0.091838256 | D49: =+D36*(100%-D45) -> 0.035025139 | E49: =+E36*(100%-E45) -> 0.069106085 | F49: =+F36*(100%-F45) -> 0.12349816 | G49: =+G36*(100%-G45) -> 0.098742097 | H49: =+H36*(100%-H45) -> 0.088960846 | I49: =+I36*(100%-I45) -> 0.11811803 | J49: =+J36*(100%-J45) -> 0.064080307 | ... N49: =+N36*(100%-N45) -> #DIV/0!
B50: G PROMEDIO 3 AÑOS | C50: =AVERAGE(G49:I49) -> 0.10194032
B52: ESTADO DE SITUACIÓN (BALANCE)
B53: ACTIVOS | C53: =+C6 -> 2017 | D53: =+D6 -> 2018 | E53: =+E6 -> 2019 | F53: =+F6 -> 2020 | G53: =+G6 -> 2021 | H53: =+H6 -> 2022 | I53: 2023 | J53: =+J6 -> 2024 | K53: 2024 | L53: =+L6 -> 2026 | M53: 2025 | N53: =+N6 -> 2028
B54: TOTAL ACTIVOS CORRIENTES | C54: 31220069000 | D54: 17142083000 | E54: 21176416000 | F54: 34040424000 | G54: 30956769000 | H54: 15681171000 | I54: 22482787000 | J54: 34518349000
B55: Efectivo y equivalentes al efectivo | C55: 4700797000 | D55: 6825982000 | E55: 7748537000 | F55: 7354859000 | G55: 8831082000 | H55: 8630533000 | I55: 9535528000 | J55: 9308546000
B56: Cuentas por cobrar a entidades relacionadas | C56: 26289555000 | D56: 10131653000 | E56: 13256518000 | F56: 26526311000 | G56: 21957115000 | H56: 6907210000 | I56: 12812623000 | J56: 25079093000
B57: Otros activos circulantes | C57: =+C54-C55-C56 -> 229717000 | D57: =+D54-D55-D56 -> 184448000 | E57: =+E54-E55-E56 -> 171361000 | F57: =+F54-F55-F56 -> 159254000 | G57: =+G54-G55-G56 -> 168572000 | H57: =+H54-H55-H56 -> 143428000 | I57: =+I54-I55-I56 -> 134636000 | J57: =+J54-J55-J56 -> 130710000 | ... N57: =+N54-N55-N56 -> 0
B58: TOTAL ACTIVOS NO CORRIENTES | C58: 450331646000 | D58: 431214357000 | E58: 487901066000 | F58: 538160661000 | G58: 516689139000 | H58: 612677495000 | I58: 654316308000 | J58: 683319047000
B59: Inversiones contabilizadas por el método de la participación | C59: 450331646000 | D59: 431214357000 | E59: 487901066000 | F59: 538160661000 | G59: 516689139000 | H59: 612677495000 | I59: 654316308000 | J59: 683319047000
B60: TOTAL ACTIVOS | C60: =+C58+C54 -> 481551715000 | D60: =+D58+D54 -> 448356440000 | E60: =+E58+E54 -> 509077482000 | F60: =+F58+F54 -> 572201085000 | G60: =+G58+G54 -> 547645908000 | H60: =+H58+H54 -> 628358666000 | I60: =+I58+I54 -> 676799095000 | J60: =+J58+J54 -> 717837396000 | ... N60: =+N58+N54 -> 0
B62: PASIVOS
B63: TOTAL PASIVOS CORRIENTES | C63: 25364065000 | D63: 9300309000 | E63: 45840675000 | F63: 25611305000 | G63: 19989200000 | H63: 7762295000 | I63: 15047436000 | J63: 27590125000
B64: Otros pasivos financieros corrientes | C64: 110775000 | D64: 113949000 | E64: 33942941000 | F64: 120168000 | G64: 128111000 | H64: 145136000 | I64: 3940333000 | J64: 4838986000
B65: Cuentas por pagar comerciales y otras cuentas por pagar | C65: 25251210000 | D65: 9186360000 | E65: 11897734000 | F65: 25491137000 | G65: 19861089000 | H65: 7617159000 | I65: 11107103000 | J65: 22751139000
B66: Pasivos por impuestos corrientes | C66: 2080000 | D66: 0 | E66: 0 | F66: 0 | G66: 0 | H66: 0 | I66: 0 | J66: 0
B67: TOTAL PASIVOS NO CORRIENTES | C67: 61635722000 | D67: 63401317000 | E67: 65112862000 | F67: 66861759000 | G67: 71281002000 | H67: 80755254000 | I67: 77036919000 | J67: 77673831000
B68: Otros pasivos financieros no corrientes | C68: 61635722000 | D68: 63401317000 | E68: 65112862000 | F68: 66861759000 | G68: 71281002000 | H68: 80755254000 | I68: 77036919000 | J68: 77673831000
B69: TOTAL PASIVOS | C69: =+C67+C63 -> 86999787000 | D69: =+D67+D63 -> 72701626000 | E69: =+E67+E63 -> 110953537000 | F69: =+F67+F63 -> 92473064000 | G69: =+G67+G63 -> 91270202000 | H69: =+H67+H63 -> 88517549000 | I69: =+I67+I63 -> 92084355000 | J69: =+J67+J63 -> 105263956000 | ... N69: =+N67+N63 -> 0
B71: PATRIMONIO
B72: Capital emitido | C72: 88778486000 | D72: 88778486000 | E72: 88778486000 | F72: 122771220000 | G72: 122771220000 | H72: 122771220000 | I72: 122771220000 | J72: 122771220000
B73: Resultados acumulados | C73: 322255624000 | D73: 326134370000 | E73: 345586780000 | F73: 404829364000 | G73: 449891134000 | H73: 526961686000 | I73: 574325449000 | J73: 601803175000
B74: Primas de emisión | C74: 102578000 | D74: 102578000 | E74: 102578000 | F74: 102578000 | G74: 102578000 | H74: 102578000 | I74: 102578000 | J74: 102578000
B75: Otras Reservas | C75: -16584760000 | D75: -39360620000 | E75: -36343899000 | F75: -47975141000 | G75: -116389226000 | H75: -109994367000 | I75: -112484107000 | J75: -112103533000
B76: Patrimonio atribuible a los propietarios de la controladora | C76: =+SUM(C72:C75) -> 394551928000 | D76: =+SUM(D72:D75) -> 375654814000 | E76: =+SUM(E72:E75) -> 398123945000 | F76: =+SUM(F72:F75) -> 479728021000 | G76: =+SUM(G72:G75) -> 456375706000 | H76: =+SUM(H72:H75) -> 539841117000 | I76: =+SUM(I72:I75) -> 584715140000 | J76: =+SUM(J72:J75) -> 612573440000 | ... N76: =+SUM(N72:N75) -> 0
B77: Participaciones no controladoras | C77: 0 | D77: 0 | E77: 0 | F77: 0 | G77: 0 | H77: 0 | I77: 0 | J77: 0
B78: TOTAL PATRIMONIO | C78: =+C76+C77 -> 394551928000 | D78: =+D76+D77 -> 375654814000 | E78: =+E76+E77 -> 398123945000 | F78: =+F76+F77 -> 479728021000 | G78: =+G76+G77 -> 456375706000 | H78: =+H76+H77 -> 539841117000 | I78: =+I76+I77 -> 584715140000 | J78: =+J76+J77 -> 612573440000 | K78: =+K72+K77+K75 -> 0 | L78: =+L72+L77+L75 -> 0 | M78: =+M72+M77+M75 -> 0 | N78: =+N72+N77+N75 -> 0
B80: ESTADO DE RESULTADOS
B81: AÑOS | C81: 2017 | D81: 2018 | E81: 2019 | F81: 2020 | G81: 2021 | H81: 2022 | I81: 2023 | J81: 2024 | K81: 2025 | L81: 2026 | M81: 2027 | N81: 2028
B82: Ingresos por ventas (Ingresos de actividades ordinarias) | C82: 0 | D82: 0 | E82: 0 | F82: 0 | G82: 0 | H82: 0 | I82: 0 | J82: 0
B83: Costo de ventas | C83: 0 | D83: 0 | E83: 0 | F83: 0 | G83: 0 | H83: 0 | I83: 0 | J83: 0
B84: GANANCIA BRUTA | C84: =+SUM(C82:C83) -> 0 | D84: =+SUM(D82:D83) -> 0 | E84: =+SUM(E82:E83) -> 0 | F84: =+SUM(F82:F83) -> 0 | G84: =+SUM(G82:G83) -> 0 | H84: =+SUM(H82:H83) -> 0 | I84: =+SUM(I82:I83) -> 0 | J84: =+SUM(J82:J83) -> 0 | ... N84: =+SUM(N82:N83) -> 0
B85: Gastos de administración | C85: -455164000 | D85: -602945000 | E85: -627613000 | F85: -785026000 | G85: -652185000 | H85: -700840000 | I85: -944074000 | J85: -277924000
B86: RESULTADO OPERACIONAL (EBITDA) | C86: =+C84+C85 -> -455164000 | D86: =+D84+D85 -> -602945000 | E86: =+E84+E85 -> -627613000 | F86: =+F84+F85 -> -785026000 | G86: =+G84+G85 -> -652185000 | H86: =+H84+H85 -> -700840000 | I86: =+I84+I85 -> -944074000 | J86: =+J84+J85 -> -277924000 | ... N86: =+N84+N85 -> 0
A87: Ingresos financieros | B87: Ingresos financieros | C87: 165631000 | D87: 214205000 | E87: 277373000 | F87: 249467000 | G87: 28770000 | H87: 0 | I87: 0 | J87: 0
B88: Costos financieros | C88: -2545419000 | D88: -2621440000 | E88: -2686615000 | F88: -3440991000 | G88: -3142491000 | H88: -1755895000 | I88: -2011185000 | J88: -688178000
B89: Participación en ganancia (pérdida) de asociadas y negocios conjuntos contabilizadas por método de participación | C89: 87631849000 | D89: 33772179000 | E89: 44188393000 | F89: 88421038000 | G89: 143229036000 | H89: 121297967000 | I89: 115964962000 | J89: 40888236000
B90: Resultados por unidades de reajuste | C90: -1035926000 | D90: -1765595000 | E90: -1827888000 | F90: -1753901000 | G90: -4432741000 | H90: -9485042000 | I90: -3846656000 | J90: -668240000
B91: Otros ingresos | C91: 0 | D91: 1322378000 | E91: 17915000 | F91: 1947982000 | G91: 0 | H91: 0 | I91: 0 | J91: 0
B92: GANANCIA ANTES DE IMPUESTOS | C92: =SUM(C87:C91)+C86 -> 83760971000 | D92: =SUM(D87:D91)+D86 -> 30318782000 | E92: =SUM(E87:E91)+E86 -> 39341565000 | F92: =SUM(F87:F91)+F86 -> 84638569000 | G92: =SUM(G87:G91)+G86 -> 135030389000 | H92: =SUM(H87:H91)+H86 -> 109356190000 | I92: =SUM(I87:I91)+I86 -> 109163047000 | J92: =SUM(J87:J90)+J86 -> 39253894000 | K92: =SUM(K87:K90)+K86 -> 0 | L92: =SUM(L87:L90)+L86 -> 0 | M92: =SUM(M87:M90)+M86 -> 0 | N92: =SUM(N87:N90)+N86 -> 0
B93: Impuestos | C93: -7110000 | D93: -1420000 | E93: -31278000 | F93: 0 | G93: 0 | H93: 751082000 | I93: 0
B94: GANANCIA (PÉRDIDA) | C94: =+C92+C93 -> 83753861000 | D94: =+D92+D93 -> 30317362000 | E94: =+E92+E93 -> 39310287000 | F94: =+F92+F93 -> 84638569000 | G94: =+G92+G93 -> 135030389000 | H94: =+H92+H93 -> 110107272000 | I94: =+I92+I93 -> 109163047000 | J94: =+J92+J93 -> 39253894000
B95: GANANCIA (PÉRDIDA) por acción | C95: =+C94/C14 -> 58.569134 | D95: =+D94/D14 -> 21.200952 | E95: =+E94/E14 -> 27.489711 | F95: =+F94/F14 -> 52.896933 | G95: =+G94/G14 -> 84.390527 | H95: =+H94/H14 -> 68.814219 | I95: =+I94/I14 -> 68.224103 | J95: =+J94/J14 -> 24.532676
B98: ESTADO DE FLUJO DE EFECTIVO
B99: AÑOS | C99: 2017 | D99: 2018 | E99: 2019 | F99: 2020 | G99: 2021 | H99: 2022 | I99: 2023 | J99: 2024 | K99: 2025 | L99: 2026 | M99: 2027 | N99: 2028
B100: ACTIVIDADES DE OPERACIÓN (FLUJO OPERACIONAL) | C100: 3947927000 | D100: 4526234000 | E100: 3206616000 | F100: 2622088000 | G100: 4590222000 | H100: 34938338000 | I100: 6628611000 | J100: -408731000
B101: ACTIVIDADES DE INVERSIÓN (FLUJO DE INVERSIÓN) | C101: 165630000 | D101: 214205000 | E101: -33323271000 | F101: 247093000 | G101: -193105000 | H101: -35138887000 | I101: 1545344000 | J101: 182049000
B102: Compras de PP&E (CAPEX) | C102: 0 | D102: 0 | E102: 0 | F102: 0 | G102: 0 | H102: 0 | I102: 0
B103: ACTIVIDADES DE FINANCIAMIENTO | C103: -2530860000 | D103: -2615254000 | E103: 31039210000 | F103: -3262859000 | G103: -2920894000 | H103: 0 | I103: -7268960000 | J103: -300000
B104: Pagos por dividendos por la entidad que informa
B105: Intereses pagados | H105: 0
B106: Incremento (disminución) neto de efectivo y equivalentes al efectivo | C106: 1582697000 | D106: 2125185000 | E106: 922555000 | F106: -393678000 | G106: 1476223000 | H106: -200549000 | I106: 904995000 | J106: -226982000
B107: Efectivo y equivalentes al efectivo al inicio del período | C107: 3118100000 | D107: 4700797000 | E107: 6825982000 | F107: 7748537000 | G107: 7354859000 | H107: 8831082000 | I107: 8630533000 | J107: 9535528000
B108: FLUJO DE EFECTIVO DEL PERIODO | C108: =+C107+C106 -> 4700797000 | D108: =+D107+D106 -> 6825982000 | E108: =+E107+E106 -> 7748537000 | F108: =+F107+F106 -> 7354859000 | G108: =+G107+G106 -> 8831082000 | H108: =+H107+H106 -> 8630533000 | I108: =+I107+I106 -> 9535528000 | J108: =+J107+J106 -> 9308546000
B110: FREE CASH FLOW | C110: =+C100+C102+C105 -> 3947927000 | D110: =+D100+D102+D105 -> 4526234000 | E110: =+E100+E102+E105 -> 3206616000 | F110: =+F100+F102+F105 -> 2622088000 | G110: =+G100+G102+G105 -> 4590222000 | H110: =+H100+H102+H105 -> 34938338000 | I110: =+I100+I102+I105 -> 6628611000 | J110: =+J100+J102+J105 -> -408731000 | K110: =+K100+K102+K105 -> 0 | L110: =+L100-L102 -> 0 | M110: =+M100-M102 -> 0 | N110: =+N100-N102 -> 0

Sheet BCI
B2: =TODAY()-1 -> 46105 | D2: PROM DIVIDENDOS SIN ADIC/EVENT | E2: PROM DIVIDENDOS TOTALES
B3: {=_FV(B6,"Precio")} -> 60500 | D3: =AVERAGE(F17:H17) -> 1070 | E3: =AVERAGE(F17:H17) -> 1070
B6: #VALUE! | C6: 2018 | D6: 2019 | E6: 2020 | F6: 2021 | G6: 2022 | H6: 2023 | I6: 2024 | J6: 2025 | K6: 2026 | L6: 2027 | M6: 2028
B7: Activos totales | C7: 41349717 | D7: 50336620 | E7: 57156299 | F7: 69158634 | G7: 78049119 | H7: 79301153
B8: Pasivos Totales | C8: =C7-C9 -> 38169264 | D8: =D7-D9 -> 46826993 | E8: =E7-E9 -> 53478139 | F8: 64657158 | G8: 73272318 | H8: 73233777
B9: Patrimonio | C9: 3180453 | D9: 3509627 | E9: 3678160 | F9: 4500076 | G9: 4775478 | H9: 6065795
B10: Número de acciones | C10: 124944872 | D10: 135892980 | E10: 141616409 | F10: 148767940 | G10: 155886505 | H10: 168837345
B11: Precio fin de año | C11: 32132 | D11: 26422 | E11: 21776 | F11: 20363 | G11: 21609 | H11: 23850
B13: Ingresos totales | C13: 1318890 | D13: 1476269 | E13: 1378417 | F13: 1760758 | G13: 2699087 | H13: 2520329
B14: Resultado operacional | C14: 454613 | D14: 518538 | E14: 342556 | F14: 719738 | G14: 911903 | H14: 817975
B15: utilidad | C15: 395794 | D15: 402645 | E15: 317454 | F15: 520391 | G15: 820822 | H15: 682468
B16: utilidad por acción | C16: 3104 | D16: 3333 | E16: 1585 | F16: 3657 | G16: 5664
B17: Dividendo | C17: 1050 | D17: 1000 | E17: 1000 | F17: 700 | G17: 1010 | H17: 1500
B18: Pay out | D18: =D17/C16 -> 0.32216495 | E18: =E17/D16 -> 0.30003 | F18: =F17/E16 -> 0.44164038 | G18: =G17/F16 -> 0.27618266 | H18: =H17/G16 -> 0.26483051 | I18: =I17/H16 -> #DIV/0! | J18: =J17/I16 -> #DIV/0! | K18: =K17/J16 -> #DIV/0! | ... M18: =M17/L16 -> #DIV/0!
B19: PAY OUT PROMEDIO 3 AÑOS | C19: =AVERAGE(F18:H18) -> 0.32755118
E21: pandemia
B22: margen operacional | C22: =C14/C13 -> 0.34469364 | D22: =D14/D13 -> 0.35124899 | E22: =E14/E13 -> 0.24851406 | F22: =F14/F13 -> 0.408766 | G22: =G14/G13 -> 0.3378561 | H22: =H14/H13 -> 0.32455088 | I22: =I14/I13 -> #DIV/0! | J22: =J14/J13 -> #DIV/0! | ... M22: =M14/M13 -> #DIV/0!
B23: margen neto | C23: =C15/C13 -> 0.30009629 | D23: =D15/D13 -> 0.27274501 | E23: =E15/E13 -> 0.23030331 | F23: =F15/F13 -> 0.29554942 | G23: =G15/G13 -> 0.30411098 | H23: =H15/H13 -> 0.27078528 | I23: =I15/I13 -> #DIV/0! | J23: =J15/J13 -> #DIV/0! | ... M23: =M15/M13 -> #DIV/0!
B24: ROE | C24: =C15/C9 -> 0.12444579 | D24: =D15/D9 -> 0.11472587 | E24: =E15/E9 -> 0.086307828 | F24: =F15/F9 -> 0.11564049 | G24: =G15/G9 -> 0.17188269 | H24: =H15/H9 -> 0.11251089 | I24: =I15/I9 -> #DIV/0! | J24: =J15/J9 -> #DIV/0! | ... M24: =M15/M9 -> #DIV/0!
B25: ROE PROMEDIO | C25: =AVERAGE(F24:H24) -> 0.13334469
B26: G | D26: =D24*(100%-D18) -> 0.077765214 | E26: =E24*(100%-E18) -> 0.06041289 | F26: =F24*(100%-F18) -> 0.064568981 | G26: =G24*(100%-G18) -> 0.12441167 | H26: =H24*(100%-H18) -> 0.082714575 | I26: =I24*(100%-I18) -> #DIV/0! | J26: =J24*(100%-J18) -> #DIV/0! | K26: =K24*(100%-K18) -> #DIV/0! | ... M26: =M24*(100%-M18) -> #DIV/0!
B27: G PROMEDIO 3 AÑOS | C27: =AVERAGE(F26:H26) -> 0.090565075
B28: DIVIDEND YIELD | C28: =+C17/C11 -> 0.032677704 | D28: =+D17/D11 -> 0.037847249 | E28: =+E17/E11 -> 0.045922116 | F28: =+F17/F11 -> 0.034376074 | G28: =+G17/G11 -> 0.046739784 | H28: =+H17/H11 -> 0.062893082 | I28: =+I17/I11 -> #DIV/0! | J28: =+J17/J11 -> #DIV/0! | ... M28: =+M17/M11 -> #DIV/0!
B29: DIV YIELD PROM 3 AÑOS | C29: =AVERAGE(F28:H28) -> 0.04800298
C41: Valor inicial | D41: valor actual | E41: diuvidendos recibidos | F41: valor actual + div
C42: 36262052 | D42: 39617415 | E42: 1754276 | F42: =D42+E42 -> 41371691
D45: =F42/C42-1 -> 0.14090871

Sheet BESALCO (TIKR)
B2: =TODAY()-1 -> 46105 | D2: PROM DIVIDENDOS SIN EVENT | E2: PROM DIVIDENDOS TOTALES | G2: MULTIPLICADOR EEFF | H2: 1000000
B3: {=_FV(B6,"Precio")} -> 1270 | D3: =AVERAGE(C45:J45) -> 10.7445 | E3: =AVERAGE(C44:J44) -> 13.5125
B6: #VALUE! | C6: 2017 | D6: 2018 | E6: 2019 | F6: 2020 | G6: 2021 | H6: 2022 | I6: 2023 | J6: 2024 | K6: 2025 | L6: 2026 | M6: 2027 | N6: 2028
B7: Activos corrientes | C7: =+C61 -> 318305160000 | D7: =+D61 -> 344726600000 | E7: =+E61 -> 388093710000 | F7: =+F61 -> 406386500000 | G7: =+G61 -> 507352150000 | H7: =+H61 -> 584214540000 | I7: =+I61 -> 626565710000 | J7: =+J61 -> 0 | ... N7: =+N61 -> 0
B8: Cuentas por cobrar | C8: =+C65 -> 153751740000 | D8: =+D65 -> 149901950000 | E8: =+E65 -> 116486400000 | F8: =+F65 -> 1.3724539e+11 | G8: =+G65 -> 212202870000 | H8: =+H65 -> 2.7178448e+11 | I8: =+I65 -> 294080550000 | J8: =+J65 -> 0 | ... N8: =+N65 -> 0
B9: Inventario | C9: =+C67 -> 92638060000 | D9: =+D67 -> 115024140000 | E9: =+E67 -> 152919190000 | F9: =+F67 -> 153223650000 | G9: =+G67 -> 171087120000 | H9: =+H67 -> 163021620000 | I9: =+I67 -> 189280580000 | J9: =+J67 -> 0 | ... N9: =+N67 -> 0
B10: Acitvos no corrientes (no circulantes o fijos) | C10: =+C70 -> 301853810000 | D10: =+D70 -> 3.5366244e+11 | E10: =+E70 -> 3.885261e+11 | F10: =+F70 -> 3.8147429e+11 | G10: =+G70 -> 4.1808841e+11 | H10: =+H70 -> 4.4602104e+11 | I10: =+I70 -> 455211020000 | J10: =+J70 -> 0 | ... N10: =+N70 -> 0
B11: Activos totales | C11: =+C10+C7 -> 620158970000 | D11: =+D10+D7 -> 698389040000 | E11: =+E10+E7 -> 776619810000 | F11: =+F10+F7 -> 787860790000 | G11: =+G10+G7 -> 925440560000 | H11: =+H10+H7 -> 1030235580000 | I11: =+I10+I7 -> 1081776730000 | J11: =+J10+J7 -> 0 | ... N11: =+N10+N7 -> 0
B12: Pasivos corrientes | C12: =+C84 -> 242664760000 | D12: =+D84 -> 242682460000 | E12: =+E84 -> 269545310000 | F12: =+F84 -> 295586900000 | G12: =+G84 -> 420190150000 | H12: =+H84 -> 479492980000 | I12: =+I84 -> 501017700000 | J12: =+J84 -> 0 | ... N12: =+N84 -> 0
B13: Pasivos no corrientes | C13: =+C94 -> 1.7815521e+11 | D13: =+D94 -> 2.600033e+11 | E13: =+E94 -> 307654050000 | F13: =+F94 -> 291380030000 | G13: =+G94 -> 281903140000 | H13: =+H94 -> 285814250000 | I13: =+I94 -> 2.8504723e+11 | J13: =+J94 -> 0 | ... N13: =+N94 -> 0
B14: Total Pasivos | C14: =+C12+C13 -> 420819970000 | D14: =+D12+D13 -> 502685760000 | E14: =+E12+E13 -> 577199360000 | F14: =+F12+F13 -> 586966930000 | G14: =+G12+G13 -> 702093290000 | H14: =+H12+H13 -> 765307230000 | I14: =+I12+I13 -> 786064930000 | J14: =+J12+J13 -> 0 | ... N14: =+N12+N13 -> 0
B15: Patrimonio | C15: =+C108 -> 187213480000 | D15: =+D108 -> 184344530000 | E15: =+E108 -> 190822010000 | F15: =+F108 -> 193801140000 | G15: =+G108 -> 215813670000 | H15: =+H108 -> 253638630000 | I15: =+I108 -> 283002980000 | J15: =+J108 -> 0 | ... N15: =+N108 -> 0
B16: Cantidad de acciones | C16: 576172664 | D16: 576172664 | E16: 576172664 | F16: 576172664 | G16: 576172664 | H16: 576172664 | I16: 576172664
